Workbook

Sheet Summary
AB2: Deep Conditioner
B4: Product Matrix
B6: Product Classification | H6: Product Assessment | N6: Ingredient Sensitivity Flags | S6: Standards | X6: Usage & Recommendations
B7: SKU | C7: Brand | D7: Product Name | E7: Product Category | F7: Price | G7: Size | H7: Primary Focus | I7: Hold | J7: Porosity Suitability | K7: Density Suitability | L7: Climate Performance | M7: Build Up Risk | N7: Aloe | O7: Coconut | P7: Protein | Q7: Humectant heavy | R7: Butter/Oil Heavy | S7: CG Approved | T7: Silicone Free | U7: Sulfate Free | V7: Beginner Friendly | W7: Advanced User Product | X7: Best Used When | Y7: Not Ideal If | Z7: Hero Use Case | AA7: Pairs well with | AB7: Product Alternatives | AC7: Best Seller
B8: AIM-CLIC-237 | C8: As I Am | D8: =VLOOKUP(B8,'Shopify Catalog'!$A:$C,3,FALSE) -> As I Am Classic Leave In Conditioner | E8: Leave In | F8: =VLOOKUP(Summary!B8,'Shopify Catalog'!A:X,24,FALSE) -> 70 | H8: Moisture | I8: None | J8: All | K8: All | L8: Heat + Humidity | M8: No | N8: No | O8: No | P8: No | Q8: No | R8: No | S8: Yes | T8: Yes | U8: Yes | V8: Yes | W8: No | X8: Damp | AA8: Stylers | AB8: Treluxe Untie the Knot | AC8: No
B9: AIM-JBOHM-237 | C9: As I Am | D9: AS I AM Jamaican Black Castor Oil Hair Mask | E9: Deep Conditioner | F9: =VLOOKUP(Summary!B9,'Shopify Catalog'!A:X,24,FALSE) -> 75 | H9: Moisture | I9: None | J9: All | K9: All | L9: Heat + Humidity | M9: No | N9: No | O9: No | P9: No | Q9: No | R9: No | S9: Yes | T9: Yes | U9: Yes | V9: Yes | X9: Wet | AA9: Treatments | AB9: Camille Rose Algae Renew Deep Conditioning Mask | AC9: No
B10: AIM-DOLIC-237 | C10: As I Am | D10: =VLOOKUP(B10,'Shopify Catalog'!$A:$C,3,FALSE) -> As I Am Dry & Itchy Scalp Olive & Tea Tree Oil Leave in Conditioner | E10: Leave In | F10: =VLOOKUP(Summary!B10,'Shopify Catalog'!A:X,24,FALSE) -> 70 | H10: Scalp | I10: None | J10: All | K10: All | L10: Heat + Humidity | M10: No | N10: Yes | O10: Yes | P10: No | Q10: Yes | R10: Yes | S10: Yes | T10: Yes | U10: Yes | V10: No | X10: Wet | AA10: Stylers | AB10: Breahni Weightless Detangler | AC10: No
B11: AIM-DIOT-118 | C11: As I Am | D11: =VLOOKUP(B11,'Shopify Catalog'!$A:$C,3,FALSE) -> As I Am Dry & Itchy Scalp Care Olive & Tea Tree Oil Treatment | E11: Treatment | F11: =VLOOKUP(Summary!B11,'Shopify Catalog'!A:X,24,FALSE) -> 65 | H11: Scalp | I11: None | J11: High | K11: All | L11: Heat + Humidity | M11: No | N11: No | O11: Yes | P11: No | Q11: Yes | R11: Yes | S11: Yes | T11: Yes | U11: Yes | V11: No | X11: Dry | AA11: Stylers | AB11: Curls & Potions Chebula & Green Tea Herba lMint Hair & Scalp Oil | AC11: No
B12: AIM-DTCT-355 | C12: As I Am | D12: =VLOOKUP(B12,'Shopify Catalog'!$A:$C,3,FALSE) -> As I Am Dry & Itchy Scalp Care Olive & Tea Tree Conditioner | E12: Instant Conditioner | F12: =VLOOKUP(Summary!B12,'Shopify Catalog'!A:X,24,FALSE) -> 70 | H12: Scalp | I12: None | J12: High | K12: Thick | L12: Heat + Humidity | M12: No | N12: Yes | O12: Yes | P12: No | Q12: Yes | R12: Yes | S12: Yes | T12: Yes | U12: Yes | V12: No | X12: Wet | AA12: Hair Mask | AB12: Inahsi Soothing Mint Moisturizing Conditioner | AC12: No
B13: AIM-DOOS-355 | C13: As I Am | D13: =VLOOKUP(B13,'Shopify Catalog'!$A:$C,3,FALSE) -> As I Am Dry & Itchy Scalp Olive & Tea Tree Oil Shampoo | E13: Cleanser | F13: =VLOOKUP(Summary!B13,'Shopify Catalog'!A:X,24,FALSE) -> 70 | H13: Scalp | I13: None | J13: High | K13: All | L13: Heat + Humidity | M13: No | N13: Yes | O13: No | P13: No | Q13: Yes | R13: No | S13: Yes | T13: Yes | U13: Yes | V13: Yes | X13: Wet | AA13: Conditioners | AB13: Curls & Potions Chebe Scalp Length Retention Shampoo | AC13: No
B14: AIM-JBSP-237 | C14: As I Am | D14: =VLOOKUP(B14,'Shopify Catalog'!$A:$C,3,FALSE) -> As I Am JBCO Shampoo | E14: Cleanser | F14: =VLOOKUP(Summary!B14,'Shopify Catalog'!A:X,24,FALSE) -> 70 | H14: Moisture | I14: None | J14: High | K14: All | L14: Heat + Humidity | M14: No | N14: No | O14: No | P14: No | Q14: No | R14: Yes | S14: Yes | T14: Yes | U14: Yes | V14: Yes | X14: Wet | AA14: Conditioners | AB14: Camille Rose Rose Cleansing Milk | AC14: No
B15: AIM-CCW-473 | C15: As I Am | D15: =VLOOKUP(B15,'Shopify Catalog'!$A:$C,3,FALSE) -> As I Am Coconut CoWash | E15: Cleanser | F15: =VLOOKUP(Summary!B15,'Shopify Catalog'!A:X,24,FALSE) -> 70 | H15: Moisture | I15: None | J15: All | K15: All | L15: Heat + Humidity | M15: No | N15: No | O15: Yes | P15: No | Q15: No | R15: Yes | S15: Yes | T15: Yes | U15: Yes | V15: Yes | X15: Wet | AA15: Cleansers | AC15: No
B16: BRN-CDC-237 | C16: Breahni | D16: =VLOOKUP(B16,'Shopify Catalog'!$A:$C,3,FALSE) -> Breahni Curl Defining Cream | E16: Styler | F16: =VLOOKUP(Summary!B16,'Shopify Catalog'!A:X,24,FALSE) -> 85 | H16: Definition | I16: Soft | J16: High | K16: All | L16: Heat + Humidity | M16: No | N16: No | O16: No | P16: No | Q16: Yes | R16: No | S16: Yes | T16: Yes | U16: Yes | V16: Yes | X16: Damp | AA16: Leave In | AB16: Treluxe Curl Supreme 4-in-1 Hydrating Crème | AC16: No
B17: BRN-CDC-59 | C17: Breahni | D17: Breahni Curl Defining Cream | E17: Styler | F17: =VLOOKUP(Summary!B17,'Shopify Catalog'!A:X,24,FALSE) -> 35 | H17: Definition | I17: Soft | J17: High | K17: All | L17: Heat + Humidity | M17: No | N17: No | O17: No | P17: No | Q17: Yes | R17: No | S17: Yes | T17: Yes | U17: Yes | V17: Yes | X17: Damp | AA17: Leave In | AC17: No
B18: BRN-LSG-237 | C18: Breahni | D18: =VLOOKUP(B18,'Shopify Catalog'!$A:$C,3,FALSE) -> Breahni Light Styling Gel | E18: Styler | F18: =VLOOKUP(Summary!B18,'Shopify Catalog'!A:X,24,FALSE) -> 80 | H18: Definition | I18: Medium | J18: All | K18: Fine | L18: Heat + Humidity | M18: No | N18: No | O18: No | P18: No | Q18: No | R18: Yes | S18: Yes | T18: Yes | U18: Yes | V18: Yes | X18: Damp | AA18: Leave In | AB18: Ecoslay Orange Marmalade CuRL Definer | AC18: No
B19: BRN-LSG-59 | C19: Breahni | D19: Breahni Light Styling Gel | E19: Styler | F19: =VLOOKUP(Summary!B19,'Shopify Catalog'!A:X,24,FALSE) -> 35 | H19: Definition | I19: Medium | J19: All | K19: Fine | L19: Heat + Humidity | M19: No | N19: No | O19: No | P19: No | Q19: No | R19: Yes | S19: Yes | T19: Yes | U19: Yes | V19: Yes | X19: Damp | AA19: Leave In | AB19: Ecoslay Orange Marmalade CuRL Definer | AC19: No
B20: BRN-MOM-237 | C20: Breahni | D20: =VLOOKUP(B20,'Shopify Catalog'!$A:$C,3,FALSE) -> Breahni Moisture Milk | F20: =VLOOKUP(Summary!B20,'Shopify Catalog'!A:X,24,FALSE) -> 70 | H20: Moisture | I20: None | J20: All | K20: Fine | L20: Heat + Humidity | M20: No | N20: No | O20: No | P20: No | Q20: No | R20: Yes | S20: Yes | T20: Yes | U20: Yes | V20: Yes | X20: Damp | AA20: Leave In | AB20: Camille Rose Curl Love Moisture Milk | AC20: No
B21: BRN-MOM-59 | C21: Breahni | D21: Breahni Moisture Milk | F21: =VLOOKUP(Summary!B21,'Shopify Catalog'!A:X,24,FALSE) -> 30 | H21: Moisture | I21: None | J21: All | K21: Fine | L21: Heat + Humidity | M21: No | N21: No | O21: No | P21: No | Q21: No | R21: Yes | S21: Yes | T21: Yes | U21: Yes | V21: Yes | X21: Damp | AA21: Leave In | AB21: Camille Rose Curl Love Moisture Milk
B22: BRN-LIC-237 | C22: Breahni | D22: =VLOOKUP(B22,'Shopify Catalog'!$A:$C,3,FALSE) -> Breahni Leave In Conditioner | E22: Leave In | F22: =VLOOKUP(Summary!B22,'Shopify Catalog'!A:X,24,FALSE) -> 65 | H22: Moisture | I22: None | J22: Low | K22: All | L22: Heat + Humidity | M22: No | N22: Yes | O22: No | P22: No | Q22: Yes | R22: No | S22: Yes | T22: Yes | U22: Yes | V22: Yes | X22: Damp | AA22: Stylers | AB22: Kinky Curly Knot Today Leave In Conditioner | AC22: No
B23: BRN-LIC-59 | C23: Breahni | D23: Breahni Leave In Conditioner | E23: Leave In | F23: =VLOOKUP(Summary!B23,'Shopify Catalog'!A:X,24,FALSE) -> 25 | H23: Moisture | I23: None | J23: Low | K23: All | L23: Heat + Humidity | M23: No | N23: Yes | O23: No | P23: No | Q23: Yes | R23: No | S23: Yes | T23: Yes | U23: Yes | V23: Yes | X23: Damp | AA23: Stylers | AC23: No
B24: BRN-HHR-237 | C24: Breahni | D24: =VLOOKUP(B24,'Shopify Catalog'!$A:$C,3,FALSE) -> Breahni Hydrating Hair Refresher | F24: =VLOOKUP(Summary!B24,'Shopify Catalog'!A:X,24,FALSE) -> 65 | H24: Moisture | I24: Soft | J24: All | K24: All | L24: Heat + Humidity | M24: No | N24: Yes | O24: No | P24: Yes | Q24: Yes | R24: No | S24: Yes | T24: Yes | U24: Yes | V24: Yes | X24: Dry | AA24: Stylers | AB24: Camille Rose Honey Dew Liquid Moisture Refresher | AC24: No
B25: BRN-HHR-59 | C25: Breahni | D25: Breahni Hydrating Hair Refresher | F25: =VLOOKUP(Summary!B25,'Shopify Catalog'!A:X,24,FALSE) -> 25 | H25: Moisture | I25: Soft | J25: All | K25: All | L25: Heat + Humidity | M25: No | N25: Yes | O25: No | P25: Yes | Q25: Yes | R25: No | S25: Yes | T25: Yes | U25: Yes | V25: Yes | X25: Dry | AA25: Stylers | AC25: No
B26: BRN-WED-237 | C26: Breahni | D26: =VLOOKUP(B26,'Shopify Catalog'!$A:$C,3,FALSE) -> Breahni Weightless Detangler | F26: =VLOOKUP(Summary!B26,'Shopify Catalog'!A:X,24,FALSE) -> 65 | H26: Detangler | I26: None | J26: All | K26: Fine | L26: Heat + Humidity | M26: No | N26: Yes | O26: Yes | P26: No | Q26: Yes | R26: No | S26: Yes | T26: Yes | U26: Yes | V26: Yes | X26: Damp | AA26: Stylers | AB26: Kinky Curly Knot Today Leave In Conditioner | AC26: No
B27: BRN-WED-59 | C27: Breahni | D27: Breahni Weightless Detangler | F27: =VLOOKUP(Summary!B27,'Shopify Catalog'!A:X,24,FALSE) -> 25 | H27: Detangler | I27: None | J27: All | K27: Fine | L27: Heat + Humidity | M27: No | N27: Yes | O27: Yes | P27: No | Q27: Yes | R27: No | S27: Yes | T27: Yes | U27: Yes | V27: Yes | X27: Damp | AA27: Stylers | AC27: No
B28: CAB-LPOT-118 | C28: Cachos Brazil | D28: =VLOOKUP(B28,'Shopify Catalog'!$A:$C,3,FALSE) -> Cachos Brazil Low Porosity Hair & Scalp Elixir - Oil Treatment | E28: Oil | F28: =VLOOKUP(Summary!B28,'Shopify Catalog'!A:X,24,FALSE) -> 70 | H28: Sealant | I28: None | J28: Low | K28: All | L28: Heat + Humidity | M28: No | N28: No | O28: No | P28: No | Q28: No | R28: No | S28: Yes | T28: Yes | U28: Yes | V28: No | X28: Dry & Damp | AA28: Stylers | AB28: Innersense I create Shine | AC28: No
B29: CAB-HPTH-118 | C29: Cachos Brazil | D29: =VLOOKUP(B29,'Shopify Catalog'!$A:$C,3,FALSE) -> Cachos Brazil High Porosity Hair & Scalp Elixir - Ideal for Color Treated Hair | F29: =VLOOKUP(Summary!B29,'Shopify Catalog'!A:X,24,FALSE) -> 70 | H29: Scalp Care | I29: None | J29: High | K29: All | L29: Heat + Humidity | M29: No | N29: No | O29: No | P29: No | Q29: No | R29: No | S29: Yes | T29: Yes | U29: Yes | V29: No | X29: Dry & Damp | AA29: Stylers | AB29: Camille Rose Rosemary Mint Strengthening Oil | AC29: No
B30: CAB-LPHB-118 | C30: Cachos Brazil | D30: =VLOOKUP(B30,'Shopify Catalog'!$A:$C,3,FALSE) -> Cachos Brazil Low Porosity Hair Butter | F30: =VLOOKUP(Summary!B30,'Shopify Catalog'!A:X,24,FALSE) -> 75 | H30: Sealant | I30: None | J30: Low | K30: All | L30: Heat + Humidity | M30: No | N30: No | O30: No | P30: No | Q30: No | R30: No | S30: Yes | T30: Yes | U30: Yes | V30: Yes | X30: Dry & Damp | AA30: Stylers | AB30: Camille Rose Almond Jai Twisting Butter | AC30: No
B31: CAB-CWDC-237 | C31: Cachos Brazil | D31: Cachos Brazil Brazilian Combing Crème-Wash & Go Styler & Deep Conditioner | E31: Styler | F31: =VLOOKUP(Summary!B31,'Shopify Catalog'!A:X,24,FALSE) -> 80 | H31: Moisture | I31: Soft | J31: All | K31: All | L31: Heat + Humidity | M31: No | N31: No | O31: No | P31: No | Q31: No | R31: No | S31: Yes | T31: Yes | U31: Yes | V31: Yes | X31: Wet | AA31: Oils & Butters | AB31: Treluxe Curl Suipreme 4-in-1 Hydrating Crème | AC31: No
B32: CAB-CWDC-118 | C32: Cachos Brazil | D32: =VLOOKUP(B32,'Shopify Catalog'!$A:$C,3,FALSE) -> Cachos Brazil Brazilian Combing Crème - Wash & Go Styler & Deep Conditioner | E32: Styler | F32: =VLOOKUP(Summary!B32,'Shopify Catalog'!A:X,24,FALSE) -> 57 | H32: Moisture | I32: Soft | J32: All | K32: All | L32: Heat + Humidity | M32: No | N32: No | O32: No | P32: No | Q32: No | R32: No | S32: Yes | T32: Yes | U32: Yes | V32: Yes | X32: Wet | AA32: Oils & Butters | AB32: Treluxe Curl Suipreme 4-in-1 Hydrating Crème | AC32: No
B33: CAB-LCMR-118 | C33: Cachos Brazil | D33: =VLOOKUP(B33,'Shopify Catalog'!$A:$C,3,FALSE) -> Cachos Brazil Rio Mist Leave-In Conditioner - Moisturizer & Curl Refresher | E33: Leave In | F33: =VLOOKUP(Summary!B33,'Shopify Catalog'!A:X,24,FALSE) -> 50 | H33: Moisture | I33: None | J33: High | K33: Medium | L33: Heat + Humidity | M33: No | N33: No | O33: No | P33: No | Q33: No | R33: No | S33: Yes | T33: Yes | U33: Yes | V33: Yes | X33: Damp | AA33: Stylers | AB33: Breahni Leave In Conditioner | AC33: No
B34: CAB-LCMR-237 | C34: Cachos Brazil | D34: Cachos Brazil Rio Mist Leave-In Conditioner - Moisturizer & Curl Refresher | E34: Leave In | F34: =VLOOKUP(Summary!B34,'Shopify Catalog'!A:X,24,FALSE) -> 75 | H34: Moisture | I34: None | J34: High | K34: Medium | L34: Heat + Humidity | M34: No | N34: No | O34: No | P34: No | Q34: No | R34: No | S34: Yes | T34: Yes | U34: Yes | V34: Yes | X34: Damp | AA34: Stylers | AB34: Breahni Leave In Conditioner | AC34: No
B35: CAM-RCM-237 | C35: Camille Rose | D35: Camille Rose Naturals Rose Cleansing Milk | F35: =VLOOKUP(Summary!B35,'Shopify Catalog'!A:X,24,FALSE) -> #N/A | H35: Moisture | I35: None | J35: All | K35: All | L35: Heat + Humidity | M35: No | N35: No | O35: No | P35: No | Q35: No | R35: No | S35: Yes | T35: Yes | U35: Yes | V35: Yes | X35: Wet | AA35: Conditioners | AB35: Innersense Hydrating Cream Hairbath | AC35: No
B36: CAM-DSM-237 | C36: Camille Rose | D36: =VLOOKUP(B36,'Shopify Catalog'!$A:$C,3,FALSE) -> Camille Rose Rosemary Strengthening Mist | F36: =VLOOKUP(Summary!B36,'Shopify Catalog'!A:X,24,FALSE) -> 65 | H36: Regrowth | I36: None | J36: Medium - High | K36: All | L36: Heat + Humidity | M36: No | N36: Yes | O36: Yes | P36: No | Q36: Yes | R36: Yes | S36: Yes | T36: Yes | U36: Yes | V36: Yes | X36: Dry | AA36: Stylers | AB36: Breahni Hydrating Refresher Spray | AC36: No
B37: CAM-HDLMR-237 | C37: Camille Rose | D37: =VLOOKUP(B37,'Shopify Catalog'!$A:$C,3,FALSE) -> Camille Rose Honey Dew - Liquid Moisture Refresher | F37: =VLOOKUP(Summary!B37,'Shopify Catalog'!A:X,24,FALSE) -> 75 | H37: Rehydrate | I37: None | J37: Low | K37: All | L37: Heat + Humidity | M37: No | N37: Yes | O37: No | P37: No | Q37: Yes | R37: Yes | S37: Yes | T37: Yes | U37: Yes | V37: Yes | X37: Dry | AA37: Stylers | AB37: Mielle Pomegranate & Honey Curl Refreshing Spray | AC37: Yes
B38: CAM-HSMS-237 | C38: Camille Rose | D38: =VLOOKUP(B38,'Shopify Catalog'!$A:$C,3,FALSE) -> Camille Rose Spiked Honey Mousse 4 in 1 Styler | F38: =VLOOKUP(Summary!B38,'Shopify Catalog'!A:X,24,FALSE) -> 75 | H38: Definition | I38: Soft | J38: All | K38: All | L38: Heat + Humidity | M38: No | N38: No | O38: No | P38: Yes | Q38: No | R38: No | S38: Yes | T38: Yes | U38: Yes | V38: Yes | X38: Damp | AA38: Leave In | AB38: The Doux Bee Girl Crazy Sexy Setting Foam | AC38: No
B39: CAM-HSMS-100 | C39: Camille Rose | D39: Camille Rose Spiked Honey Mousse 4 in 1 Styler | F39: =VLOOKUP(Summary!B39,'Shopify Catalog'!A:X,24,FALSE) -> 35 | H39: Definition | I39: Soft | J39: All | K39: All | L39: Heat + Humidity | M39: No | N39: Yes | O39: No | P39: No | Q39: No | R39: Yes | S39: Yes | T39: Yes | U39: Yes | V39: Yes | X39: Damp | AA39: Leave In | AB39: The Doux Bee Girl Crazy Sexy Setting Foam | AC39: No
B40: CAM-SHSD-56 | C40: Camille Rose | D40: =VLOOKUP(B40,'Shopify Catalog'!$A:$C,3,FALSE) -> Camille Rose Rosemary Oil Strengthening Hair & Scalp Drops | E40: Oil | F40: =VLOOKUP(Summary!B40,'Shopify Catalog'!A:X,24,FALSE) -> 65 | H40: Nourishment | I40: None | J40: High | K40: Thick | L40: Heat + Humidity | M40: No | N40: No | O40: No | P40: No | Q40: No | R40: Yes | S40: Yes | T40: Yes | U40: Yes | V40: Yes | X40: Dry & Damp | AA40: Stylers | AB40: Mielle Rosemary Mint Strengthening Oil Original | AC40: No
B41: CAM-OSLC-237 | C41: Camille Rose | D41: =VLOOKUP(B41,'Shopify Catalog'!$A:$C,3,FALSE) -> Camille Rose Rosemary Oil Strengthening Leave-In Conditioner | E41: Leave In | F41: =VLOOKUP(Summary!B41,'Shopify Catalog'!A:X,24,FALSE) -> 70 | H41: Moisture | I41: None | J41: High | K41: All | L41: Heat + Humidity | M41: No | N41: No | O41: No | P41: No | Q41: Yes | R41: Yes | S41: Yes | T41: Yes | U41: Yes | V41: Yes | X41: Damp | AA41: Stylers | AB41: Inahsi Aloe Hibiscus Leave In | AC41: No
B42: CAM-O5SM-351 | C42: Camille Rose | D42: =VLOOKUP(B42,'Shopify Catalog'!$A:$C,3,FALSE) -> Camille Rose Rosemary Oil 5 Minute Strengthening Hair Mask | F42: =VLOOKUP(Summary!B42,'Shopify Catalog'!A:X,24,FALSE) -> 75 | H42: Strength | I42: None | J42: High | K42: All | L42: Heat + Humidity | M42: No | N42: No | O42: No | P42: No | Q42: No | R42: No | S42: Yes | T42: Yes | U42: Yes | V42: Yes | X42: Wet | AA42: Treatments | AB42: Mielle Rosemay Mint Strengthening Hair Masque | AC42: No
B43: CAM-OSSC-351 | C43: Camille Rose | D43: =VLOOKUP(B43,'Shopify Catalog'!$A:$C,3,FALSE) -> Camille Rose Rosemary Oil Strengthening Hair & Scalp Cleanser | F43: =VLOOKUP(Summary!B43,'Shopify Catalog'!A:X,24,FALSE) -> 70 | H43: Strength | I43: None | J43: High | K43: All | L43: Heat + Humidity | M43: No | N43: No | O43: No | P43: No | Q43: Yes | R43: No | S43: Yes | T43: Yes | U43: Yes | V43: Yes | X43: Wet | AA43: Conditioners | AB43: Mielle Rosemary Mint Strengthening Shampoo | AC43: No
B44: CAM-HCWDS-355 | C44: Camille Rose | D44: =VLOOKUP(B44,'Shopify Catalog'!$A:$C,3,FALSE) -> Camille Rose Honeycomb Curl Whip Texture-Defining Supercream | E44: Styler | F44: =VLOOKUP(Summary!B44,'Shopify Catalog'!A:X,24,FALSE) -> 80 | H44: Definition | I44: Medium | J44: High | K44: All | L44: Heat + Humidity | M44: No | N44: No | O44: Yes | P44: No | Q44: Yes | R44: No | S44: Yes | T44: Yes | U44: Yes | V44: Yes | X44: Damp | AA44: Leave In | AB44: Innersense Inner Peace Whipped Crème Texturizer | AC44: No
B45: CAM-KBMHB-118 | C45: Camille Rose | D45: =VLOOKUP(B45,'Shopify Catalog'!$A:$C,3,FALSE) -> Camille Rose Naturals Kids Brown Butter Melt Hair Balm | F45: =VLOOKUP(Summary!B45,'Shopify Catalog'!A:X,24,FALSE) -> 48 | H45: Hair Growth | I45: None | J45: All | K45: All | L45: Heat + Humidity | M45: Yes | N45: No | O45: No | P45: No | Q45: No | R45: Yes | S45: Yes | T45: Yes | U45: Yes | V45: Yes | X45: Dry | AA45: Stylers | AB45: Cachos Brazil Low Porosity Hair Butter | AC45: No
B46: CAM-KSPB-237 | C46: Camille Rose | D46: =VLOOKUP(B46,'Shopify Catalog'!$A:$C,3,FALSE) -> Camille Rose Naturals Kids Sweet Puddin' Buttercream | E46: Styler | F46: =VLOOKUP(Summary!B46,'Shopify Catalog'!A:X,24,FALSE) -> 45 | H46: Moisture | I46: Soft | J46: All | K46: All | L46: Heat + Humidity | M46: No | N46: No | O46: Yes | P46: No | Q46: No | R46: No | S46: Yes | T46: Yes | U46: Yes | V46: Yes | X46: Dry & Damp | AA46: oils & Butters | AB46: Breahnio Curl Defining Cream
B47: CAM-NKSG-237 | C47: Camille Rose | D47: =VLOOKUP(B47,'Shopify Catalog'!$A:$C,3,FALSE) -> Camille Rose Naturals Kids Sundae Glaze | F47: =VLOOKUP(Summary!B47,'Shopify Catalog'!A:X,24,FALSE) -> 45 | H47: Moisture | I47: None | J47: All | K47: All | L47: Heat + Humidity | M47: No | N47: No | O47: Yes | P47: No | Q47: No | R47: Yes | S47: Yes | T47: Yes | U47: Yes | V47: Yes | X47: Damp | AA47: Stylers | AB47: Breahni Leave In Conditioner | AC47: No
B48: CAM-HHLI-266 | C48: Camille Rose | D48: =VLOOKUP(B48,'Shopify Catalog'!$A:$C,3,FALSE) -> Camille Rose Honey Hydrate Leave-In | F48: =VLOOKUP(Summary!B48,'Shopify Catalog'!A:X,24,FALSE) -> 70 | H48: Moisture | I48: None | J48: All | K48: Thick | L48: Heat + Humidity | M48: No | N48: Yes | O48: No | P48: No | Q48: Yes | R48: Yes | S48: Yes | T48: Yes | U48: Yes | V48: Yes | X48: Damp | AA48: Stylers | AB48: Mielle Pomegranate & Honey Leave In Conditioner | AC48: No
B49: CAM-JMMC-237 | C49: Camille Rose | D49: =VLOOKUP(B49,'Shopify Catalog'!$A:$C,3,FALSE) -> Camille Rose Jansyn's Moisture Max Conditioner | E49: Instant Conditioner | F49: =VLOOKUP(Summary!B49,'Shopify Catalog'!A:X,24,FALSE) -> 70 | H49: Moisture | I49: None | J49: Low | K49: All | L49: Heat + Humidity | M49: No | N49: Yes | O49: Yes | P49: No | Q49: No | R49: Yes | S49: Yes | T49: Yes | U49: Yes | V49: Yes | X49: Wet | AA49: Treatments | AB49: Jessicurl Too Shea Extra Conditioner | AC49: No
B50: CAM-AWBG-237 | C50: Camille Rose | D50: =VLOOKUP(B50,'Shopify Catalog'!$A:$C,3,FALSE) -> Camille Rose Aloe Whipped Butter Gel | E50: Styler | F50: =VLOOKUP(Summary!B50,'Shopify Catalog'!A:X,24,FALSE) -> 75 | H50: Definition | I50: Medium | J50: High | K50: All | L50: Heat + Humidity | M50: No | N50: Yes | O50: No | P50: No | Q50: No | R50: Yes | S50: Yes | T50: Yes | U50: Yes | V50: Yes | X50: Damp | AA50: Leave In | AB50: Innersense Inner Peace Whipped Crème Texturizer | AC50: No
B51: CAM-CUM-355 | C51: Camille Rose | D51: =VLOOKUP(B51,'Shopify Catalog'!$A:$C,3,FALSE) -> Camille Rose Curl Maker | F51: =VLOOKUP(Summary!B51,'Shopify Catalog'!A:X,24,FALSE) -> 95 | H51: Definition | I51: Medium | J51: All | K51: All | L51: Heat + Humidity | M51: No | N51: Yes | O51: Yes | P51: No | Q51: No | R51: Yes | S51: Yes | T51: Yes | U51: Yes | V51: Yes | X51: Wet | AA51: Leave In | AB51: Kinky Curly Curling Custard | AC51: Yes
B52: CAM-FHNDC-355 | C52: Camille Rose | D52: =VLOOKUP(B52,'Shopify Catalog'!$A:$C,3,FALSE) -> Camille Rose Fresh Honey Nectar Deep Conditioning Treatment | F52: =VLOOKUP(Summary!B52,'Shopify Catalog'!A:X,24,FALSE) -> 75 | H52: Moisture | I52: None | J52: Medium - High | K52: All | L52: Heat + Humidity | M52: No | N52: No | O52: No | P52: Yes | Q52: Yes | R52: No | S52: Yes | U52: Yes | V52: Yes | X52: Wet | AA52: Hair Mask | AB52: Jessicurl Deep Conditioning Treatment | AC52: No
B53: CAM-CRMCS-237 | C53: Camille Rose | D53: =VLOOKUP(B53,'Shopify Catalog'!$A:$C,3,FALSE) -> Camille Rose Clean Rinse Moisturizing & Clarifying Shampoo | E53: Cleanser | F53: =VLOOKUP(Summary!B53,'Shopify Catalog'!A:X,24,FALSE) -> 70 | H53: Cleanse | I53: None | J53: All | K53: All | L53: Hard Water | M53: No | N53: No | O53: No | P53: No | Q53: Yes | R53: No | S53: Yes | T53: Yes | U53: Yes | V53: Yes | X53: Wet | AA53: Conditioners | AB53: Inahsi Soothing Mint Clarifying Shampoo | AC53: No
B54: CAM-LFC-237 | C54: Camille Rose | D54: =VLOOKUP(B54,'Shopify Catalog'!$A:$C,3,FALSE) -> Camille Rose Lavender Fresh Cleanse | F54: =VLOOKUP(Summary!B54,'Shopify Catalog'!A:X,24,FALSE) -> 72 | H54: Detangling +Moisture | I54: None | J54: All | K54: All | L54: Heat + Humidity | M54: No | N54: No | O54: No | P54: No | Q54: No | R54: No | S54: Yes | T54: Yes | U54: Yes | V54: Yes | X54: Wet | AA54: Conditioners | AB54: AS I AM JBCO Shampoo | AC54: No
B55: CAM-MCBCS-237 | C55: Camille Rose | D55: =VLOOKUP(B55,'Shopify Catalog'!$A:$C,3,FALSE) -> Camille Rose Mint Condition Braid & Scalp Spray | F55: =VLOOKUP(Summary!B55,'Shopify Catalog'!A:X,24,FALSE) -> 65 | H55: Scalp Nourishment | I55: None | J55: All | K55: Thick | L55: Heat + Humidity | M55: No | N55: Yes | O55: No | P55: No | Q55: Yes | R55: Yes | S55: Yes | T55: Yes | U55: Yes | V55: No | X55: Dry | AA55: Leave In | AC55: No
B56: CAM-AJTB-237 | C56: Camille Rose | D56: =VLOOKUP(B56,'Shopify Catalog'!$A:$C,3,FALSE) -> Camille Rose Almond Jai Twisting Butter | F56: =VLOOKUP(Summary!B56,'Shopify Catalog'!A:X,24,FALSE) -> 75 | H56: Elongation | I56: Soft | J56: Medium - High | K56: All | L56: Heat + Humidity | M56: No | N56: No | O56: No | P56: No | Q56: No | R56: No | S56: Yes | T56: Yes | U56: Yes | V56: Yes | X56: Damp | AA56: Leave In | AB56: Uncle Funky's Daughter Extra Butter | AC56: No
B57: CAM-CHUGS-237 | C57: Camille Rose | D57: =VLOOKUP(B57,'Shopify Catalog'!$A:$C,3,FALSE) -> Camille Rose Cocoa Nibs & Honey - Ultimate Growth Serum | F57: =VLOOKUP(Summary!B57,'Shopify Catalog'!A:X,24,FALSE) -> 80 | H57: Hair Growth | I57: None | J57: All | K57: Thick | L57: Heat + Humidity | M57: No | N57: No | O57: Yes | P57: No | Q57: No | R57: Yes | S57: Yes | T57: Yes | U57: Yes | V57: No | X57: Dry | AA57: Stylers | AC57: No
B58: CAM-MPCC-355 | C58: Camille Rose | D58: Camille Rose Moroccan Pear Conditioning Custard | F58: =VLOOKUP(Summary!B58,'Shopify Catalog'!A:X,24,FALSE) -> 70 | H58: Moisture | I58: None | J58: Low | K58: Fine | L58: Heat + Humidity | M58: No | N58: Yes | O58: Yes | P58: No | Q58: No | R58: No | S58: Yes | T58: Yes | U58: Yes | V58: Yes | X58: Wet | AA58: Hair Mask | AB58: tgin Tripple Moisture Replenishing Conditioner | AC58: No
B59: CAM-CLOM-237 | C59: Camille Rose | D59: =VLOOKUP(B59,'Shopify Catalog'!$A:$C,3,FALSE) -> Camille Rose Curl Love Moisture Milk | F59: =VLOOKUP(Summary!B59,'Shopify Catalog'!A:X,24,FALSE) -> 75 | H59: Moisture | I59: None | J59: High | K59: All | L59: Heat + Humidity | M59: No | N59: Yes | O59: No | P59: No | Q59: No | R59: No | S59: Yes | T59: Yes | U59: Yes | V59: Yes | X59: Damp | AA59: Stylers | AB59: Breahni Moisture Milk | AC59: Yes
B60: CAM-CLOM-59 | C60: Camille Rose | D60: Camille Rose Curl Love Moisture Milk | F60: =VLOOKUP(Summary!B60,'Shopify Catalog'!A:X,24,FALSE) -> 25 | H60: Moisture | I60: None | J60: High | K60: All | L60: Heat + Humidity | M60: No | N60: Yes | O60: No | P60: No | Q60: No | R60: No | S60: Yes | T60: Yes | U60: Yes | V60: Yes | X60: Damp | AA60: Stylers | AB60: Breahni Moisture Milk | AC60: Yes
B61: CAM-ADCM-237 | C61: Camille Rose | D61: =VLOOKUP(B61,'Shopify Catalog'!$A:$C,3,FALSE) -> Camille Rose Algae Renew Deep Conditioning Mask | F61: =VLOOKUP(Summary!B61,'Shopify Catalog'!A:X,24,FALSE) -> 85 | H61: Moisture | I61: None | J61: High | K61: All | L61: Heat + Humidity | M61: No | N61: Yes | O61: Yes | P61: No | Q61: Yes | R61: No | S61: Yes | T61: Yes | U61: Yes | V61: Yes | X61: Wet | AA61: Treatments | AB61: Uncle Funky's Daughter Heal & Renew Intensive Hair Masque | AC61: No
B62: CAM-ADCM-50 | C62: Camille Rose | D62: Camille Rose Algae Renew Deep Conditioning Mask | F62: =VLOOKUP(Summary!B62,'Shopify Catalog'!A:X,24,FALSE) -> 25 | H62: Moisture | I62: None | J62: High | K62: All | L62: Heat + Humidity | M62: No | N62: Yes | O62: Yes | P62: No | Q62: Yes | R62: No | S62: Yes | T62: Yes | U62: Yes | V62: Yes | X62: Wet | AA62: Treatments | AC62: No
B63: CUB-RHW-237 | C63: Curls | D63: =VLOOKUP(B63,'Shopify Catalog'!$A:$C,3,FALSE) -> Curls Blueberry Bliss Reparative Mask | F63: =VLOOKUP(Summary!B63,'Shopify Catalog'!A:X,24,FALSE) -> 75 | H63: Moisture-Protein Balance | I63: None | J63: High | K63: All | L63: Heat + Humidity | M63: No | N63: No | O63: No | P63: Yes | Q63: Yes | R63: No | S63: Yes | T63: Yes | U63: Yes | V63: Yes | X63: W | AA63: Treatments | AB63: Inahsi Mango Avocado Restorative Hair Masque | AC63: No
B64: CUB-TSC-237 | C64: Curls | D64: =VLOOKUP(B64,'Shopify Catalog'!$A:$C,3,FALSE) -> Curls Blueberry Bliss Twist-N-Shout Cream | E64: Styler | F64: =VLOOKUP(Summary!B64,'Shopify Catalog'!A:X,24,FALSE) -> 65 | H64: Definition | I64: Medium | J64: High | K64: Medium-Thick | L64: Heat + Humidity | M64: No | N64: No | O64: Yes | P64: No | Q64: No | R64: Yes | S64: Yes | T64: Yes | U64: Yes | V64: Yes | X64: Damp | AA64: Leave In | AB64: Camille Rose Almond Jai Twisting Butter | AC64: No
B65: CUB-CCP-118 | C65: Curls | D65: =VLOOKUP(B65,'Shopify Catalog'!$A:$C,3,FALSE) -> Curls Blueberry Bliss Curl Control Paste | F65: =VLOOKUP(Summary!B65,'Shopify Catalog'!A:X,24,FALSE) -> 40.6 | H65: Definition | I65: Medium | J65: All | K65: All | L65: Heat + Humidity | M65: No | N65: No | O65: No | P65: Yes | Q65: Yes | R65: Yes | S65: Yes | T65: Yes | U65: Yes | V65: Yes | X65: Damp | AA65: Leave In | AB65: Innersesnse I Create hold | AC65: No
B66: CUB-MTHT-118 | C66: Curls | D66: =VLOOKUP(B66,'Shopify Catalog'!$A:$C,3,FALSE) -> Curls Blueberry & Mint Tea Hair Growth & Scalp Treatment | F66: =VLOOKUP(Summary!B66,'Shopify Catalog'!A:X,24,FALSE) -> 42 | H66: Treatment | I66: None | J66: High | K66: All | L66: Heat + Humidity | M66: No | N66: No | O66: No | P66: No | Q66: No | R66: No | S66: Yes | T66: Yes | U66: Yes | V66: No | X66: Dry | AA66: Stylers | AB66: Mielle Rosemary Mint Hair Oil | AC66: No
B67: CUB-HGO-59 | C67: Curls | D67: =VLOOKUP(B67,'Shopify Catalog'!$A:$C,3,FALSE) -> Curls Blueberry Bliss Hair Growth Oil | E67: Oil | F67: =VLOOKUP(Summary!B67,'Shopify Catalog'!A:X,24,FALSE) -> 60 | H67: Hair Growth | I67: None | J67: All | K67: All | L67: Heat + Humidity | M67: No | N67: No | O67: No | P67: No | Q67: No | R67: No | S67: Yes | T67: Yes | U67: Yes | V67: Yes | X67: Dry | AA67: Stylers | AB67: Soultanicals Bloom Supa Potent Healthy Hair Growth Oil | AC67: No
B68: CUB-CCJ-237 | C68: Curls | D68: =VLOOKUP(B68,'Shopify Catalog'!$A:$C,3,FALSE) -> Curls So So Def Vitamin C Curl Defining Jelly | F68: =VLOOKUP(Summary!B68,'Shopify Catalog'!A:X,24,FALSE) -> 65 | H68: Definition & hold | I68: Medium | J68: All | K68: All | L68: Heat + Humidity | M68: No | N68: No | O68: No | P68: Yes | Q68: No | R68: No | S68: Yes | T68: Yes | U68: Yes | V68: No | X68: Damp | AA68: Leave In | AB68: Camille Rose Curl Maker | AC68: No
B69: CUB-RLC-237 | C69: Curls | D69: =VLOOKUP(B69,'Shopify Catalog'!$A:$C,3,FALSE) -> Curls Blueberry Bliss Reparative Leave In Conditioner | E69: Leave In | F69: =VLOOKUP(Summary!B69,'Shopify Catalog'!A:X,24,FALSE) -> 65 | H69: Moisture-Protein Balance | I69: None | J69: High | K69: All | L69: Heat + Humidity | M69: Yes | N69: No | O69: No | P69: Yes | Q69: No | R69: No | S69: Yes | T69: Yes | U69: Yes | V69: No | X69: Damp | AA69: Stylers | AB69: Innersense Sweet Spirit Leave In | AC69: No
B70: CUB-RHW-237 | C70: Curls | D70: =VLOOKUP(B70,'Shopify Catalog'!$A:$C,3,FALSE) -> Curls Blueberry Bliss Reparative Mask | F70: =VLOOKUP(Summary!B70,'Shopify Catalog'!A:X,24,FALSE) -> 75 | H70: Moisture-Protein Balance | I70: None | J70: High | K70: All | L70: Heat + Humidity | M70: No | N70: Yes | O70: No | P70: Yes | Q70: Yes | R70: No | S70: Yes | T70: Yes | U70: Yes | V70: Yes | X70: Wet | AA70: Conditioners | AB70: Innersense Hydrating Cream Hairbath | AC70: No
B71: CUP-TCT-237 | C71: Curls & Potions | D71: =VLOOKUP(B71,'Shopify Catalog'!$A:$C,3,FALSE) -> Curls & Potions Chebula & Green Tea 2 in 1 Conditioning Treatment | F71: =VLOOKUP(Summary!B71,'Shopify Catalog'!A:X,24,FALSE) -> 95 | H71: Reduce Hair Loss | I71: None | J71: All | K71: All | L71: Heat + Humidity | M71: No | N71: Yes | O71: No | P71: No | Q71: Yes | R71: No | S71: Yes | T71: Yes | U71: Yes | V71: Yes | X71: Wet | AA71: Hair Mask | AB71: tgin Tripple Moisture Replanishing Conditioner | AC71: No
B72: CUP-CHM-237 | C72: Curls & Potions | D72: =VLOOKUP(B72,'Shopify Catalog'!$A:$C,3,FALSE) -> Curls & Potions Chebe Hydration Mask | F72: =VLOOKUP(Summary!B72,'Shopify Catalog'!A:X,24,FALSE) -> 78 | H72: Moisture | I72: None | J72: All | K72: All | L72: Heat + Humidity | M72: No | N72: Yes | O72: No | P72: No | Q72: Yes | R72: No | S72: Yes | T72: Yes | U72: Yes | V72: Yes | X72: Wet | AA72: Oils | AB72: Camille Rose Algae Renew Deep Conditioner | AC72: No
B73: CUP-GTRR-237 | C73: Curls & Potions | D73: =VLOOKUP(B73,'Shopify Catalog'!$A:$C,3,FALSE) -> Curls & Potions Chebula & Green Tea Hair Repair Rinse | F73: =VLOOKUP(Summary!B73,'Shopify Catalog'!A:X,24,FALSE) -> 80 | H73: Reduce Hair Loss | I73: None | J73: All | K73: All | L73: Heat + Humidity | M73: No | N73: No | O73: No | P73: Yes | Q73: Yes | R73: No | S73: Yes | T73: Yes | U73: Yes | V73: No | W73: Yes | X73: Damp | AA73: Conditioners | AB73: Ecoslay Matcha Boost Protein Treatment | AC73: No
B74: CUP-GTSO-59 | C74: Curls & Potions | D74: =VLOOKUP(B74,'Shopify Catalog'!$A:$C,3,FALSE) -> Curls & Potions Chebula & Green Tea Herbal Mint Hair & Scalp Oil | E74: Oil | F74: =VLOOKUP(Summary!B74,'Shopify Catalog'!A:X,24,FALSE) -> 70 | H74: Reduce Hair Loss | I74: None | J74: All | K74: All | L74: Heat + Humidity | M74: No | N74: No | O74: No | P74: No | Q74: No | R74: No | S74: Yes | T74: Yes | U74: Yes | V74: No | X74: Dry | AA74: Stylers | AB74: Soultanicals Bloom Super Potent Health Hair Growth Oil | AC74: No
B75: CUP-SLRS-237 | C75: Curls & Potions | D75: =VLOOKUP(B75,'Shopify Catalog'!$A:$C,3,FALSE) -> Curls & Potions Chebe Scalp & Length Retention Shampoo | E75: Cleanser | F75: =VLOOKUP(Summary!B75,'Shopify Catalog'!A:X,24,FALSE) -> 85 | H75: Dry Scalp | I75: None | J75: All | K75: All | L75: Heat + Humidity | M75: No | N75: Yes | O75: No | P75: Yes | Q75: Yes | R75: No | S75: No | T75: Yes | U75: Yes | V75: Yes | X75: Wet | AA75: Conditioners | AC75: No
B76: CUP-BRHR-237 | C76: Curls & Potions | D76: =VLOOKUP(B76,'Shopify Catalog'!$A:$C,3,FALSE) -> Curls & Potions Bamboo Rice Water Hair Rinse | F76: =VLOOKUP(Summary!B76,'Shopify Catalog'!A:X,24,FALSE) -> 90 | H76: Hair Growth | I76: None | J76: High | K76: All | L76: Heat + Humidity | M76: No | N76: No | O76: Yes | P76: No | Q76: No | R76: Yes | S76: Yes | T76: Yes | U76: Yes | V76: No | W76: Yes | X76: Dry & Damp | AA76: Conditioners | AB76: Curls Blueberry Bliss Hair Growth Oil | AC76: No
B77: CUP-BUMB-237 | C77: Curls & Potions | D77: =VLOOKUP(B77,'Shopify Catalog'!$A:$C,3,FALSE) -> Curls & Potions Butter Me Up Buttercream | E77: Leave In | F77: =VLOOKUP(Summary!B77,'Shopify Catalog'!A:X,24,FALSE) -> 75 | H77: Moisture | I77: None | J77: All | K77: Medium-Thick | L77: Heat + Humidity | M77: No | N77: Yes | O77: No | P77: No | Q77: Yes | R77: Yes | S77: Yes | T77: Yes | U77: Yes | V77: Yes | X77: Wet & Damp | AA77: Conditioners | AB77: Uncle Funky's Daughter Extra Butter Curl Forming Crème | AC77: No
B78: CUP-RMLIC-237 | C78: Curls & Potions | D78: =VLOOKUP(B78,'Shopify Catalog'!$A:$C,3,FALSE) -> Curls & Potions Rice Milk Leave In Conditioner | E78: Leave In | F78: =VLOOKUP(Summary!B78,'Shopify Catalog'!A:X,24,FALSE) -> 80 | H78: Moisture | I78: None | J78: High | K78: All | L78: Heat + Humidity | M78: No | N78: Yes | O78: No | P78: Yes | Q78: Yes | R78: Yes | S78: Yes | T78: Yes | U78: Yes | V78: Yes | X78: Damp | AA78: Stylers | AB78: Curls Blueberry Bliss Reparative Leave In Conditioner | AC78: No
B79: CUP-SCD-237 | C79: Curls & Potions | D79: =VLOOKUP(B79,'Shopify Catalog'!$A:$C,3,FALSE) -> Curls & Potions Supreme Curl Detox | F79: =VLOOKUP(Summary!B79,'Shopify Catalog'!A:X,24,FALSE) -> 80 | H79: Resets Curls | I79: None | J79: Low | K79: All | L79: Hard Water | M79: No | N79: No | O79: No | P79: No | Q79: Yes | R79: No | S79: Yes | T79: Yes | U79: Yes | V79: No | X79: Wet | AA79: Conditioners | AB79: Innersense Detox Hair Mask | AC79: No
B80: CUP-DMP-237 | C80: Curls & Potions | D80: =VLOOKUP(B80,'Shopify Catalog'!$A:$C,3,FALSE) -> Curls & Potions Deep Moisture Potion | F80: =VLOOKUP(Summary!B80,'Shopify Catalog'!A:X,24,FALSE) -> 80 | H80: Moisture | I80: None | J80: All | K80: All | L80: Heat + Humidity | M80: No | N80: Yes | O80: No | P80: No | Q80: Yes | R80: No | S80: Yes | T80: Yes | U80: Yes | V80: Yes | X80: Wet | AA80: Treatments | AB80: Treluxe Soothe & Restore Ultra Moisturizing Deep Conditioner | AC80: No
B81: CUP-CCG-237 | C81: Curls & Potions | D81: =VLOOKUP(B81,'Shopify Catalog'!$A:$C,3,FALSE) -> Curls & Potions Chebe Clay Gloss | F81: =VLOOKUP(Summary!B81,'Shopify Catalog'!A:X,24,FALSE) -> 84 | H81: Moisture | I81: None | J81: All | K81: All | L81: Hard Water | M81: No | N81: Yes | O81: Yes | P81: Yes | Q81: Yes | R81: No | S81: Yes | T81: Yes | U81: Yes | V81: No | X81: Wet | AA81: Conditioners | AB81: Innersense Hydrating Hair Mask | AC81: No
B82: CUP-RWGST-237 | C82: Curls & Potions | D82: =VLOOKUP(B82,'Shopify Catalog'!$A:$C,3,FALSE) -> Curls & Potions Chebe and Rice Water Growth Stimulating Treatment | F82: =VLOOKUP(Summary!B82,'Shopify Catalog'!A:X,24,FALSE) -> 80 | H82: Itchy Scalp | I82: None | J82: All | K82: All | L82: Heat + Humidity | M82: No | N82: Yes | O82: Yes | P82: Yes | Q82: Yes | R82: No | S82: Yes | T82: Yes | U82: Yes | V82: No | X82: Dry | AA82: Stylers | AB82: Curls & Potions Chebula & Green Tea Herbal Mint Hair & Scalp Oil | AC82: No
B83: CUO-CPSG-237 | C83: Curls & Potions | D83: =VLOOKUP(B83,'Shopify Catalog'!$A:$C,3,FALSE) -> Curls & Potions Curling Potion Styling Gel | E83: Styler | F83: =VLOOKUP(Summary!B83,'Shopify Catalog'!A:X,24,FALSE) -> 75 | H83: Definition | I83: Medium | J83: All | K83: All | L83: Heat + Humidity | M83: Yes | N83: Yes | O83: Yes | P83: No | Q83: Yes | R83: Yes | S83: Yes | T83: Yes | U83: Yes | V83: Yes | X83: Wet | AA83: Leave In | AB83: tgin Curl Bomb Moisturizing Styling Gel | AC83: No
B84: CUP-WGRS-237 | C84: Curls & Potions | D84: =VLOOKUP(B84,'Shopify Catalog'!$A:$C,3,FALSE) -> Curls & Potions Bamboo and Rice Water Growth & Restore Shampoo | E84: Cleanser | F84: =VLOOKUP(Summary!B84,'Shopify Catalog'!A:X,24,FALSE) -> 80 | H84: Hair Growth | I84: None | J84: All | K84: All | L84: Heat + Humidity | M84: No | N84: Yes | O84: Yes | P84: Yes | Q84: Yes | R84: No | S84: Yes | T84: Yes | U84: Yes | V84: Yes | X84: Wet | AA84: Conditioners | AB84: AS I AM JBCO Shampoo | AC84: No
B85: CUP-RWRM-237 | C85: Curls & Potions | D85: =VLOOKUP(B85,'Shopify Catalog'!$A:$C,3,FALSE) -> Curls & Potions Bamboo and Rice Water Deep Repair Masque | F85: =VLOOKUP(Summary!B85,'Shopify Catalog'!A:X,24,FALSE) -> 80 | H85: Repair | I85: None | J85: High | K85: All | L85: Heat + Humidity | M85: No | N85: Yes | O85: No | P85: Yes | Q85: Yes | R85: No | S85: Yes | T85: Yes | U85: Yes | V85: Yes | X85: Wet | AA85: Treatments | AB85: Inahsi Mango Avocado Restorative Hair Masque | AC85: No
B86: ECO-BPDC-237 | C86: Ecoslay | D86: =VLOOKUP(B86,'Shopify Catalog'!$A:$C,3,FALSE) -> Ecoslay Matcha Boost Protein Deep Conditioner | E86: Deep Conditioner | F86: =VLOOKUP(Summary!B86,'Shopify Catalog'!A:X,24,FALSE) -> 80 | H86: Hair Strength | I86: None | J86: All | K86: All | L86: Heat + Humidity | M86: No | N86: No | O86: No | P86: Yes | Q86: No | R86: No | S86: Yes | T86: Yes | U86: Yes | V86: No | W86: Yes | X86: Wet | AA86: Conditioners | AB86: Protein Defence By Healthy Hair Studio by Enitan | AC86: No
B87: ECO-BPDC-59 | C87: Ecoslay | D87: Ecoslay Matcha Boost Protein Deep Conditioner | E87: Deep Conditioner | F87: =VLOOKUP(Summary!B87,'Shopify Catalog'!A:X,24,FALSE) -> 30 | H87: Hair Strength | I87: None | J87: All | K87: All | L87: Heat + Humidity | M87: No | N87: No | O87: No | P87: Yes | Q87: No | R87: No | S87: Yes | T87: Yes | U87: Yes | V87: Yes | W87: Yes | X87: Wet | AA87: Conditioners | AC87: No
B88: ECO-GMTR-237 | C88: Ecoslay | D88: =VLOOKUP(B88,'Shopify Catalog'!$A:$C,3,FALSE) -> Ecoslay Ginger & Moringa Tea Hair Rinse | F88: =VLOOKUP(Summary!B88,'Shopify Catalog'!A:X,24,FALSE) -> 73.5 | H88: Reduce Hair Loss | I88: None | K88: All | L88: Hard Water | M88: No | N88: Yes | O88: No | P88: No | Q88: No | R88: No | S88: Yes | T88: Yes | U88: Yes | V88: No | W88: Yes | X88: Wet | AA88: Conditioners | AB88: Curls & Potions Chebula & Green Tea Hair Repair Tea Rinse
B89: ECO-PPS-237 | C89: Ecoslay | D89: =VLOOKUP(B89,'Shopify Catalog'!$A:$C,3,FALSE) -> Ecoslay Peppermint Schnapps | F89: =VLOOKUP(Summary!B89,'Shopify Catalog'!A:X,24,FALSE) -> 80 | H89: Moisture | I89: None | J89: High | K89: All | L89: Heat + Humidity | M89: No | N89: No | O89: Yes | P89: No | Q89: No | R89: No | S89: Yes | T89: Yes | U89: Yes | V89: Yes | W89: Yes | X89: Wet | AA89: Conditioners | AB89: Camille Rose Clean Rinse Moisturizing & Clarifying Shampoo | AC89: No
B90: ECO-PPS-59 | C90: Ecoslay | D90: Ecoslay Peppermint Schnapps | F90: =VLOOKUP(Summary!B90,'Shopify Catalog'!A:X,24,FALSE) -> 30 | H90: Moisture | I90: None | J90: High | K90: All | L90: Heat + Humidity | M90: Yes | N90: No | O90: Yes | P90: Yes | Q90: No | R90: No | S90: Yes | T90: Yes | U90: Yes | V90: Yes | W90: Yes | X90: Wet | AA90: Conditioners | AB90: Camille Rose Clean Rinse Moisturizing & Clarifying Shampoo | AC90: No
B91: ECO-PHOT-118 | C91: Ecoslay | D91: =VLOOKUP(B91,'Shopify Catalog'!$A:$C,3,FALSE) -> Ecoslay Hot Sauce Pre-Poo/Hot Oil Treatment | F91: =VLOOKUP(Summary!B91,'Shopify Catalog'!A:X,24,FALSE) -> 80 | H91: Healthy Scalp | I91: None | J91: All | K91: Thick | L91: Heat + Humidity | M91: No | N91: No | O91: No | P91: No | Q91: No | R91: Yes | S91: Yes | T91: Yes | U91: Yes | V91: No | W91: Yes | X91: Damp | AA91: Conditioners | AB91: Curls Blueberry Bliss Hair Growth Oil | AC91: No
B92: ECO-PHOT-59 | C92: Ecoslay | D92: Ecoslay Hot Sauce Pre-Poo/Hot Oil Treatment | F92: =VLOOKUP(Summary!B92,'Shopify Catalog'!A:X,24,FALSE) -> 40 | H92: Healthy Scalp | I92: None | J92: All | K92: Thick | L92: Heat + Humidity | M92: No | N92: No | O92: No | P92: No | Q92: No | R92: Yes | S92: Yes | T92: Yes | U92: Yes | V92: No | W92: Yes | X92: Damp | AA92: Conditioners | AB92: Curls Blueberry Bliss Hair Growth Oil | AC92: No
B93: ECO-CL-237 | C93: Ecoslay | D93: =VLOOKUP(B93,'Shopify Catalog'!$A:$C,3,FALSE) -> Ecoslay Chai Latte | F93: =VLOOKUP(Summary!B93,'Shopify Catalog'!A:X,24,FALSE) -> 75 | H93: Moisture | I93: None | J93: Low | K93: All | L93: Heat + Humidity | M93: No | N93: No | O93: Yes | P93: No | Q93: No | R93: No | S93: Yes | T93: Yes | U93: Yes | V93: Yes | W93: Yes | X93: Damp | AA93: Conditioners | AB93: Jessicurl Gentle Lather Shampoo | AC93: No
B94: ECO-CL-59 | C94: Ecoslay | D94: Ecoslay Chai Latte | F94: =VLOOKUP(Summary!B94,'Shopify Catalog'!A:X,24,FALSE) -> 30 | H94: Moisture | I94: None | J94: All | K94: All | L94: Heat + Humidity | M94: No | N94: No | O94: Yes | P94: No | Q94: No | R94: No | S94: Yes | T94: Yes | U94: Yes | V94: Yes | W94: Yes | X94: Damp | AA94: Conditioners | AB94: Jessicurl Gentle Lather Shampoo | AC94: No
B95: ECO-LBC-473 | C95: Ecoslay | D95: =VLOOKUP(B95,'Shopify Catalog'!$A:$C,3,FALSE) -> Ecoslay Lemon Buttercream | E95: Leave In | F95: =VLOOKUP(Summary!B95,'Shopify Catalog'!A:X,24,FALSE) -> 80.5 | H95: Definition | I95: Soft | J95: High | K95: Medium-Thick | L95: Heat + Humidity | M95: No | N95: No | O95: No | P95: No | Q95: Yes | R95: No | S95: Yes | T95: Yes | U95: Yes | V95: Yes | W95: Yes | X95: Damp | AA95: Leave In | AB95: Camille Rose Almond Jai Twisting Butter | AC95: No
B96: ECO-LBC-59 | C96: Ecoslay | D96: Ecoslay Lemon Buttercream | E96: Leave In | F96: =VLOOKUP(Summary!B96,'Shopify Catalog'!A:X,24,FALSE) -> 21 | H96: Definition | I96: Soft | J96: High | K96: Medium-Thick | L96: Hard Water | M96: No | N96: No | O96: No | P96: No | Q96: Yes | R96: No | S96: Yes | T96: Yes | U96: Yes | V96: Yes | W96: Yes | X96: Damp | AA96: Leave In | AB96: Camille Rose Almond Jai Twisting Butter | AC96: No
B97: ECO-OMCD-237 | C97: Ecoslay | D97: Ecoslay Orange Marmalade Curl Definer | F97: =VLOOKUP(Summary!B97,'Shopify Catalog'!A:X,24,FALSE) -> 85 | H97: Definition | I97: Medium | J97: All | K97: All | L97: Heat + Humidity | M97: No | N97: Yes | O97: No | P97: No | Q97: Yes | R97: No | S97: Yes | T97: Yes | U97: Yes | V97: Yes | W97: Yes | X97: Wet | AA97: Leave In | AB97: Camille Rose Curl Maker | AC97: No
B98: EC0-OMDC-237 | C98: Ecoslay | D98: Ecoslay Orange Marmalade Curl Definer | F98: =VLOOKUP(Summary!B98,'Shopify Catalog'!A:X,24,FALSE) -> #N/A | H98: Definition | I98: Medium | J98: All | K98: All | L98: Heat + Humidity | M98: No | N98: Yes | O98: No | P98: No | Q98: Yes | R98: No | S98: Yes | T98: Yes | U98: Yes | V98: Yes | W98: Yes | X98: Wet | AA98: Leave In | AB98: Camille Rose Curl Maker | AC98: No
B99: ECO-RPLC-437 | C99: Ecoslay | D99: Ecoslay Rice Pudding Leave-In Conditioner | E99: Leave In | F99: =VLOOKUP(Summary!B99,'Shopify Catalog'!A:X,24,FALSE) -> #N/A | H99: Moisture | I99: None | J99: All | K99: Thick | L99: Heat + Humidity | M99: No | N99: No | O99: No | P99: No | Q99: No | R99: No | S99: Yes | T99: Yes | U99: Yes | V99: Yes | X99: Damp | AA99: Stylers | AB99: Soultanicals Afro Whizz Curl Defining Leave In | AC99: No
B100: ECO-RPLC-59 | C100: Ecoslay | D100: Ecoslay Rice Pudding Leave-In Conditioner | E100: Leave In | F100: =VLOOKUP(Summary!B100,'Shopify Catalog'!A:X,24,FALSE) -> 30 | H100: Moisture | I100: None | J100: All | K100: Thick | L100: Heat + Humidity | M100: No | N100: No | O100: No | P100: No | Q100: No | R100: No | S100: Yes | T100: Yes | U100: Yes | V100: Yes | X100: Damp | AA100: Stylers | AB100: Soultanicals Afro Whizz Curl Defining Leave In | AC100: No
B101: ECO-BCDC-473 | C101: Ecoslay | D101: =VLOOKUP(B101,'Shopify Catalog'!$A:$C,3,FALSE) -> Ecoslay Banana Cream Deep Conditioner | E101: Deep Conditioner | F101: =VLOOKUP(Summary!B101,'Shopify Catalog'!A:X,24,FALSE) -> 115 | H101: Moisture | I101: None | J101: High | K101: All | L101: Heat + Humidity | M101: No | N101: Yes | O101: Yes | P101: No | Q101: Yes | R101: No | S101: Yes | T101: Yes | U101: Yes | V101: Yes | X101: Wet | AA101: Stylers | AB101: Camille Rose Algae Renre Deep Conditioning Treatment | AC101: No
B102: ECO-BCDC-118 | C102: Ecoslay | D102: Ecoslsay Banana Cream Deep Conditioner | E102: Deep Conditioner | F102: =VLOOKUP(Summary!B102,'Shopify Catalog'!A:X,24,FALSE) -> 60 | H102: Moisture | I102: None | J102: High | K102: All | L102: Heat + Humidity | M102: No | N102: Yes | O102: Yes | P102: No | Q102: Yes | R102: No | S102: Yes | T102: Yes | U102: Yes | V102: Yes | X102: Wet | AA102: Stylers | AB102: Camille Rose Algae Renre Deep Conditioning Treatment | AC102: No
B103: ECO-BCDC-59 | C103: Ecoslay | D103: Ecosslay Banana Cream Deep Conditioner | E103: Deep Conditioner | F103: =VLOOKUP(Summary!B103,'Shopify Catalog'!A:X,24,FALSE) -> #N/A | H103: Moisture | I103: None | J103: High | K103: All | L103: Heat + Humidity | M103: No | N103: Yes | O103: Yes | P103: No | Q103: Yes | R103: No | S103: Yes | T103: Yes | U103: Yes | V103: Yes | X103: Wet | AA103: Stylers | AB103: Camille Rose Algae Renre Deep Conditioning Treatment | AC103: No
...

Sheet Reference Data
B2: For drop down options
B4: Brand | C4: Product Category | D4: Hold | E4: Porosity Suitability | F4: Density Suitability | G4: Climate Performance | H4: Build Up Risk | I4: Aloe | J4: Coconut | K4: Protein | L4: Humectant heavy | M4: Butter/Oil Heavy | N4: CG Approved | O4: Silicone Free | P4: Sulfate Free | Q4: Beginner Friendly | R4: Advanced User Product | S4: Best Seller
B5: As I Am | C5: Cleanser | D5: None | E5: All | F5: All | G5: Heat + Humidity | H5: Yes | I5: Yes | J5: Yes | K5: Yes | L5: Yes | M5: Yes | N5: Yes | O5: Yes | P5: Yes | Q5: Yes | R5: Yes | S5: Yes
B6: Breahni | C6: Detox | D6: Soft | E6: Low | F6: Fine | G6: Hard Water | H6: No | I6: No | J6: No | K6: No | L6: No | M6: No | N6: No | O6: No | P6: No | Q6: No | R6: No | S6: No
B7: Cachos Brazil | C7: Instant Conditioner | D7: Medium | E7: Low - Medium | F7: Medium
B8: Camille Rose | C8: Deep Conditioner | D8: Strong | E8: Medium | F8: Medium-Thick
B9: Curls | C9: Leave In | E9: Medium - High | F9: Thick
B10: Curls & Potions | C10: Treatment | E10: High
B11: Design Essentials | C11: Styler
B12: Ecoslay | C12: Oil
B13: Eden BodyWorks | C13: Scalp Treatment
B14: Healthy Hair Studio by Enitan
B15: Inahsi Naturals
B16: Innersense
B17: Innersense Beauty
B18: Jessicurl
B19: Kinky-Curly
B20: Mielle Organics
B21: Soultanicals
B22: Taliah Waajid
B23: Tangle Teezer
B24: TGIN
B25: The Doux
... B27: Uncle Funky's Daughter

Sheet Shopify Catalog
A1: SKU | B1: Handle | C1: Title | D1: Body (HTML) | E1: Vendor | F1: Product Category | G1: Type | H1: Tags | I1: Published | J1: Option1 Name | K1: Option1 Value | L1: Option1 Linked To | M1: Option2 Name | N1: Option2 Value | O1: Option2 Linked To | P1: Option3 Name | Q1: Option3 Value | R1: Option3 Linked To | S1: Variant SKU | T1: Variant Grams | U1: Variant Inventory Tracker | V1: Variant Inventory Policy | W1: Variant Fulfillment Service | X1: Variant Price | Y1: Variant Compare At Price | Z1: Variant Requires Shipping | AA1: Variant Taxable | AB1: Unit Price Total Measure | AC1: Unit Price Total Measure Unit | AD1: Unit Price Base Measure | AE1: Unit Price Base Measure Unit | AF1: Variant Barcode | AG1: Image Src | AH1: Image Position | AI1: Image Alt Text | AJ1: Gift Card | AK1: SEO Title | AL1: SEO Description | AM1: Google Shopping / Google Product Category | AN1: Google Shopping / Gender | AO1: Google Shopping / Age Group | AP1: Google Shopping / MPN | AQ1: Google Shopping / Condition | AR1: Google Shopping / Custom Product | AS1: Google Shopping / Custom Label 0 | AT1: Google Shopping / Custom Label 1 | AU1: Google Shopping / Custom Label 2 | AV1: Google Shopping / Custom Label 3 | AW1: Google Shopping / Custom Label 4 | AX1: Brand Button Url (product.metafields.custom.brand_button_url) | AY1: Brand Description (product.metafields.custom.brand_description) | AZ1: Brand Heading (product.metafields.custom.brand_heading) | BA1: How to use (product.metafields.custom.how_to_use) | BB1: Ingredients (product.metafields.custom.ingredients) | BC1: Google: Custom Product (product.metafields.mm-google-shopping.custom_product) | BD1: Product rating count (product.metafields.reviews.rating_count) | BE1: Age restrictions (product.metafields.shopify.age-restrictions) | BF1: Event type (product.metafields.shopify.event-type) | BG1: Hair care finish (product.metafields.shopify.hair-care-finish) | BH1: Hair care items included (product.metafields.shopify.hair-care-items-included) | BI1: Hair type (product.metafields.shopify.hair-type) | BJ1: Hold level (product.metafields.shopify.hold-level) | BK1: Product form (product.metafields.shopify.product-form) | BL1: Target gender (product.metafields.shopify.target-gender) | BM1: Ticket type (product.metafields.shopify.ticket-type) | BN1: Complementary products (product.metafields.shopify--discovery--product_recommendation.complementary_products) | BO1: Related products (product.metafields.shopify--discovery--product_recommendation.related_products) | BP1: Related products settings (product.metafields.shopify--discovery--product_recommendation.related_products_display) | BQ1: Search product boosts (product.metafields.shopify--discovery--product_search_boost.queries) | BR1: Variant Image | BS1: Variant Weight Unit | BT1: Variant Tax Code | BU1: Cost per item | BV1: Status
A2: =S2 -> SCE-SCED-LMP | B2: summer-curl-edit-dew | C2: Summer Curl Edit – Dew | Low to Medium Porosity Curl Ritual | D2: <p>Your answer to summer styling without the weight.<br>Dew is your low to medium porosity ritual—crafted for curls that resist moisture, frizz easily, and fall flat in the heat.</p> <p>Inside this editorial curation, you'll find a humidity-proof layering system designed to hydrate without heaviness, define without crunch, and hold without buildup.</p> <p>Each product is meticulously selected for its lightweight texture, ingredient harmony, and climate-specific performance under Middle Eastern heat. It’s curation, not guesswork.</p> <p> </p> <p>What's inside:</p> <p>1 X Uncle Funky's Daughter Midnite Train Leave In (8oz)</p> <p>1 X Kinky Curly Knot Today Leave In (8oz)</p> <p>1 X The Doux Mousse Def Texture Foam (7oz)</p> <p>1 X TreLuxe Hi Definition Styling Gel (8oz)</p> | E2: Emerson | F2: Health & Beauty > Personal Care > Hair Care > Hair Styling Products | H2: Aloe Vera, Best seller, bestseller, Bestsellers, Bundle, Bundle Set, CG Approved, CGM, CGM Approved, curl protection, Curly Hair, Frizz Free, Hair Growth & Length Retention, Low Porosity Essentials, Moisture Rich, Natural, Natural Hair, Protein Free, Styler, Sulfate - Free, Summer Curl Edit - Dew, Summer Essential | I2: FALSE | J2: Title | K2: Default Title | S2: SCE-SCED-LMP | T2: 3000 | U2: shopify | V2: deny | W2: manual | X2: 320 | Y2: 0 | Z2: TRUE | AA2: TRUE | AG2: https://cdn.shopify.com/s/files/1/0504/5187/3989/files/8.jpg?v=1751428670 | AH2: 1 | AJ2: FALSE | AL2: Your low to medium porosity summer curl solution. Lightweight, frizz control, long-lasting hold—even in 45° heat. Limited release. Shop Dew while it lasts. | AY2: Expertly paired curl rituals for hair that thrive. Each curation is handpicked and tested for performance, so you get results, not just products. No overwhelm. Just proven formulas that work beautifully together. | AZ2: Emerson | BA2: See individual product pages | BB2: See individual product pages | BD2: 1 | BS2: kg | BU2: 162.43 | BV2: draft
A3: =S3 -> SCE-SCEQ-HPC | B3: summer-curl-edit-quench | C3: Summer Curl Edit – Quench | High Porosity Curl Ritual | D3: <p>For curls that thirst and frizz.<br>Quench is your high-porosity ritual—designed to saturate dry strands, seal in moisture and sculpt definition that survives the Gulf summer.</p><br> <p>This is your moisture-rich curation for bounce, elasticity, and hold that doesn’t quit.</p> <p>Engineered for performance and indulgence, this edit layers hydrating and sealing formulas that work in tandem to protect against breakage, reduce porosity stress and create long-lasting curl memory.</p><br> <p>What's inside:</p> <p>1x The Doux Fast Forward Conditioner (8oz)</p> <p>1x TréLuxe Aloe Vera Curl Primer (8oz)</p> <p>1x Uncle Funky’s Daughter Curly Magic (18oz)</p> <p>1x Innersense I Create Hold (10oz)</p> | E3: Emerson | F3: Health & Beauty > Personal Care > Hair Care > Hair Styling Products | H3: Aloe Vera, Best seller, bestseller, Bestsellers, Bundle Set, CG Approved, CGM, CGM Approved, Chemically Treated Hair, Colour Safe, curl protection, Curly Hair, Frizz Free, High Porosity Essentials, Moisture Rich, Natural, Natural Hair, New Arrivals, Protein Free, Styler, Sulfate - Free, Summer Curl Edit, Summer Curl Edit – Quench, Summer Essential | I3: FALSE | J3: Title | K3: Default Title | S3: SCE-SCEQ-HPC | T3: 3000 | U3: shopify | V3: continue | W3: manual | X3: 369 | Y3: 0 | Z3: TRUE | AA3: TRUE | AG3: https://cdn.shopify.com/s/files/1/0504/5187/3989/files/8.jpg?v=1751428670 | AH3: 1 | AJ3: FALSE | AL3: Your high porosity summer curl solution. Deep moisture, frizz control, long-lasting hold—even in 45° heat. Limited release. Shop Quench while it lasts. | AY3: Expertly paired curl rituals for hair that thrive. Each curation is handpicked and tested for performance, so you get results, not just products. No overwhelm. Just proven formulas that work beautifully together. | AZ3: Emerson | BA3: See individual product pages | BB3: See individual product pages | BD3: 1 | BS3: kg | BU3: 186.8 | BV3: draft
A4: =S4 -> M&M-LMP | B4: mummy-me-kit-low-to-medium-porosity | C4: Mummy & Me Kit - Low to Medium Porosity | D4: <p>Support delicate curls with care and consistency.</p> <p><span class="s2">Curated especially for little ones with low to medium porosity hair, this gentle yet effective ritual supports strands that resist moisture but retain it once it’s sealed in. Each product has been handpicked to soften strands</span><span class="s1">, encourage moisture penetration, reduce frizz, and deliver long lasting nourishment without heaviness or build up.</span></p> <p>Whether you’re learning your child’s hair together or already in your groove, this set empowers you to care with confidence.<br><span class="s2"></span></p> <p>What’s inside:</p> <p>1 X Camille Rose Sweet Cleansing Rinse </p> <p>1 X Camille Rose Conditioning Custard</p> <p>1 X Camille Rose Sundae Glaze Leave In</p> <p>1 X Breahni Light Styling Gel</p> | E4: Emerson | F4: Uncategorized | H4: Best seller, Bundle, Bundle Set, CG Approved, CGM Approved, Curl Definer, Curl Defining, Curl defining gel, Curl Defining Leave-in, Curl definition, Hair Styling, Kid Safe, Kinky Curl Knot Today, Kinky Curly, Kinky Curly Knot Today, Knot Today, Styler, Styling, Styling Custard, The Mummy & Me Edit | I4: TRUE | J4: Title | K4: Default Title | S4: M&M-LMP | T4: 1500 | U4: shopify | V4: deny | W4: manual | X4: 225.25 | Y4: 265 | Z4: TRUE | AA4: TRUE | AG4: https://cdn.shopify.com/s/files/1/0504/5187/3989/files/05C20F6E-68CC-48BF-96CF-5DE5A14357D4.jpg?v=1749913912 | AH4: 1 | AJ4: FALSE | AY4: Expertly paired curl rituals for hair that thrive. Each curation is handpicked and tested for performance, so you get results, not just products. No overwhelm. Just proven formulas that work beautifully together. | AZ4: Emerson | BA4: See individual product pages. | BB4: See individual product pages. | BS4: kg | BV4: active
A5: =S5 -> DUO-8BG-355 | B5: the-doux | C5: The Doux 808 Base Gel | D5: <div class="content-block product-rte rte"> <div class="content-slide-content" data-height=""> <div id="liquid-liquid_QY683U" class="content-slide-space variant_metafields"> <p class="whitespace-normal break-words">Drop the base and watch your curls go boom. 808 Base Gel lays down the foundation for every curl style in your rotation – from wash-and-gos to twist-outs. This medium-hold gel brings the bass line your curls need to stay defined and frizz-free all day.</p> </div> </div> </div> <p>808 Base Gel is the beat drop your curls have been waiting for. Like its namesake bass drum that anchors every track, this gel creates the foundation that makes your whole style hit different.</p> <p>The medium-hold formula strikes that perfect balance – strong enough to lock in your pattern but flexible enough to keep curls bouncy and touchable. While other gels leave you crunchy or flaky, 808 keeps it smooth with a formula that defines without the drama. It's built to be your first layer, creating a frizz-fighting base that other products can build on.</p> <p>Use it solo for simple, defined curls or stack it under MOUSSE DEF for next-level volume and hold. Your wash-and-go just got more reliable, your twist-out more defined, and your TWA more popping. This is the gel that turns good curl days into great ones – because every masterpiece starts with a solid foundation.</p> <p>Frizz trying to remix your style? Not happening.</p> <p>Definition falling flat by midday? 808's got the stamina.</p> <p>Your curls about to stay fresh from morning meeting to midnight.</p> | E5: The Doux | F5: Health & Beauty > Personal Care > Hair Care > Hair Styling Products | G5: Styler | H5: Base Gel, Bouncy curls, CG Approved, CG Method, cgapproved, CGM Approved, Curl Defining, Curl definition, Curly Hair, Frizz control, Frizz Free, Gel, Medium Hold, Natural, Natural Gel, Natural Hair, Styler, Styling, Styling Gel, Sulfate - Free, The Doux, Twist out, Wash- n -go | I5: TRUE | J5: Size | K5: 12 oz | S5: DUO-8BG-355 | T5: 560 | U5: shopify | V5: deny | W5: manual | X5: 75 | Z5: TRUE | AA5: TRUE | AG5: https://cdn.shopify.com/s/files/1/0504/5187/3989/files/808N_eb8317d9-b065-4ba2-b06a-75c5d2d0d5f1.png?v=1755075993 | AH5: 1 | AI5: The Doux 808 Base Gel | AJ5: FALSE | AL5: Discover The Doux 808 Base Gel in the UAE. A medium hold base gel for layering, flexible curl defining & Fights frizz. Perfect for all curl types & textures | AM5: 1901 | AY5: The Doux is an award winning brand of super-fresh, texture focused solutions inspired by the life of a stylist and love for the culture. Merging old-school flava with new-school science. The Doux developed a range of simple, multi-functional formulas designed to put an end to the complicated regimens and conflicting information that are shattering your confidence. | AZ5: The Doux | BA5: WET IT: Start with soaking wet hair (water is your friend)<br> APPLY IT: Apply in sections, letting curls clump naturally.<br> ROCK IT: Rock it solo or layer MOUSSE DEF on top for extra hold.<br> DIFFUSE IT: Diffuse until 100% dry for maximum bounce.<br> FLUFF IT: Fluff from the roots and let them curls live.<br> THE BASE: 808 always goes first – it's the base, remember? No oils or creams before this gel. Let it do its job as the foundation, then build your style from there.<br> | BB5: Aloe Barbadensis Leaf Juice Powder, Water (Aqua), Cetearyl Alcohol, Behentrimonium Methosulphate, C13-15 Alkane, Cetrimonium Chloride, Butyrospermum Parkii (Shea) Butter, Simmondsia Chinensis (Jojoba) Seed Oil, Butylene Glycol, Aminoethylaminopropyl Dimethicone, Polyquaternium-37, PPG-1 Trideceth-6, Propylene Glycol Dicaprylate/Dicaprate, Stearalkonium Chloride, Aloe Vera Callus Extract (Stem Cell), Hydrolyzed Vegetable Protein PG-Propyl Silanetriol, Ananas Sativus (Pineapple) Fruit Extract, Glycerin, Phenethyl Alcohol, Fragrance, Hydrolyzed Quinoa, Cereus Grandiflorus (Cactus) Flower Extract, Hydrolyzed Soy Protein, Tocopheryl Acetate, Caprylhydroxamic Acid, Arginine, Brassica Campestris/Aleurites Fordi Oil Copolymer, Aspergillus Ferment, Disodium EDTA, Lactic Acid, Alanine , Aspartic Acid , Glutamic Acid, Histidine, Isoleucine, Leucine, Lysine, Phenylalanine, Proline, Serine, Threonine, Tyrosine, Valine | BN5: the-doux-big-poppa-defining-gel; the-doux-mousse-def-texture-foam | BP5: only manual | BR5: https://cdn.shopify.com/s/files/1/0504/5187/3989/files/808N_eb8317d9-b065-4ba2-b06a-75c5d2d0d5f1.png?v=1755075993 | BS5: kg | BU5: 35.2 | BV5: active
A6: =S6 -> DUO-BEHG-355 | B6: the-doux-bananas-xtreme-hold-hair-gel | C6: The Doux Bananas Xtreme Hold Hair Gel | D6: <p><span>This hold is bananas, B-A-N-A-N-A-S! The Bananas Xtreme hold Hair Gel is the extreme styler that locks your look down tighter than Fort Knox.</span></p> <p>BANANAS XTREME HOLD HAIR GEL said "let's go crazy" and meant every word. This isn't playing around with medium hold – we're talking extreme, unbreakable, your-hair-isn't-moving-till-you-say-so kind of control.</p> <p>Whether you're sculpting glass-hair sleek edges, creating gravity-defying spikes that salute the sky, or slicking back a style so smooth it looks like liquid, BANANAS delivers that professional-strength hold.</p> <p>The formula brings serious grip without the helmet head effect – your style stays locked but doesn't feel like concrete. Perfect for when you need your hair to stay exactly where you put it, no questions asked. From intricate designs to simple slick-backs, from defined curls to sculptural styles, this gel has the muscle to make it happen.</p> <p>And here's where it gets bananas – when you're ready to switch it up, just add water and watch it reactivate like magic.</p> <p>No flaking, no residue, just extreme hold that goes hard but stays flexible enough to rework. Your style game is about to go absolutely bananas.</p> | E6: The Doux | F6: Health & Beauty > Personal Care > Hair Care > Hair Styling Products | G6: Styler | H6: CG Approved, CG Method, cgapproved, CGM, CGM Approved, Colour Safe, Curl Definer, Curl Defining, Curl definition, curls, Curly Hair, Frizz control, Frizz Free, Hair Styling, Kid Safe, Natural, Natural Hair, Styler, Styling, Styling Gel, Xtreme Hold | I6: TRUE | J6: Size | K6: 12 oz | S6: DUO-BEHG-355 | T6: 0 | U6: shopify | V6: deny | W6: manual | X6: 85 | Z6: TRUE | AA6: TRUE | AF6: 850031703902 | AG6: https://cdn.shopify.com/s/files/1/0504/5187/3989/files/EF045710-ED5F-4FB3-A306-699C24D37D4E.webp?v=1754305163 | AH6: 1 | AI6: The Doux Bananas Gel Available in Dubai, UAE | Emerson Hair & Beauty | AJ6: FALSE | AL6: Discover The Doux Bananas Xtreme Hold Gel: A strong hold gel that defines curls without flaking, humid resistant, controls frizz, nourishes edges & locks in style | AY6: The Doux is an award winning brand of super-fresh, texture focused solutions inspired by the life of a stylist and love for the culture. Merging old-school flava with new-school science. The Doux developed a range of simple, multi-functional formulas designed to put an end to the complicated regimens and conflicting information that are shattering your confidence. | AZ6: The Doux | BA6: WET IT: Drench hair thoroughly – this gel loves water. <br> APPLY IT: Get generous from roots to ends, no skimping. <br> DEFINE IT: Shingle or finger coil for curls that pop off.<br> DRY IT: Diffuse or sit under the dryer until 100% dry. <br> STYLE IT: Fluff and separate once completely dry. <br> REACTIVATE IT: Spritz with water to rework anytime. <br> | BB6: Water (Aqua), PVP, Propanediol, Maltodextrin/VP Copolymer, Sorbitol, Acrylates Copolymer, Honey, Aminomethyl Propanol, Acrylates/C10-30 Alkyl Acrylate Crosspolymer, Aloe Barbadensis Leaf Juice, Musa Sapientum (Banana) Fruit Extract, Tocopheryl Acetate, Panthenol, Silk Amino Acids, Sodium Hyaluronate, Ascorbic Acid, Phenoxyethanol, Ethylhexylglycerin, Helianthus Annus (Sunflower) Seed Oil Lactic Acid, Fragrance (Parfum), Yellow 5 (CI 19140) | BN6: the-doux-fast-forward-heat-prep-conditioner; the-doux-press-rewind-curl-rentention-shampoo | BP6: ahead | BS6: kg | BU6: 37.43 | BV6: active
A7: =S7 -> MIE-MMTHS | B7: mielle-mongongo-oil-thermal-heat-protectant-spray-not-so-perfect | C7: Mielle Mongongo Oil Thermal & Heat Protectant Spray -(Not So Perfect) | D7: <p><strong>** Product content is full - however the lid is broken**</strong></p> <p>Do you use heat in your styling routine? Protect your hair with Mielle's all-natural protectant spray</p> <p>• Provides Intense Heat Defense™ and Curl Pattern Protection™<br>• Protects against high-heat styling<br>• Made without parabens, preservatives, or harmful chemicals</p> | E7: Mielle Organics | F7: Health & Beauty > Personal Care > Hair Care > Hair Styling Products | G7: Moisturizers & Leave - Ins | H7: Blowdrying spray, CG Approved, CG Method, cgapproved, CGM, CGM Approved, Chemically Treated Hair, Frizz control, Hair SPF, Heat Protectant, Heat Protector, High Porosity, Kid Safe, Mielle, Mielle Organics, Natural Hair, Sulfate - Free | I7: FALSE | J7: Size | K7: 4 oz | S7: MIE-MMTHS | T7: 340 | U7: shopify | V7: deny | W7: manual | X7: 0 | Z7: TRUE | AA7: TRUE | AJ7: FALSE | AM7: 1901 | AY7: Mielle Organics a natural haircare brand that delivers on its promises of healthier, stronger and more hydrated hair through use of organic ingredients, products have been uniquely formulated to deliver hydration, moisture and definition.<br> | AZ7: Mielle Organics | BA7: After shampooing apply to clean, wet hair and gently comb through from roots to ends.<br> Proceed with desired heat styling. Avoid eye contact. Keep out of reach of children. | BB7: Water (Aqua, Eau), Cetearyl Alcohol, Polysorbate 60, Amodimethicone, Cetrimonium, Chloride, Trideceth-12, Glycerin,Propylene Glycol, Peg-12 Dimethicone, Polysorbate-20, PVP, Prunus Amygdalus Dulcis (Sweet Almond) Oil, Plukenetia Volubilis (Sacha Inchi) Seed Oil, Argania Spinosa (Argan) Kernel Oil, chinziophyton Rautanenii (Mongongo) Kernel Oil, Vitis Vinifera (Grape) Seed Oil, Disodium EDTA, Tocopheryl, Acetate, Cyclopentasiloxane, Dimethiconol, Hydrolyzed Wheat Protein, Fragrance (Parfum), Phenoxyethanol, Benzoic Acid, Ethylhexylglycerin, Glycereth-2 Cocoate | BS7: kg | BU7: 25.65 | BV7: draft
A8: =S8 -> AIM-JBOHM-237 | B8: as-i-am-jamaican-black-castor-oil-hair-mask | C8: As I Am Jamaican Black Castor Oil Hair Mask | D8: <p class="MsoNormal">Enrich dehydrated hair with an intense therapy hair mask. This rich, creamy treatment moisturizes, detangles and conditions hair. Provides long-lasting hydration. Restores and repairs your hair health. Use to soften hair, ease combing, treat dry scalps.</p> | E8: As I Am | F8: Health & Beauty > Personal Care > Hair Care > Hair Care Kits | G8: Treatment | H8: CG Approved, CG Method, cgapproved, CGM, CGM Approved, Curly Hair, Deep conditioning masque, Detangling, Dry scalp, Hair Mask, Hair Masque, Hair Masque Treatment, Hair restorator, Hair Treatment, Hydrating, Hydrating Mask, Hydration, Moisture Rich, Natural, Natural Hair, Scalp Care, Sulfate - Free | I8: TRUE | J8: Size | K8: 8 oz | S8: AIM-JBOHM-237 | T8: 440 | U8: shopify | V8: deny | W8: manual | X8: 75 | Z8: TRUE | AA8: TRUE | AF8: 858380040150 | AG8: https://cdn.shopify.com/s/files/1/0504/5187/3989/files/453A048A-5B00-4F1D-8817-AC7DC51BBB5F.png?v=1745307994 | AH8: 1 | AI8: As I Am Jamaican Black Castor Oil Hair Mask | AJ8: FALSE | AL8: A creamy treatment enrich with moisturizer and detangler that provides a long lasting hydration. Helps to restore and repair the hair and treat hair scalp. It helps to soften the hair while combing. | AM8: 8452 | AY8: As I Am products consists of wonderfully formulated products designed specifically for; curly and tightly coiled hair; each with an impressive ingredient listing that includes many of nature's finest organic ingredients. <p>Perfect for Type 3 & 4 Hair Types.</pr> | AZ8: As I Am | BA8: Apply a generous amount to hair strands and working the product from root to tip <br> Leave it on for 15-20 minutes <br> Rinse well. | BB8: Aqua/water/eau, Hydrogenated vegetable oil, Cetearyl alcohol, Cetyl alcohol, Betaine, Ricinus communis (castor) seed oil, Ascorbic acid, Linum usitatissimum (linseed) seed extract, Ceramide ng, Glycerin, Tocopherol, Stearamidopropyl dimethylamine, Behentrimonium chloride, Quaternium-80, Propanediol, Fragrance/parfum, Phenoxyethanol, Citric acid, Polyquaternium-37, Dipropylene glycol, Caprylyl glycol, Isostearyl ethylimidazolinium ethosulfate, Propylene glycol dicaprylate/dicaprate, Piroctone olamine, Polyacrylamide, Laureth-9, Peg-8, Ppg-1 trideceth-6, Sodium lauroyl lactylate, Peg-100 stearate, Hydroxypropyl bispalmitamide mea, Peg-3 distearate, Sodium lauroyl glutamate, Cocamidopropyl betaine, Sodium cocoyl isethionate, Ceteareth-25, Sodium benzoate, Potassium sorbate, Sodium chloride, Amyl cinnamal, Hexyl cinnamal, Limonene | BS8: kg | BU8: 28.63 | BV8: active
A9: =S9 -> DUO-BGHCC-473 | B9: the-doux-bee-girl-honey-curl-custard | C9: The Doux Bee Girl Honey Curl Custard | D9: <div class="easyslider-item easyslider-active" data-es-marker="slide-mist-demeanor-super-charged-honey-shine-mist-3" data-es-handle="slide-what-it-doux"> <div class="easyslider-content" aria-expanded="true" aria-hidden="false" aria-labelledby="easyslider-label-7527090290910-0" role="tabpanel"> <div class="easyslider-content-wrapper"> <p><span>Meet the custard that doesn’t just style your curls - it revives them. </span>This luxurious, honey-infused formula drenches even the tightest coils in lasting hydration while sculpting definition that feels soft to the touch - never crunchy, never flaking. <br><br>The secret? Super-charged honey with a positive charge that smooths the cuticle, locks in moisture, and ignites mirror-like shine.<br><span></span></p> <p>Every scoop is fortified with Aloe and powerhouse vitamins B, C &amp; E to protect growth, while Keratin and Silk Amino Acids wrap each strand in strength and bounce. The result: curls that spring, move, and glow with confidence - juicy, touchable, alive.<br><span></span></p> <p> </p> <p><span>Because thirsty curls don’t just need control</span></p> </div> </div> </div> | E9: The Doux | F9: Health & Beauty > Personal Care > Hair Care > Hair Styling Products | G9: Styler | H9: CG Approved, CG Method, cgapproved, CGM, CGM Approved, Curl Defining, Curl Defining Custard, Curl definition, Curling Custard, Curly Hair, Hair Styling, Natural, Natural Hair, Soft Hold, Styler, Styling, Styling Custard, Styling Gel, Sulfate - Free, The Doux | I9: TRUE | J9: Size | K9: 16 oz | S9: DUO-BGHCC-473 | T9: 0 | U9: shopify | V9: deny | W9: manual | X9: 75 | Z9: TRUE | AA9: TRUE | AG9: https://cdn.shopify.com/s/files/1/0504/5187/3989/files/3AF0A611-7EF1-4606-92F2-33B29B96EF11.webp?v=1750222328 | AH9: 1 | AI9: The Doux Bee Girl Honey Curl Custard | AJ9: FALSE | AK9: The Doux Bee Girl Honey Curl Custard | AL9: Discover the Doux Bee Girl Honey Curl Custard: A soft hold curl defining custard that hydrates, defines even the tightest curls with no crunch/flakes. | AM9: 1901 | AY9: The Doux is an award winning brand of super-fresh, texture focused solutions inspired by the life of a stylist and love for the culture. Merging old-school flava with new-school science. The Doux developed a range of simple, multi-functional formulas designed to put an end to the complicated regimens and conflicting information that are shattering your confidence. | AZ9: The Doux | BA9: Apply to clean, wet hair in small sections. Rake through with fingers to clump curls. Hood dry or diffuse until 100% dry. Fluff to the gods or as desired. | BB9: AQUA (WATER, EAU), PROPANEDIOL, ACRYLATES COPOLYMER, MALTODEXTRIN/VP COPOLYMER, SORBITOL, PVP, AMINOMETHYL PROPANOL, PARFUM (FRAGRANCE), ACYLATES/C1030 ALKYL ACRYLATE CROSSPOLYMER, PHENOXYETHANOL, HYDROXYPROPYLTRIMONIUM HONEY, MEL (HONEY, MIEL), PANTHENOL, SODIUM HYALURONATE, KERATIN AMINO ACIDS, SILK AMINO ACIDS, ASCORBIC ACID, TOCOPHERYL ACETATE, ALOE BARBADENSIS LEAF JUICE, LACTIC ACID, ETHYLHEXYLGLYCERIN. | BN9: the-doux-crazy-sexy-curl-honey-setting-foam; curls-blueberry-bliss-curl-control-jelly; curls-blueberry-bliss-hair-growth-oil | BP9: only manual | BR9: https://cdn.shopify.com/s/files/1/0504/5187/3989/files/3AF0A611-7EF1-4606-92F2-33B29B96EF11.webp?v=1750222328 | BS9: kg | BU9: 30.78 | BV9: active
A10: =S10 -> UFD-SBTDM-222 | B10: uncle-funkys-daughter-soul-bounce-texture-defining-mousse | C10: Uncle Funky's Daughter Soul Bounce Texture Defining Mousse | D10: <p>Lock in hold, boost shine, amplify volume and define texture with Uncle Funky's Daughter honey, quinoa &amp; keratin formulated texture defining mousse. Pairs well with top selling Curly Magic for amazing results.</p> <p> </p> | E10: Uncle Funky's Daughter | F10: Health & Beauty > Personal Care > Hair Care > Hair Styling Products | G10: Styler | H10: CG Approved, CG Method, cgapproved, CGM, CGM Approved, Curl Definer, Curl defining mousse, Curl definition, Curly Hair, cury hair, Hair volume, Mousse, Natural, Natural Hair, Styler, Styling Mousse, Sulfate - Free, Summer Curl Edit, Volumizing foam | I10: TRUE | J10: Size | K10: 7.5 oz | S10: UFD-SBTDM-222 | T10: 440 | U10: shopify | V10: deny | W10: manual | X10: 80 | Z10: TRUE | AA10: TRUE | AF10: 856681006561 | AG10: https://cdn.shopify.com/s/files/1/0504/5187/3989/files/4B28B776-F7B4-4D84-A121-344C06024716.jpg?v=1744365128 | AH10: 1 | AI10: Uncle Funky's Daughter Soul Bounce Texture Defining Mousse | AJ10: FALSE | AL10: Lock in hold, boost shine, amplify volume and define texture with Uncle Funky's Daughter honey mousse, quinoa & keratin formulated texture defining mousse. It create a touchable hold which enhances shine and texture without crunch or build-up. Weather you are setting styling, enhancing curls or adding volume this mousse gives a flawless result. | AM10: 1901 | AY10: Enjoy this range of naturally formulated products crafted to satisfy every curl and enhance and celebrate your natural curl pattern. <br> This range includes the infamous Curly Magic Curl Stimulator. Uncle Funky's Daughter also commonly known as UFD is created with the finest natural ingredients to promote moisture, hydration, curl formation and curl protection.<br> | AZ10: Uncle Funky's Daughter | BA10: Divide freshly cleansed and conditioner hair into sections. Apply a liberal amount to wet or dry hair combing or fingering through from root to end. Style as desired. Allow hair to dry naturally or use a diffuser or hood dryer. How it works: This fast drying, texture-defining mousse locks in long-lasting hold, boosts shine, amplifies volume, and enchances texture & definition. | BB10: Water (Aqua), Honey (Mel), Oleth-20, Cocamidopropyl Betaine, Polyquaternium-55, PVP, Fragrance, (Parfum), Phenoxyethanol, Ethylhexylglycerin, Polysorbate 20, Hydrolyzed Quinoa, Hydrolyzed Keratin, Tocopheryl Acetate, Citric Acid, Disodium EDTA. | BN10: camille-rose-curl-maker; uncle-funkys-daughter-curly-magic | BP10: only manual | BS10: kg | BU10: 29.6 | BV10: active
A11: =S11 -> TRX-AVCP-237 | B11: treluxe-soothe-restore-aloe-vera-curl-primer | C11: TréLuxe Aloe Vera Curl Primer | D11: <p>Save time on washday, and throughout the week! TréLuxe innovative Aloe Vera Curl Primer:</p> <p><span style="font-weight: 400;">✔️</span>reduces detangling time by up to 70%,</p> <p><span style="font-weight: 400;">✔️</span>smooths and defines curls for easier application of styling products,</p> <p><span>✔️</span>reduces the amount of water needed to refresh curls between wash days,</p> <p><span>✔️</span>decreases drying time without sacrificing moisture.</p> <p>This is the beginning of long-lasting, frizz-free curl definition that you no longer have to work for!</p> <p><span style="font-weight: 400;"><strong>How it works:</strong><span> </span>The primer's plant-based ingredients help smooth, detangle, moisturize, and soften your waves and curls to extend wash day results, and save time when refreshing. The extreme slip makes detangling a breeze; and well-defined curls are quickly served up without weighing down delicate strands, due to the lightweight formula. </span></p> <p><span style="font-weight: 400;"><strong>Can be used as</strong><span> </span>a: Pre-Style Primer | Pre-poo Detangler | Moisturizing/Curl Clumping Refresher </span></p> | E11: TréLuxe | F11: Uncategorized | G11: Moisturizers & Leave - Ins | H11: Aloe Vera, CG Approved, CG Method, CGM, CGM Approved, Curl clumping refresher, Curl Defining, Curl definition, Curl primer, curls, Curly Hair, detangler, Hair Primer, High Porosity Essentials, Hydrating, Moisturizer, Natural, Natural Hair, New Arrivals, Treluxe, Vegan, Vegan Hair Care | I11: TRUE | J11: Size | K11: 8 Fl oz | S11: TRX-AVCP-237 | T11: 440 | U11: shopify | V11: deny | W11: manual | X11: 95 | Z11: TRUE | AA11: TRUE | AF11: 851533006065 | AG11: https://cdn.shopify.com/s/files/1/0504/5187/3989/files/AEF5802C-35D7-4E1A-90E5-8A82F2402369.png?v=1741151047 | AH11: 1 | AI11: TréLuxe Aloe Vera Curl Primer | AJ11: FALSE | AY11: TréLuxe products were created to solve the curly hair woes of dryness, frizz, weak strands, and dull hair using premium quality natural ingredients and Active Botanical blends that moisturize, strengthen, and define curly and wavy hair.<br> No parabens, No silicones, No phthalates, No sulfates, No artificial colors, Gluten-free, Cruelty-free | AZ11: TréLuxe | BA11: On Wash Day: <br> cleanse and rinse hair and scalp, optional: apply Untie the Knot Nourishing Leave-In Conditioner if hair is prone to dryness and more moisture is needed while hair is still wet, apply Aloe Vera Curl Primer to your waves or curls, starting with a quarter sized amount. <br> <br> Evenly distribute product through hair to detangle knots and smooth strands. apply styling product(s) <br> <br> To Refresh between Wash Days:<br> <br> Apply to dry, damp, or wet hair, to increase moisture and define curls between wash days. <br> <br> Evenly distribute product through hair *Aloe Vera Curl Primer can be left on, or rinsed out. <br> <br> **Best used on hair and scalp that is cleansed at least once per week. <br> | BB11: Water (Aqua), Aloe Barbadensis (Aloe Vera) Leaf Juice, Glycerin, PEG-40 Hydrogenated Castor Oil, Ascorbic Acid (Vitamin C), Polyquaternium-37, Tocopheryl (Vitamin E) Acetate, Menthyl Ethylamido Oxalate, Hydrogenated Castor Oil/Sebacic Acid Copolymer, Sorbitol, Guar Hydroxypropyltrimonium Chloride, Citric Acid, Potassium Sorbate, Sodium Benzoate, Polysorbate 20, PEG-45m, Fragrance (Parfum), Phenoxyethanol, Caprylyl Glycol, Sorbic Acid | BS11: kg | BU11: 42.02 | BV11: active
A12: =S12 -> UFD-UCUGK | B12: uncle-funkys-daughter-ultimate-kinky-curly-discovery-kit | C12: Uncle Funky's Daughter Ultimate Curly Girls Kit | D12: <p><strong>Best Sellers Sample Pack </strong></p> <p>The best-selling Uncle Funky Daughter’s products together at last! </p> <p>Pack includes 1 bottle each of Midnite Train Leave-in Conditioner, Supercurl Miracle Moisture Crème, Extra Butter Curl Forming Crème, Curly Magic Curl Stimulator, and Thirsty Curls Leave-In Curl Revitalizer, all in 2 ounce trial sizes.</p> <p><strong>How it works</strong></p> <ul> <li>Midnite Train strengthens tresses and promotes growth</li> <li>Supercurl stretches curls, adds shine &amp; hydrates</li> <li>Extra Butter creates definition &amp; shine for lasting styles</li> <li>Curly Magic provides a firm hold, shine &amp; definition</li> <li>Thirsty Curls revives the bounce in frizzy, fallen curls</li> </ul> | E12: Uncle Funky's Daughter | F12: Uncategorized | G12: Hair care | H12: Bundle Set, CG Approved, CGM, CGM Approved, Colour Safe, Curl Defining, Curl definition, curls, Curly Hair, discovery kit, Hair Styling, Hydrating Conditioner, Kid Safe, leave-in Conditioner, Mini, Mini Size, Moisture Rich, Natural, Natural Hair, Styler, Styling, Styling Cream, Sulfate - Free, Travel Kit | I12: TRUE | J12: Size | K12: 2 oz | S12: UFD-UCUGK | T12: 1200 | U12: shopify | V12: deny | W12: manual | X12: 100 | Z12: TRUE | AA12: TRUE | AF12: 861916000122 | AG12: https://cdn.shopify.com/s/files/1/0504/5187/3989/files/FED42630-563E-48E4-9FE6-B96BDF6E9DE9.png?v=1739809064 | AH12: 1 | AI12: Uncle Funky's Daughter Midnite Train, Supercurl, Extra Butter, Curly Magic and Thirsty Curls | AJ12: FALSE | AL12: Now in one convenient trial-size bundle! Your uncle funky's daughter product perfect for trying, travelling or gifting. This pack houses the 5 best selling curl essentials of 2oz each which provide stretcjes curls, add shine, delivers intense hydration, provide firm hold and frizz control | AY12: Enjoy this range of naturally formulated products crafted to satisfy every curl and enhance and celebrate your natural curl pattern. <br> This range includes the infamous Curly Magic Curl Stimulator. Uncle Funky's Daughter also commonly known as UFD is created with the finest natural ingredients to promote moisture, hydration, curl formation and curl protection.<br> | AZ12: Uncle Funky's Daughter | BA12: Directions Step 1: Lightly Spray the Scalp & Hair with Midnite Train Leave-in Conditioner Step 2: Type 3 Naturals: Apply Supercurl Miracle Moisture Crème from Root to Ends in Sections| Type 4 Naturals: Apply Extra Butter Brilliant Shine Crème from Root to Ends in Sections Step 3: Apply Curly Magic Curl Stimulator in Sections from Root to End (Note: A Little Dap Will Do Ya!) Step 4: Style as Desired. Diffuse or Air Dry Day 2 or 3: Lightly Spray Thirsty Curls Revitalizer Spray onto Tresses to Revive Curls | BB12: Midnite Train: Water, Glycerin, Aloe Barbadensis Leaf Juice, Polysorbate 20, Olea Europaea (Olive) Fruit Oil, Urtica Dioica (Nettle) Extract, Anthemis Nobilis Flower Extract, Symphytum Officinale Leaf Extract, Calendula Officinalis Flower Extract, Salvia Officinalis (Sage) Extract, Rosmarinus Officinalis (Rosemary) Leaf Extract, Equisetum Arvense Extract, Mentha Piperita (Peppermint) Leaf Extract, Arctium Lappa Root Extract, Kelp Extract, Honey, Sodium PCA, Sea Salt, Citric Acid, Panthenol, Potassium Sorbate, Sodium Hydroxymethylglycinate, Fragrance. Supercurl Moisture Creme: Water, Glycine Soja (Soybean) Oil, Glycerin, Cocos Nucifera (Coconut) Oil, Honey, Polymide-1, Caprylic/Capric Triglyceride, Butyrospermum Parkii (Shea Butter), Fragrance, Cetearyl Alcohol, Ceteareth-20, Glyceryl Stearate, Olea Europaea (Olive) Fruit Oil, Aloe Barbadensis (Aloe Vera) Leaf Extract, Prunus Amygdalus Dulcis (Sweet Almond) Oil, Macadamia Ternifolia (Macadamia) Seed Oil, Potassium Hydroxide, Xanthan Gum, Carbomer, Tetrasodium EDTA, Phenoxyethanol, Caprylyl Glycol, Potassium Sorbate, Caramel. Extra Butter Curl Foaming Creame: Water, Cocos Nucifera (Coconut) Oil, Glycerin, Elaeis Guineensis (Palm) Kernel Oil, Butyrospermum Parkii (Shea Butter), Glyceryl Stearate, Stearic Acid, Cetearyl Alochol, Organic Aloe Barbadensis (Aloe Vera) Leaf Extract, Caprylic/Capric Tryglyceride, Prunus Amygdalus Dulcis (Sweet Almond) Oil, Macadamia Ternifolia (Macadamia) Seed Oil, Fragrance, Potassium Hydroxide, Xanthan Gum, Carbomer, Phenoxyethanol, Caprylyl Glycol, Potassium Sorbate, Tetrasodium EDTA. Curly Magic: Water, Glycerin, Aloe Barbadensis (Aloe Vera) Leaf Juice*, Simmendsia Chinensis (Jojoba) Seed Oil, Hydrolyzed Wheat Protein, Althaea Officinalis (Marshmallow) Root Extract, Urtica Dioica (Nettle) Extract, Equisetum Arvense (Horsetail) Extract, Tocopherol (Vitamin E), Phenoxyethanol, Ethylhexylglycerin, Fragrance *Organically Sourced Thirsty Curls: Water, Polysorbate 20, Glycerin, Cetrimonium Chloride, Polyquatemium-11, PEG-8, Cocos Nucifera (Coconut) Milk, Urtica Dioica (Nettle) Extract, Anthemis Nobilis (Chamomile) Flower Extract, Symphytum Officinale (Comfrey) Leaf Extract, Calendula Officinalis (Marigold) Flower Extract, Salvia Officinalis (Sage) Leaf Extract, Rosmarinus Officinalis (Rosemary) Leaf Extract, Equisetum Arvense (Horsetail) Leaf Extract, Sodium Hyaluronate, Sodium PCA, Panthenol, Magnesium Sulfate, PEG-12 Dimethicone, Citric Acid, Potassium Sorbate, Phenoxyethanol, Caprylyl Glycol, Sodium Hydroxymethylglycinate, Fragrance. | BS12: kg | BU12: 40.37 | BV12: active
A13: =S13 -> DUO-CRSCU-100 | B13: the-doux-crazy-sexy-curl-honey-setting-foam | C13: The Doux Crazy Sexy Curl Honey Setting Foam | D13: <p><span>WHAT IT DOUX? “What about your coils?!?” This ALL IN 1 Styler conditions, detangles, defines and sets wash &amp; go’s…(*catches breath*), twist-outs, braids and TWA’s in one step! Fast-drying with a strong, but flexible hold. No frizz. No flaking. No cap! Just #Science</span></p> <p><span>WHAT’S GOOD?</span></p> <ul> <li> <span>Honey: Fights Frizz. </span><span>Smells good.</span> </li> <li><span>Aloe: Moisturizes + Hydrates hair</span></li> <li><span>Bamboo: Strengthens + Holds</span></li> </ul> | E13: The Doux | F13: Health & Beauty > Personal Care > Hair Care > Hair Styling Products | G13: Styler | H13: Curl Definer, Curl Defining, Curl defining mousse, Curl definition, Curl Styling, Curly Hair, flexible hold, Hair Styling, Kid Safe, Mummy & Me Edit, Natural, Natural Hair, New Arrivals, Protective Styling, Styler, Styling, Styling Foam, Styling Mousse, Sulfate - Free, The Doux, The Doux Crazy Sexy Curl Setting Foam, Twist out, Twists, Wash- n -go | I13: TRUE | J13: Size | K13: 3.4 oz | S13: DUO-CRSCU-100 | T13: 230 | U13: shopify | V13: deny | W13: manual | X13: 45 | Z13: TRUE | AA13: TRUE | AF13: 850031703476 | AG13: https://cdn.shopify.com/s/files/1/0504/5187/3989/files/76A827DB-DDEF-421C-9F3C-C58DEF4C97FF.jpg?v=1748263840 | AH13: 1 | AI13: The Doux Bee Girl Honey Curl Custard | AJ13: FALSE | AL13: The Doux Crazy Sexy Setting Foam: Discover the multi purpose styling foam that fights frizz, detangles, hydrates & defines curls. for twist/braids out, Twa | AM13: 1901 | AY13: The Doux is an award winning brand of super-fresh, texture focused solutions inspired by the life of a stylist and love for the culture. Merging old-school flava with new-school science. The Doux developed a range of simple, multi-functional formulas designed to put an end to the complicated regimens and conflicting information that are shattering your confidence. | AZ13: The Doux | BA13: DOUX YOU: For best results, DO NOT apply oil to the hair before applying this product. <br> We mean it! <br> Apply a juicy amount to clean, damp hair in small sections, smoothing from roots to ends. <br> Air dry, hood dry, or diffuse. <br> Allow hair to dry 100% before separating curls. | BB13: Aqua (Water, Eau), Polyquaternium-55, Cocamidopropyl Hydroxysultaine, Aloe Barbadensis Leaf Juice, Panthenol, Pvp, Hydroxypropyltrimonium Honey, Bambusa Vulgaris (Bamboo) Extract, Propanediol, Disodium Edta, Silk Amino Acids, Tocopheryl Acetate, Polysorbate 20, Ethylhexylglycerin, Oleth-20, Parfum (Fragrance), Glycereth-2 Cocoate, Phenoxyethanol, Sorbic Acid, Caramel, Benzoic Acid, Coumarin | BN13: the-doux-bee-girl-honey-curl-custard | BP13: only manual | BR13: https://cdn.shopify.com/s/files/1/0504/5187/3989/files/09042FD7-14A0-4BA8-BE34-18A75278C142.webp?v=1748263901 | BS13: kg | BU13: 21.98 | BV13: active
A14: =S14 -> DUO-FFHPC-237 | B14: the-doux-fast-forward-heat-prep-conditioner | C14: The Doux Fast Forward Heat Prep Conditioner | D14: <p>A silicone free and curl-safe conditioner with real heat protection. A Must- Have in the<br>Middle Eastern Climate!</p> <p>Powered by bonding technology, this prep treatment smooths the cuticle and restores hair<br>elasticity, blocks humidity, and protects against heat up to 450°F. Ideal for softening and<br>detangling curls before stretching or styling.</p> | E14: The Doux | F14: Health & Beauty > Personal Care > Hair Care > Shampoo & Conditioner | G14: Conditioner | H14: Chemically Treated Hair, Colour Safe, Conditioner, Curly Hair, Hair Strengthening, High Porosity Essentials, Natural, Natural Hair, New Arrivals, Rinse out Conditioner, Strengthening Conditioner, Strengthening Treatment, Sulfate - Free, The Doux | I14: TRUE | J14: Size | K14: 8 oz | S14: DUO-FFHPC-237 | T14: 440 | U14: shopify | V14: deny | W14: manual | X14: 85 | Z14: TRUE | AA14: TRUE | AF14: 850031703827 | AG14: https://cdn.shopify.com/s/files/1/0504/5187/3989/files/0340F188-EC9B-4B89-8669-59D3C4758D0E.webp?v=1748010431 | AH14: 1 | AI14: The Doux Fast Forward Heat Prep Conditioner | AJ14: FALSE | AL14: Discover The Doux Fast Forward Heat Prep Conditioner: A silicone free instant conditioner to strengthen hair, detangle & heat protectant. For High porosity hair | AM14: 6017 | AY14: The Doux is an award winning brand of super-fresh, texture focused solutions inspired by the life of a stylist and love for the culture. Merging old-school flava with new-school science. The Doux developed a range of simple, multi-functional formulas designed to put an end to the complicated regimens and conflicting information that are shattering your confidence. | AZ14: The Doux | BA14: DOUX YOU: After cleansing with The Doux PRESS REWIND Curl Retention Shampoo™, apply a generous amount from scalp to ends. <br> Gently detangle with fingers or a detangling tool, starting at the ends and working up toward the scalp. <br> Allow it to sit for 3-5 minutes, then rinse thoroughly. | BB14: Water (Aqua), Cetearyl Alcohol, Glycerin, Butyrospermum Parkii (Shea) Butter, C13-15 Alkane, Polyquaternium-37, Aminoethylaminopropyl Dimethicone, Oenocarpus Bataua Fruit Oil, Behentrimonium Methosulfate, Cereus Grandiflorus (Cactus) Flower Extract, Butylene Glycol, Hydrolyzed Quinoa, Aloe Vera Callus Extract (Stem Cell), Hydrolyzed Soy Protein, Propylene Glycol, Dicaprylate/Dicaprate, Phenethyl Alcohol, Cetrimonium Chloride, Brassica Campestris/Aleurites Fordi Oil Copolymer, Fragrance, PPG-1 Trideceth-6, Hydrolyzed Vegetable Protein PG-Propyl Silanetriol, Tocopheryl Acetate, Caprylhydroxamic Acid, Arginine, Alcohol, Aspergillus Ferment, Lactic Acid, Disodium EDTA, Alanine, Aspartic Acid, Glutamic Acid, Histidine, Isoleucine, Leucine, Lysine, Phenylalanine, Proline, Serine, Threonine, Tyrosine, Valine, Ananas Sativus (Pineapple) Fruit Extract, Stearalkonium Chloride, Dimethyl Stearamine. | BN14: the-doux-press-rewind-curl-rentention-shampoo; the-doux-bananas-xtreme-hold-hair-gel | BP14: only manual | BS14: kg | BU14: 40.18 | BV14: active
A15: =S15 -> DUO-PRCRS-237 | B15: the-doux-press-rewind-curl-rentention-shampoo | C15: The Doux Press Rewind Curl Retention Shampoo | D15: <p>Bonding-powered reset for curls that stretch + snap back.</p> <p>Bonding-powered reset for curls that stretch + snap back Formulated with DOUX-plex™ bonding tech, this shampoo strengthens while it gently cleanses, blocking humidity and restoring elasticity so curls stay soft, bouncy and frizz free, whether straightened or naturally curly.</p> | E15: The Doux | F15: Uncategorized | G15: Shampoo & Cleanser | H15: Chemically Treated Hair, cleanser, Cleansing, Cleansing Shampoo, Colour Safe, Colour Treated Hair, curls, Curly Hair, Detangling, Detangling Shampoo, Gentle Cleanser, Gentle Cleansing, Gentle Shampoo, Healthy Scalp, High Porosity Essentials, Moisture Rich, Moisturizing Shampoo, Natural, Natural Hair, New Arrivals, Strengthening Shampoo, The Doux | I15: TRUE | J15: Size | K15: 8 oz | S15: DUO-PRCRS-237 | T15: 440 | U15: shopify | V15: deny | W15: manual | X15: 85 | Z15: TRUE | AA15: TRUE | AF15: 850031703810 | AG15: https://cdn.shopify.com/s/files/1/0504/5187/3989/files/B2230D91-6E18-4A0E-9BEE-C9C730044F20.webp?v=1748010350 | AH15: 1 | AI15: The Doux Press Rewind Curl Retention Shampoo | AJ15: FALSE | AL15: The Doux Press Rewind Curl Retention Shampoo: A Gentle shampoo that is Humid resistant with bonding tech to reset curls. Gentle cleanser, restores elasticity | AY15: The Doux is an award winning brand of super-fresh, texture focused solutions inspired by the life of a stylist and love for the culture. Merging old-school flava with new-school science. The Doux developed a range of simple, multi-functional formulas designed to put an end to the complicated regimens and conflicting information that are shattering your confidence. | AZ15: The Doux | BA15: Rinse hair with warm water until fully saturated. <br> Apply a generous amount, working through from scalp to ends. <br> Leave in for 2-3 minutes. Rinse and repeat. <br> Follow with The Doux FAST FORWARD Heat Prep Conditioner. <br> **For best results, we recommend applying this product to hair free of heavy waxes or oil-based stylers.** | BB15: Water (Aqua), SodiumC14-16 Olefin Sulfonate, Cocamidopropyl Betaine, Quaternium-91, Glycerin, Guar Hydroxypropyltrimonium Chloride, Hydrolyzed Vegetable Protein PG-Propyl Silanetriol, Aloe Vera Callus Extract (Stem Cell), Aspergillus Ferment, Sodium Cocoyl Amino Acids, Phenethyl Alcohol, Fragrance, Cetrimonium Chloride, PEG-6 Caprylic/Capric Glycerides, Cereus Grandiflorus (Cactus) Flower Extract, PEG-150 Pentaerythrityl Tetrastearate, Potassium Dimethicone PEG-7 Panthenyl Phosphate, Caprylhydroxamic Acid, Arginine, Sodium Hydroxide, C13-15 Alkane, Brassica Campestris/Aleurites Fordi Oil Copolymer, Oenocarpus Bataua Fruit Oil, PPG-3 Benzyl Ether Myristate, Lactic Acid, Ananas Sativus (Pineapple) Fruit Extract, Tocopheryl Acetate, Hydrolyzed Soy Protein. | BN15: the-doux-fast-forward-heat-prep-conditioner; the-doux-bananas-xtreme-hold-hair-gel | BP15: only manual | BS15: kg | BU15: 40.18 | BV15: active
A16: =S16 -> DUO-BPDG-473 | B16: the-doux-big-poppa-defining-gel | C16: The Doux Big Poppa Defining Gel | D16: <p>A one-and-done favorite for juicy definition. The humidity resistant and frizz fighting<br>formula you need for defined curls that last in the Middle East!</p> <p>This anti-shrinkage styling gel locks in curl definition without flakes or stiffness. Designed<br>to deliver a moisturized hold in one step for long-lasting shine and definition.</p> | E16: The Doux | F16: Health & Beauty > Personal Care > Hair Care > Hair Styling Products | G16: Styler | H16: Best seller, bestseller, Bestsellers, Chemically Treated Hair, Colour Safe, Colour Treated Hair, Coloured Hair, Curl Definer, Curl Defining, Curl defining gel, Curl definition, Curly Hair, defining gel, Edge Gel, Frizz control, Hair Styling, Humidity resistant, Natural, Natural Hair, New Arrivals, Styler, Styling, Styling Gel, Sulfate - Free, The Doux | I16: TRUE | J16: Size | K16: 16 oz | S16: DUO-BPDG-473 | T16: 880 | U16: shopify | V16: deny | W16: manual | X16: 70 | Z16: TRUE | AA16: TRUE | AF16: 850031703001 | AG16: https://cdn.shopify.com/s/files/1/0504/5187/3989/files/3924D415-214E-41F9-850E-4282D0F3E00F.webp?v=1746808769 | AH16: 1 | AI16: The Doux Big Poppa Defining Gel | AJ16: FALSE | AL16: The Doux Big Poppa Defining Gel: The Humid resistant and frizz fighting gel to define curls without flakes, lock in moisture and works well in the Middle East | AM16: 1901 | AY16: The Doux is an award winning brand of super-fresh, texture focused solutions inspired by the life of a stylist and love for the culture. Merging old-school flava with new-school science. The Doux developed a range of simple, multi-functional formulas designed to put an end to the complicated regimens and conflicting information that are shattering your confidence. | AZ16: The Doux | BA16: DOUX YOU: Apply to freshly washed, clean, wet, product-free hair in small sections from roots to ends. <br> Use alone or top it off with a small amount of MOUSSE DEF Texture Foam for added humidity resistance. <br> Air dry or diffuse, avoid touching it until 100% dry. We mean it. Don’t touch. <br> Once dry, fluff & style away. <br> Mean it. Don’t touch. Once dry, fluff & style away. | BB16: Water, Glycerin, PPG-5-Ceteth-20, PVP, Polysorbate 20, Carbomer, Orbignya Oleifera Seed Oil, Copaifera Officinalis (Balsam Copaiba) Resin, Hydrolyzed Keratin, Fragrance, Phenoxyethanol, Caprylyl Glycol, Ethylhexylglycerin, Aminomethyl Propanol, Fragrance (Parfum). | BD16: 1 | BN16: the-doux; the-doux-mousse-def-texture-foam | BP16: only manual | BS16: kg | BU16: 33.87 | BV16: active
A17: =S17 -> DUO-DMTF-207 | B17: the-doux-mousse-def-texture-foam | C17: The Doux Mousse Def Texture Foam | D17: <p>The Curl Defining Mousse Of The Season!</p> <p>The award-winning light weight, foaming styler delivers definition, flexible hold, soft shine and faster drying with zero crunch. Loved for creating bouncy sleek long-lasting styles with no flakes or build-up.</p> <p>Mousse Def is going viral for a reason, grab it now while it lasts.</p> | E17: The Doux | F17: Health & Beauty > Personal Care > Hair Care | G17: Styler | H17: Best seller, bestseller, Bestsellers, Colour Treated Hair, Coloured Hair, Curl Styling, Curly Hair, Foam, Hair Styling, Low Porosity Essentials, Natural, Natural Hair, New Arrivals, Protective Styling, Styler, Styling, Styling Foam, Styling Mousse, Sulfate - Free, The Doux, Twist out, Twists | I17: TRUE | J17: Size | K17: 7 oz | S17: DUO-DMTF-207 | T17: 340 | U17: shopify | V17: deny | W17: manual | X17: 85 | Z17: TRUE | AA17: TRUE | AF17: 850031703063 | AG17: https://cdn.shopify.com/s/files/1/0504/5187/3989/files/C22C6FB5-5764-4E84-9F0F-7B508441D301.png?v=1746808389 | AH17: 1 | AI17: The Doux Def Mousse Texture Foam | AJ17: FALSE | AK17: The Doux Mousse Def Texture Foam | The Best Curly Hair Mousse | AL17: The Curl Defining Mousse Of The Season! Award-winning lightweight, foaming styler delivers definition, flexible hold, shine and faster drying with zero crunch. | AM17: 4211 | AY17: The Doux is an award winning brand of super-fresh, texture focused solutions inspired by the life of a stylist and love for the culture. Merging old-school flava with new-school science. The Doux developed a range of simple, multi-functional formulas designed to put an end to the complicated regimens and conflicting information that are shattering your confidence. | AZ17: The Doux | BA17: DOUX YOU: Curly styles: Distribute liberally through damp hair, smoothing from root to ends.<br> Straight styles: Apply a quarter-sized amount to edges prior to blowing dry for added shine, control, and resistance to humidity. <br> | BB17: Water, Polyquaternium-55, Cocamidopropyl Hydroxysultaine, Aloe Barbadensis Leaf, PVP, Tocopheryl Acetate, Citric Acid, Silk Amino Acids, Polysorbate 20, Ethylhexylglycerin, Oleth-20, Fragrance (Parfum), Glycereth-2 Cocoate, Isostearamidopropyl Morpholine Lactate, Phenoxyethanol, Benzoic Acid, Disodium EDTA | BN17: the-doux; the-doux-big-poppa-defining-gel; uncle-funkys-daughter-curly-magic; innersense-i-create-hold; innersense-i-create-shine | BP17: only manual | BR17: https://cdn.shopify.com/s/files/1/0504/5187/3989/files/C22C6FB5-5764-4E84-9F0F-7B508441D301.png?v=1746808389 | BS17: kg | BU17: 38.71 | BV17: active
A18: =S18 -> DOU-DMTF-100 | B18: the-doux-mousse-def-texture-foam | K18: 3.4 oz | S18: DOU-DMTF-100 | T18: 0 | U18: shopify | V18: deny | W18: manual | X18: 45 | Z18: TRUE | AA18: TRUE | AF18: 850031703469 | AG18: https://cdn.shopify.com/s/files/1/0504/5187/3989/files/4B9DAF1E-DB56-47E5-8C74-180B7E497CE6.webp?v=1746808274 | AH18: 2 | BR18: https://cdn.shopify.com/s/files/1/0504/5187/3989/files/4B9DAF1E-DB56-47E5-8C74-180B7E497CE6.webp?v=1746808274 | BS18: kg | BU18: 21.98
A19: =S19 -> MIE-PHLIC-355 | B19: mielle-pomegranate-honey-leave-in-conditioner-1 | C19: Mielle Pomegranate & Honey Leave-In Conditioner (Not so Perfect) | D19: <p><strong>**Product content is full, however the pump is missing - images attached**</strong></p> <p>Start your hair care routine the right way with Mielle’s Pomegranate &amp; Honey Leave-In Conditioner. With a blend of natural ingredients like babassu oil and citrus extracts, the nourishing formula adds penetrating moisture to every hair strand and seals it in for lasting hydration. It also provides natural shine, prevents frizz, and makes detangling easier without weighing down your hair.</p> <p> </p> | E19: Mielle Organics | F19: Health & Beauty > Personal Care > Hair Care > Hair Styling Products | G19: Leave - In | H19: Bestsellers, CG Approved, CG Method, CGM Approved, Colour Treated Hair, Curl Defining Leave-in, Curly Hair, detangler, Detangling, Kid Safe, Leave In, leave-in Conditioner, Mielle, Mielle Organics, Moisturizer, Mummy & Me Edit, Natural, Natural Hair, Not so perfect, The Mummy & Me Edit | I19: TRUE | J19: Size | K19: 12 fl oz | S19: MIE-PHLIC-355 | T19: 540 | U19: shopify | V19: deny | W19: manual | X19: 55 | Z19: TRUE | AA19: TRUE | AG19: https://cdn.shopify.com/s/files/1/0504/5187/3989/files/2730841A-434C-4514-BCA5-7D7A2D68FB34.png?v=1737714276 | AH19: 1 | AJ19: FALSE | AM19: 1901 | AY19: Mielle Organics a natural haircare brand that delivers on its promises of healthier, stronger and more hydrated hair through use of organic ingredients, products have been uniquely formulated to deliver hydration, moisture and definition.<br> | AZ19: Mielle | BA19: Simply apply after conditioning, work through to the tips, and style however you like! A great leave-in conditioner is the first and most vital step when styling. <br> The Pomegranate &amp; Honey Leave-In Conditioner is the first step in the PRIME + DEFINE system. Follow up with one of three styling products in this range - Curl Smoothie, Twisting Souffle or Coil Sculpting Custard. | BB19: Water (Aqua, Eau), Behentrimonium Methosulfate, Cetyl Alcohol, Butylene Glycol, Cetyl Alcohol, Glycerin, *Orbignya Oleifera (Babassu) Oil, *Mauritia Flexuosa (Buriti) Fruit Oil, *Copaiferi Officinalis (Balsam Copaiba) Resin, *Astrocaryum Murumuru Seed Butter, Vaccinium Myrtillus Fruit Extract, Saccharum Officinarum (Sugar Cane) Extract, Acer Saccharinum (Sugar Maple) Extract, Citrus Aurantium Dulcis (Orange) Fruit Extract, Citrus Medica Limonum Citrus Medica Limonum (Lemon) Fruit Extract, Punica Granatum (Pomegranate) Extract, Betaine, Hexylene Glycol, Honey (Mel, Miel), Pyrus Malus (Apple) Fruit Extract, Camellia Sinensis Leaf Extract, Hexapeptide-11, Citric Acid, Fragrance (Parfum), Phenoxyethanol, Benzoic Acid, Ethylhexylglycerin, Glycereth-2 Cocoate<br> *Certified Organic Ingredients | BS19: kg | BV19: active
A20: =S20 -> ENI-DFT-59 | B20: deep-follicle-treatment-by-healthy-hair-studio-by-enitan | C20: Deep Follicle Treatment by Healthy Hair Studio by Enitan - Not So Perfect | D20: <p><strong>**Product is in perfect condition only defect is the packaging is missing**</strong></p> <p>Deep Follicle treatment is a potent ayurvedic treatment formulated to deliver root stimulating herbs to the follicles carried by cannabis sativa seed oil obtained by cold pressing the seeds of cannabis sativa. This treatment helps to improve the health of the connecting tissue that surrounds the root of the hair. If you are experience any form of hair loss or spot balding this treatment delivers on its claims. <br><br></p> <p> </p> <p> </p> | E20: Healthy Hair Studio by Enitan | F20: Health & Beauty > Personal Care > Hair Care | G20: Oil | H20: CG Approved, CGM Approved, Colour Treated Hair, Hair Growth, Hair Loss, Hair Treatment, Healthy Scalp, Length Retention, Scalp Care, Scalp Massage, shop all | I20: TRUE | J20: size | K20: 3.5 fl | S20: ENI-DFT-59 | T20: 240 | U20: shopify | V20: deny | W20: manual | X20: 105 | Z20: TRUE | AA20: TRUE | AG20: https://cdn.shopify.com/s/files/1/0504/5187/3989/files/C9C43EB9-345D-40C1-B2E2-BF80CAE7BEAA.png?v=1735618445 | AH20: 1 | AJ20: FALSE | AM20: 486 | AY20: Healthy Hair Studio by Enitan was founded by Enitan Agidee who boasts years of experience as a trichologist and hair educator. <br> Healthy Hair Studio by Enitan is a natural, holistic hair care brand centered around maintaining healthy textured hair. <br> Each product has been carefully crafted and scientifically proven to support, maintain and promote growth of natural-textured hair. | AZ20: Healthy Hair Studio By Enitan | BA20: For thinning spots - Massage directly but carefully on the thinning areas or hairline/crown daily every two days. <br> To stimulate entire scalp - Massage lightly and slowly mid week and the night before your wash day as a therapeutic approach to increase the levels of oxygen to widen the follicles which leads to better quality hair growth.<br> Enitan of the Healthy Hair Studio favours science and healthy hair practices. She advises a minimum can of 6 weeks for substantial results when using the treatment whilst maintaining healthy hair practices for sustained growth. | BB20: Cannabis sativa Seed Oil, Panax ginseng, Centella asiatica, Bacopa monnieri, Eclipta prostrata, Rosmarinus officinalis and Red thyme | BS20: kg | BV20: active
A21: =S21 -> INN-PHHB-295 | B21: innersense-pure-harmony-hairbath | C21: Innersense Pure Harmony HairBath | D21: <p><span>A cleansing shampoo for fine to medium hair that enhances volume and shine.</span></p> <p><span>Made with fine to medium textures in mind, this shampoo deeply cleanses hair and leaves it with a weightless bounce and brilliant shine. Its sulfate free (SLS/SLES) formula is crafted with naturally softening cleansers such as Coconut, Rice Bran and Avocado Oil to clarify strands without stripping moisture. Nourishing Shea Butter and Organic Pumpkin Seed Oil smooth frizz and deliver shine, while Quinoa and Rice extracts fortify brittle strands to help reduce breakage.</span></p> <p><span>Best for fine to medium hair.</span></p> <p><span>Fragrance: Orange, Tangerine</span></p> | E21: Innersense Beauty | F21: Health & Beauty > Personal Care > Hair Care > Hair Styling Products | G21: Shampoo & Cleanser | H21: Best seller, bestseller, Bestsellers, CG Approved, CG Method, cgapproved, CGM, CGM Approved, cleanser, Cleansing, Cleansing Shampoo, Colour Safe, Colour Treated Hair, Curly Hair, Fine Hair, Gentle Cleansing, Innersense, innersense Pure Harmony Hair Bath, Kid Safe, Medium Hair, Moisturizing Shampoo, Natural, Natural Hair, Oily Scalp, Sulfate - Free, Weightless Detangler | I21: TRUE | J21: Size | K21: 10 oz | S21: INN-PHHB-295 | T21: 560 | U21: shopify | V21: deny | W21: manual | X21: 120 | Z21: TRUE | AA21: TRUE | AF21: 852415001666 | AG21: https://cdn.shopify.com/s/files/1/0504/5187/3989/files/1B23B4C0-6777-424F-A1A6-5550D410A9B0.png?v=1738318782 | AH21: 1 | AI21: Innersense Pure Harmony HairBath | AJ21: FALSE | AL21: A Gentle cleansing shampoo for fine to medium hair that enhances volume & shine. This shampoo cleanses hair without stripping & leaves it with weightless bounce | AM21: 1901 | AY21: Innersense Organic Beauty is a love story between two seasoned beauty professionals who share a passion for health, hair, beauty and the planet. <br> Founded 2005 to meet the need for clean, pure, organic and non-toxic professional quality hair care products. In doing so, sourcing the highest quality and Certified Organic ingredients, in the purest, most concentrated form has been at the forefront of each product. Innersense have create a complete, award-winning line of safe, sustainable and cruelty free haircare products. | AZ21: Innersense | BA21: Take a deep breath and become present.<br> Apply a small amount of Hairbath to hands and awaken into a light lather. <br> Massage into scalp using fingertips. Rinse thoroughly.<br> Take a moment to appreciate clean hair. | BB21: Water, Aqua- EAU, Cocamidopropyl Hydroxysultaine, Sodium Cocoyl Isethionate, Caprylyl/Capryl Glucoside, Glycerin, Sodium Chloride, Sodium Lauroyl Methyl Isethionate, Butyrosepermum Parkii (Shea Butter), Citrus Aurantium Dulcis (Orange) Peel Oil6, Citrus Medica Limonum (Lemon) Peel Oil, Eucalyptus Globulus (Eucalyptus), Cucurbita Pepo (Pumpkin Seed Oil)*, Hydroxypropyltrimonium Honey, Hydrolyzed Quinoa, Trisodium Ethylenediamine Disuccinate, Sodium Benzoate, Hydrolyzed Rice Protein, Guar Hydroxypropyltrimonium Chloride, Persea Gratissima (Avocado) Oil, Oryza Sativa (Rice) Bran Oil, Camellia Sinensis (Green Tea) Leaf Extract*, Cucumis Sativus (Cucumber) Fruit Extract, Persea Gratissima (Avocado)* Fruit Extract, Mangifera Indica (Mango)* Fruit Extract. *Certified Organic | BI21: other | BN21: innersense-pure-inspiration-daily-conditioner; innersense-detox-hair-mask | BP21: only manual | BS21: kg | BU21: 54 | BV21: active
A22: =S22 -> INN-PHHB-59 | B22: innersense-pure-harmony-hairbath | K22: 2 oz | S22: INN-PHHB-59 | T22: 560 | U22: shopify | V22: deny | W22: manual | X22: 45 | Z22: TRUE | AA22: TRUE | AF22: 852415001673 | BS22: kg | BU22: 54
A23: =S23 -> INN-CCUM-59 | B23: innersense-i-create-curl-memory | C23: Innersense I Create Curl Memory | D23: <p><span>A hydrating styling gelee that provides flexible hold and long lasting curls.</span></p> <p><span data-mce-fragment="1">Create touchable, long lasting curls with this flexible styling gelee that smooths, hydrates and holds in a single step. Its nourishing formula features Bamboo Extract, Sugar Complex and Certified Organic Aloe Vera to provide curl memory, improve manageability and boost moisture.</span></p> <p><span data-mce-fragment="1">Best for coarse, curly and coily hair.</span></p> <p><span data-mce-fragment="1">Fragrance note: Sweet Chamomile </span></p> | E23: Innersense Beauty | F23: Uncategorized | G23: Styler | H23: CG Approved, CG Method, CGM Approved, Coil, Coily Hair, Colour Safe, Curl Defining, Curl definition, curls, Curly Hair, Elongating, flexible hold, Hair Styling, Hydrating, Innersense, Innersense I Create Curl Memory, Kid Safe, Natural, Natural Hair, Styler, Styling, Styling Gel, Sulfate - Free, Vegan, Vegan Hair Care | I23: TRUE | J23: Styler | K23: 2 oz | S23: INN-CCUM-59 | T23: 240 | U23: shopify | V23: deny | W23: manual | X23: 45 | Z23: TRUE | AA23: TRUE | AF23: 810121310892 | AG23: https://cdn.shopify.com/s/files/1/0504/5187/3989/files/33369CE3-3FB4-4F28-BD1E-72CA15F8CA02.png?v=1744098871 | AH23: 1 | AI23: Innersense I Create Curl Memory | AJ23: FALSE | AL23: A hydrating styling gelee that provides flexible hold and long lasting curls. This gelee smooths, hydrates & holds in one step for coarse, curly & coily hair styles | AY23: Innersense Organic Beauty is a love story between two seasoned beauty professionals who share a passion for health, hair, beauty and the planet. <br> Founded 2005 to meet the need for clean, pure, organic and non-toxic professional quality hair care products. In doing so, sourcing the highest quality and Certified Organic ingredients, in the purest, most concentrated form has been at the forefront of each product. Innersense have create a complete, award-winning line of safe, sustainable and cruelty free haircare products. | AZ23: Innersense | BA23: Take a deep breath and become present. Section wet hair.<br> Distribute 1 to 2 pumps into hands and awaken the formula by rubbing palms together. <br>Apply from roots to ends. Diffuse or air dry to define texture and style. <br> Your beautifully styled hair is a reflection of you. | BB23: Water/Aqua/EAU, Sucrose,Xanthan Gum, Glycerine, Aloe Barbadensis Leaf Juice*, Oryza Sativa(Rice) Extract*,Propanediol, Capryloyl Glycerin/Sebacic Acid Copolymer, Diheptyl Succinate, Potassium Sorbate, Sodium Levulinate, Citric Acid, Caprylic/Capric Triglyceride, Citrus Aurantium Dulcis (Orange) Peel Oil, Phylostachys Bambusoides (Bamboo) Extract, Hydroxypropyltrimonium Honey, Sodium Gluconate, Aspalathus Linearis Leaf Extract*, Chamomilla Recutita (Matricaria) Flower Extract*, Eucalyptus Globulus Leaf Extract* Ginkgo Biloba Leaf Extract*, Honey Extract*, Leoconostoc/ Raddish Root Ferment Filtrate, Sorbic Acid, Limonenet. | BN23: innersense-i-create-volume; innersense-quiet-calm-curl-control | BP23: only manual | BR23: https://cdn.shopify.com/s/files/1/0504/5187/3989/files/1F316212-62B3-4CB6-B972-1C3F6C150CD6.png?v=1744098831 | BS23: kg | BU23: 18.35 | BV23: active
A24: =S24 -> INN-CCUM-295 | B24: innersense-i-create-curl-memory | K24: 10 oz | S24: INN-CCUM-295 | T24: 560 | U24: shopify | V24: deny | W24: manual | X24: 120 | Z24: TRUE | AA24: TRUE | AF24: 810121310878 | AG24: https://cdn.shopify.com/s/files/1/0504/5187/3989/files/4146CBEC-2E2F-428A-9668-938CBC5422A1.png?v=1744098871 | AH24: 2 | BR24: https://cdn.shopify.com/s/files/1/0504/5187/3989/files/90EC6880-53A1-44C4-BA48-C24BE8F67EC1.png?v=1744098831 | BS24: kg | BU24: 51.38
A25: =S25 -> INN-RDS-70 | B25: innersense-refresh-dry-shampoo | C25: Innersense Refresh Dry Shampoo | D25: <p><span>A foam-to-powder dry shampoo that nourishes the scalp and hair.</span></p> <p><span>Refresh hair between washes with this propellent free dry shampoo crafted with clean, scalp soothing ingredients. Its foam-to-powder formula uses Tapioca Starch to absorb excess oil, while naturally astringent Witch Hazel helps prevent a powdery residue and soothes the scalp. Hair loving Quinoa and Certified Organic Honey leave hair with body, shine and balanced hydration.</span></p> <p><span>Ideal for all hair types and textures.</span></p> <p><span>Fragrance: Orange, Tangerine</span></p> | E25: Innersense Beauty | F25: Uncategorized | G25: Shampoo & Cleanser | H25: All curl types, CG Approved, CG Method, cgapproved, CGM, CGM Approved, Cleansing, Coloured Hair, Curly Hair, Dry Shampoo, Gentle Cleansing, Healthy Scalp, Natural, Natural Hair, Refresher, Scalp Care, Shampoo, Sulfate - Free | I25: TRUE | J25: Shampoo | K25: 2.37 oz | S25: INN-RDS-70 | T25: 240 | U25: shopify | V25: deny | W25: manual | X25: 95 | Z25: TRUE | AA25: TRUE | AF25: 810121310021 | AG25: https://cdn.shopify.com/s/files/1/0504/5187/3989/files/D5F23067-D49D-4A20-852C-10A9D4E93553.png?v=1738255238 | AH25: 1 | AI25: Innersense Refresh Dry Shampoo | AJ25: FALSE | AL25: A foam-to-powder dry shampoo that nourishes the scalp and hair. Refresh hair between washes with this propellent free dry shampoo. perfect for all hair textures | AY25: Innersense Organic Beauty is a love story between two seasoned beauty professionals who share a passion for health, hair, beauty and the planet. <br> Founded 2005 to meet the need for clean, pure, organic and non-toxic professional quality hair care products. In doing so, sourcing the highest quality and Certified Organic ingredients, in the purest, most concentrated form has been at the forefront of each product. Innersense have create a complete, award-winning line of safe, sustainable and cruelty free haircare products. | AZ25: Innersense | BA25: Separation is natural. Shake well before use. Take a deep breath and become present.<br> Add 1 to 2 pumps into palms and rub together to awaken. <br> Massage into roots, hairline and nape. <br> Air or blow dry to refresh your energy and scalp. | BB25: Water, Hamamelis Virginiana (Witch Hazel) Leaf Extract, Tapioca Starch, Alcohol, Caprylyl/Capryl Glucoside, Citrus Aurantium Dulcis Peel Oil, Caprylic/Capric Triglyceride, Zea Maize (Corn) Starch, Decyl Glucoside, Lauryl Glucoside, Dehydroacetic Acid, Benzyl Alcohol, Galactoarabinan, Pullulan, Glycerin, Xanthan Gum, Potassium Sorbate, Sodium Benzoate, Hydroxypropyltrimonium Honey, Sorbic Acid, Panthenol (Vitamin B-5), Hydrolyzed Rice Protein, Hydrolyzed Quinoa, Chamomilla Recutita (Matricaria) Flower Extract*, Eucalyptus Globulus Leaf Extract*, Ginkgo Biloba Leaf Extract*, Aspalathus Linearis Leaf Extract*, Honey Extract*, Tocopheryl Acetate (Vitamin E), Linalool Ϯ, LimoneneϮ | BS25: kg | BU25: 44.04 | BV25: active
A26: =S26 -> INN-PIDC-295 | B26: innersense-pure-inspiration-daily-conditioner | C26: Innersense Pure Inspiration Daily Conditioner | D26: <p><span>A weightless conditioner for fine to medium hair.</span></p> <p><span>Detangle and smooth fine to medium hair with this conditioner that softens strands with weightless hydration. Its clean, silicone free formula features ingredients such as Rice Bran Oil, Aloe Vera, and Avocado Oil to provide lightweight moisture and leave hair with body. Organic Green Tea douses hair with natural antioxidants to protect against environmental stressors and add lustrous shine.</span></p> <p><span>Best for fine to medium hair.</span></p> <p>Fragrance:<span> Grapefruit, Jasmine</span></p> <p><span>Detangling</span><span></span></p> <p><span>Strengthening</span></p> <p><span>Boosts volume + shine</span></p> | E26: Innersense Beauty | F26: Health & Beauty > Personal Care > Hair Care > Shampoo & Conditioner > Conditioners | G26: Conditioner | H26: CG Approved, CG Method, cgapproved, CGM, CGM Approved, Conditioner, Curly Hair, detangler, Detangling, Fine Hair, Frizz control, hair care, Hair Conditioning, Hair Strengthening, Hair volume, Lightweight, Medium Hair, Moisture Protein Balanced, Moisture Rich, Moisturizing Conditioner, Natural, Natural Hair, Strengthening Conditioner, Strengthening Treatment, Sulfate - Free | I26: TRUE | J26: Conditioner | K26: 10 oz | S26: INN-PIDC-295 | T26: 540 | U26: shopify | V26: deny | W26: manual | X26: 120 | Z26: TRUE | AA26: TRUE | AF26: 852415001611 | AG26: https://cdn.shopify.com/s/files/1/0504/5187/3989/files/7ED1D009-3460-4466-965F-63B8339E3943.png?v=1738318398 | AH26: 1 | AI26: Innersense Pure Inspiration Daily Conditioner | AJ26: FALSE | AL26: A weightless conditioner for fine to medium hair. A Curly hair Conditioner that Detangles, Strengthens, boosts Volume, Shine & Softens the hair strands. | AM26: 543616 | AY26: Innersense Organic Beauty is a love story between two seasoned beauty professionals who share a passion for health, hair, beauty and the planet. <br> Founded 2005 to meet the need for clean, pure, organic and non-toxic professional quality hair care products. In doing so, sourcing the highest quality and Certified Organic ingredients, in the purest, most concentrated form has been at the forefront of each product. Innersense have create a complete, award-winning line of safe, sustainable and cruelty free haircare products. | AZ26: Innersense | BA26: After cleansing, apply 1-2 pumps to palms and emulsify between hands.<br>Take a deep breath and mindfully distribute from mid-lengths to ends using fingertips or comb.<br>Leave on for 1-5 minutes. Rinse thoroughly. <br> Take a moment to appreciate clean, nourished hair. | BB26: Water, Hamamelis Virginiana (Witch Hazel) Leaf Extract, Tapioca Starch, Alcohol, Caprylyl/Capryl Glucoside, Citrus Aurantium Dulcis Peel Oil, Caprylic/Capric Triglyceride, Zea Maize (Corn) Starch, Decyl Glucoside, Lauryl Glucoside, Dehydroacetic Acid, Benzyl Alcohol, Galactoarabinan, Pullulan, Glycerin, Xanthan Gum, Potassium Sorbate, Sodium Benzoate, Hydroxypropyltrimonium Honey, Sorbic Acid, Panthenol (Vitamin B-5), Hydrolyzed Rice Protein, Hydrolyzed Quinoa, Chamomilla Recutita (Matricaria) Flower Extract*, Eucalyptus Globulus Leaf Extract*, Ginkgo Biloba Leaf Extract*, Aspalathus Linearis Leaf Extract*, Honey Extract*, Tocopheryl Acetate (Vitamin E), Linalool Ϯ, LimoneneϮ | BN26: innersense-pure-harmony-hairbath; innersense-detox-hair-mask | BP26: only manual | BS26: kg | BU26: 54 | BV26: active
A27: =S27 -> INN-PIDC-59 | B27: innersense-pure-inspiration-daily-conditioner | K27: 2 oz | S27: INN-PIDC-59 | T27: 540 | U27: shopify | V27: deny | W27: manual | X27: 45 | Z27: TRUE | AA27: TRUE | AF27: 852415001604 | BS27: kg | BU27: 16.2
A28: =S28 -> JES-AIRS-237 | B28: jessicurl-awe-inspiraling-refresher-spray | C28: Jessicurl Awe Inspiraling Refresher Spray | D28: <p><span>Awe Inspiraling Refresher Spray is a mid-day and next day curl refresher that revives curls!</span><br><br><span>It provides hydration, moisture and curl enhancement. It revitalizes your curls by re-activating the styling products that are already in your hair without adding ingredients that provide hold.</span><br><br><span>As a result, you’ll get the revitalized curls that you seek without stickiness or product build-up.</span></p> | E28: Jessicurl | F28: Uncategorized | G28: Conditioner | H28: CG Approved, Chemically Treated Hair, Coily Hair, Curly Hair, Frizz control, Frizz Free, Hair Refresher, Hydrating Hair Refresher, Jessicurl, Low Porosity Essentials, Natural, Natural Hair, Refresh Curls, Refresher, Refreshing Spray, Styler, Styling Cream, Styling Lotion, Sulfate - Free, Summer Curl Edit, Summer hero styler | I28: TRUE | J28: Fragrance | K28: No Fragrance | M28: Size | N28: 8 oz | S28: JES-AIRS-237 | T28: 440 | U28: shopify | V28: deny | W28: manual | X28: 85 | Z28: TRUE | AA28: TRUE | AF28: 851543001111 | AG28: https://cdn.shopify.com/s/files/1/0504/5187/3989/files/9614412E-4D80-4EA6-979C-981A5ED40601.png?v=1738747937 | AH28: 1 | AI28: Jessicurl Awe Inspiraling Refresher Spray | AJ28: FALSE | AL28: Jessicurl Awe Inspiraling Refresher Spray - A curl refreshing spray to revive curls, enhance curls, add hyration & moisture and re-activates styling products | AY28: Whether you have fine waves or tight coils...You have the right to remain curly!<br> Jessicurl products were designed using Naturally Curly’s hair typing system to design products for every type of curl out there, not just curly hair in general. | AZ28: Jessicurl | BA28: Shake bottle and spray lightly onto dry hair. Scrunch with hands to revive droopy curls. An alternate method is to spray it into your hands, rub them together, then scrunch it in that way. If you find you need a bit more hold mid-day or second-day, put a pea sized drop of Confident Coils Styling Solution into your palm, spray with Awe Inspiraling Spray, rub hands together and scrunch. For added volume, flip hair upside down to do this. This stuff is pretty concentrated, so less is more. | BB28: <strong>No Fragrance:</strong> Aqua (Water), Glycerin, Magnesium Sulfate, Aloe Barbadensis (Aloe Vera) Leaf Juice Powder, Simmondsia Chinensis (Jojoba) Seed Oil, Diazolidinyl Urea, Iodopropynyl Butylcarbamate <strong>Island Fantasy :</strong> Aqua (Water), Glycerin, Magnesium Sulfate, Aloe Barbadensis (Aloe Vera) Leaf Juice Powder, Simmondsia Chinensis (Jojoba) Seed Oil, Parfum (Fragrance), Diazolidinyl Urea, Iodopropynyl Butylcarbamate, *Coumarin, *Limonene <br> <br> <strong>Citrus Lavender:</strong> Aqua (Water), Glycerin, Magnesium Sulfate, Aloe Barbadensis (Aloe Vera) Leaf Juice Powder, Simmondsia Chinensis (Jojoba) Seed Oil, Lavandula Officinalis (Lavender) Flower Oil, Citrus Sinensis (Sweet Orange) Peel Oil Expressed, Citrus Paradisi (Grapefruit) Peel Oil, Diazolidinyl Urea, Iodopropynyl Butylcarbamate, *Limonene,* Linalool <br> <div><br></div> *These ingredients are naturally occurring active ingredients found in the essential oils used in some of our products. | BS28: kg | BU28: 28.3 | BV28: active
A29: =S29 -> JES-AIRS-237 | B29: jessicurl-awe-inspiraling-refresher-spray | K29: Citrus Lavender | N29: 8 oz | S29: JES-AIRS-237 | T29: 440 | U29: shopify | V29: deny | W29: manual | X29: 85 | Z29: TRUE | AA29: TRUE | AF29: 851543001074 | BS29: kg | BU29: 28.3
A30: =S30 -> JES-AIRS-237 | B30: jessicurl-awe-inspiraling-refresher-spray | K30: Island Fantasy | N30: 8 oz | S30: JES-AIRS-237 | T30: 440 | U30: shopify | V30: deny | W30: manual | X30: 85 | Z30: TRUE | AA30: TRUE | BS30: kg | BU30: 28.3
A31: =S31 -> CAM-DSM-237 | B31: camille-rose-rosemary-strengthening-mist | C31: Camille Rose Rosemary Strengthening Mist | D31: <p><span>A rosemary hair spray crafted to decrease scalp inflammation, stimulate hair follicles, and promote healthy hair growth.</span></p> <p>Achieve length retention and strengthen hair strands with a blend of pure rosemary oil, peppermint, amla, apigenin, shikakai, and biotin. This formulation is ideal for all hair textures. Nourish your scalp and thicken hair with essential oils and nutrients designed to support your hair health.</p> <p> </p> | E31: Camille Rose | F31: Uncategorized | G31: Oils & Refreshers | H31: bestseller, Bestsellers, BS2022, Camille Rose, CG Approved, Chemically Treated Hair, Colour Safe, Curly Hair, Detangler, Detangling, Detangling Spray, Honey, Kid Safe, Leave In, Moisturizer, Natural, Natural Hair, Nettle, Refresher, Refreshing spray, Styling, Sulfate - Free | I31: TRUE | J31: Size | K31: 8fl oz | S31: CAM-DSM-237 | T31: 440 | U31: shopify | V31: deny | W31: manual | X31: 65 | Z31: TRUE | AA31: TRUE | AF31: 860003058480 | AG31: https://cdn.shopify.com/s/files/1/0504/5187/3989/files/A2DD9A89-A4DE-4BE3-AA0A-D95F88D9C869.png?v=1731998224 | AH31: 1 | AI31: Camille Rose Rosemary Strengthening Mist | AJ31: FALSE | AL31: A well crafted nutrient-rich formula curated to reduce scalp inflammation, stimulate hair follicles, and promote healthy hair growth. Achieve length retention, strengthen hair strands and also nourish the scalp making it ideal for all hair texture. | AY31: Camille Rose Naturals is a trusted source for premium hair and beauty products formulated with gourmet ingredients to provide true nourishment to your strands.<br> <br> Each product is developed with integrity and hand crafted with love. Perfect for all hair types and textures. <br> | AZ31: Camille Rose | BA31: Spray on scalp and strands daily, concentrating on areas where regrowth is desired. <br> May replace water as a refresher on wet or dry hair. <br> For best results, pair with Camille Rose Rosemary Oil Leave In Conditioner | BB31: Water (Aqua), Aloe Barbadensis Leaf Juice, Glycerin, Polysorbate 20, Cetrimonium Chloride, Rosmarinus Officinalis (Rosemary) Leaf Oil, Urtica Dioica (Nettle) Leaf Extract, Melissa Officinalis (Melissa) Leaf Extract, Mentha Piperita (Peppermint) Leaf Extract, Equisetum Arvense (Horsetail) Leaf Extract, Yucca Leaf Extract, Rosmarinus Officinalis (Rosemary) Flower/Leaf/Stem Extract, Ricinus communis (Castor Beans) Oil, Mentha Piperita (Peppermint) Oil, Polyquaternium-37, Phenoxyethanol, Ethylhexylglycerin, and Phthalate-Free Fragrance (Parfum) | BS31: kg | BU31: 24 | BV31: active
A32: =S32 -> ENI-SLS-190 | B32: slippery-lime-shampoo-by-healthy-hair-studio-by-enitan | C32: Slippery Lime Shampoo by Healthy Hair Studio By Enitan | D32: <p>The Slippery Lime Shampoo is scientifically designed to help reduce oxidative stress on the scalp. Through key ingredient Slippery Lime you’ll be left with a cleansed and refreshed scalp and enjoy a soft rinse as well as a deeply moisturising experience.</p> | E32: Healthy Hair Studio by Enitan | F32: Uncategorized | H32: Cleansing Shampoo, Healthy Hair Studio By Enitan, Moisturising Shampoo, Moisturizing Shampoo | I32: TRUE | J32: Title | K32: Default Title | S32: ENI-SLS-190 | T32: 440 | U32: shopify | V32: deny | W32: manual | X32: 95 | Z32: TRUE | AA32: TRUE | AF32: 5060924590068 | AG32: https://cdn.shopify.com/s/files/1/0504/5187/3989/files/A8F13CF3-90B3-47A7-B46D-34557AA6AE4B.webp?v=1731660166 | AH32: 1 | AI32: Slippery Lime Shampoo by Healthy Hair Studio By Enitan | AJ32: FALSE | AL32: Slippery Lime Shampoo by Healthy Hair Studio By Enitan - A gentle sulphate free shampoo that gently cleanses hair & refresh scalp. Helps with Oxidative stress | AY32: Healthy Hair Studio by Enitan was founded by Enitan Agidee who boasts years of experience as a trichologist and hair educator. <br> Healthy Hair Studio by Enitan is a natural, holistic hair care brand centered around maintaining healthy textured hair. <br> Each product has been carefully crafted and scientifically proven to support, maintain and promote growth of natural-textured hair. | AZ32: Healthy Hair Studio by Enitan | BA32: Wet hair and massage on palm for 5 seconds, then apply to scalp and hair to massage and cleanse. <br> Formulated to bring vitality with immediate contact. | BB32: Aqua, Sodium Methyl Cocoyl Taurate, Limonene, Citrus Aurantifolia Oil, Lauryl Glucoside, Sodium Chloride, Baobab extract, Xanthan Gum, Sodium Methyl Oleoyl Taurate, Coco-Glucoside, Benzyl Alcohol, Glycol Distearate, Sodium Lauroyl Sarcosinate, Limonene, Glycerin, Citric Acid, Tocopherol, Dehydroacetic Acid, Sodium Benzoate, Potassium Sorbate. | BN32: inches-conditioned; mighty-moisture-leave-in-moisturiser-by-healthy-hair-studio-by-enitan | BP32: only manual | BS32: kg | BU32: 47.29 | BV32: active
A33: =S33 -> UFD-MTPDC-237 | B33: uncle-funkys-daughter-maximum-thermal-protection-deep-conditioner | C33: Uncle Funky's Daughter Maximum Thermal Protection Deep Conditioner | D33: <p><span>Envelop your hair in the embrace of this silk, bamboo and quinoa-infused deep conditioner. Formulated to replenish moisture, fortify each strand, and reduce breakage, leaving your hair irresistibly soft and strong. </span></p> | E33: Uncle Funky's Daughter | F33: Uncategorized | G33: Conditioners | H33: CG Approved, Colour Safe, Coloured Hair, Curly Hair, Deep Conditioner, Deep Treatment, Gentle Cleanser, Kid Safe, Moisture-Protein Balanced, Natural, Natural Hair, Sulfate - Free, Weak & Brittle Hair, Weak Hair | I33: TRUE | J33: Size | K33: 8 fl oz | S33: UFD-MTPDC-237 | T33: 540 | U33: shopify | V33: deny | W33: manual | X33: 95 | Z33: TRUE | AA33: TRUE | AF33: 856681006455 | AG33: https://cdn.shopify.com/s/files/1/0504/5187/3989/files/Uncle_Funky_s_Daughter_Maximum_Thermal_Protection_Deep_Conditioner.png?v=1725978692 | AH33: 1 | AI33: Uncle Funky's Daughter Maximum Thermal Protection Deep Conditioner | AJ33: FALSE | AL33: Envelop your hair in the embrace of this silk, bamboo and quinoa-infused deep conditioner. Formulated specially to replenish moisture, fortify each strand, and reduce breakage, leaving your hair incredibly soft, smooth and strong. Deeply hydrating and help reduce breakage. | AY33: Enjoy this range of naturally formulated products crafted to satisfy every curl and enhance and celebrate your natural curl pattern. <br> This range includes the infamous Curly Magic Curl Stimulator. Uncle Funky's Daughter also commonly known as UFD is created with the finest natural ingredients to promote moisture, hydration, curl formation and curl protection.<br> | AZ33: Uncle Funky's Daughter | BA33: Step 1: Shampoo with the Maximum Thermal Protection Purifying Cleanser.<br> Step 2: Apply to clean, wet hair from roots to ends.<br> Step 3: Cover with plastic cap and let stand 5 minutes or apply heat for 30 minutes.<br> Step 4: Rinse.<br> | BB33: Water (Aqua), Behentrimonium Methosulfate, Cetearyl Alcohol, Glycerin, Aloe Barbadensis (Aloe Vera) Leaf Juice*, Glycine Soja (Soybean) Oil, Cetyl Alcohol, Cetrimonium Chloride, Argania Spinosa (Argan) Kernel Oil,Cetyl Esters, Vitis Vinifera (Grape) Seed Oil, Glyceryl Stearate, Olea Europea (Olive) Oil, Hydrolyzed Quinoa Protein, Silk Amino Acids, Bambusa Vulgaris (Bamboo) Extract, Persea Gratissima (Avocado) Oil, Quaternium-80, Fragrance (Parfum), Dehydroacetic Acid, Benzyl Alcohol, Hydroxyethylcellulose, Mentha Piperita (Peppermint) Oil*, Adansonia Digitata (Baobab) Seed Oil*, Rosmarinus Officinalis (Rosemary) Oil, Lavandula Angustifolia (Lavender) Oil, Citric Acid *Organically Sourced | BS33: kg | BU33: 53.22 | BV33: active
A34: =S34 -> UFD-RFMC-237 | B34: uncle-funkys-daughter-rich-funky-moisturizing-cleanser | C34: Uncle Funky's Daughter Rich & Funky Moisturizing Cleanser | D34: <p><span>This far-out, sulfate-free, foamy cleanser delivers a righteous dose of moisture and detangling magic. It's a long-lasting, concentrated formula with a clean, fresh natural scent that'll have you feeling fresh and fab. Can you dig it?</span></p> | E34: Uncle Funky's Daughter | F34: Uncategorized | G34: Shampoo & Cleanser | H34: CG Approved, Cleansing, Cleansing Shampoo, Colour Safe, Coloured Hair, Curly Hair, Gentle Cleanser, Kid Safe, Moisture Rich, Moisturizing Shampoo, Natural, Natural Hair, Protein Free, Sulfate - Free | I34: TRUE | J34: Size | K34: 8 fl oz | S34: UFD-RFMC-237 | T34: 540 | U34: shopify | V34: deny | W34: manual | X34: 90 | Z34: TRUE | AA34: TRUE | AF34: 856681006141 | AG34: https://cdn.shopify.com/s/files/1/0504/5187/3989/files/Uncle_Funky_s_Daughter_Richy_Funky_Moisturizing_Cleanser.png?v=1725978057 | AH34: 1 | AI34: Uncle Funky's Daughter Rich & Funky Moisturizing Cleanser | AJ34: FALSE | AL34: This concentrated long lasting formula create a rich lather that gently cleanse without stripping, while the clean fresh natural scent leaves you feeling fresh and ready for the grove. It is sulfate-free & curl friendly, its also detangle and softens the hair. | AY34: Enjoy this range of naturally formulated products crafted to satisfy every curl and enhance and celebrate your natural curl pattern. <br> This range includes the infamous Curly Magic Curl Stimulator. Uncle Funky's Daughter also commonly known as UFD is created with the finest natural ingredients to promote moisture, hydration, curl formation and curl protection.<br> | AZ34: Uncle Funky's Daughter | BA34: Step 1: Massage into wet hair to activate a foamy sulfate-free lather. <br> Step 2: Thoroughly rinse and repeat as needed.<br> Step 3: Use weekly or as desired.<br> | BB34: Water, Extracts of Comfrey, Rosemary, Horsetail, Willow Bark, Calendula, Kelp, Cocamidopropyl Hydroxysultaine, Disodium Laureth Sulfosuccinate, Cocamidopropyl Betaine, Sodium C14-26 Olefin Sulfonate, Cocamide MEA, Polysorbate 20, Fragrance, Polyquaternium-10, PEG-55 Propylene Glycol Oleate, Cetrimonium Chloride, Citric Acid, Sodium Citrate, Methylchloroisothiazolinone, Methylisothiazolinone, Annatto | BS34: kg | BU34: 53.22 | BV34: active
A35: =S35 -> UFD-THCUR-237 | B35: uncle-funkys-daughter-thirsty-curls | C35: Uncle Funky's Daughter Thirsty Curls | D35: <p><span>Groovy curls need love too! Quench the thirst with our leave-in mist that hydrates, conditions, and preserves moisture. Revive bounce and vitality without rewashing, all with the ease of a convenient leave-in application. Pairs well with Supercurl, Extra Butter, and Curly Magic for maximum moisture and a firm hold.</span></p> | E35: Uncle Funky's Daughter | F35: Uncategorized | G35: Moisturizers & Leave - Ins | H35: CG Approved, Colour Safe, Coloured Hair, Curly Hair, Hair Refresher, Hydrating Hair Refresher, Kid Safe, Leave In Conditioner, Lightweight Leave In, Low Porosity Essentials, Moisture Rich, Mummy & Me Edit, Natural, Natural Hair, New Arrivals, Protein Free, Refresher, Sulfate - Free, Thirsty Curls | I35: TRUE | J35: Size | K35: 8 fl oz | S35: UFD-THCUR-237 | T35: 540 | U35: shopify | V35: deny | W35: manual | X35: 85 | Z35: TRUE | AA35: TRUE | AF35: 856681006103 | AG35: https://cdn.shopify.com/s/files/1/0504/5187/3989/files/Uncle_Funky_s_Daughter_Thirsty_Curls.png?v=1725977265 | AH35: 1 | AI35: Uncle Funky's Daughter Thirsty Curls | AJ35: FALSE | AL35: Refresh, revive, and rehydrate with this lightweight leave-in mist that delivers a burst of moisture to thirsty curls. Perfect for in-between wash days, it hydrates, conditions, and restores bounce—all without the need to rinse or rewash. This product pair with supercurl, extra butter or curly magic. It revives curls without build-up. | AY35: Enjoy this range of naturally formulated products crafted to satisfy every curl and enhance and celebrate your natural curl pattern. <br> This range includes the infamous Curly Magic Curl Stimulator. Uncle Funky's Daughter also commonly known as UFD is created with the finest natural ingredients to promote moisture, hydration, curl formation and curl protection.<br> | AZ35: Uncle Funky's Daughter | BA35: Option 1: Spray on wet or dry curls to moisturize and define.<br> Option 2: Use before Extra Butter or Supercurl to hydrate strands and increase moisture.<br> Option 3: Use as a refresher after Curly Magic.<br> | BB35: Water, Polysorbate 20, Glycerin, Cetrimonium Chloride, Polyquaternium-11, PEG-8, Cocos Nucifera (Coconut) Milk, Urtica Dioica (Nettle) Extract, Anthemis Nobilis (Chamomile) Flower Extract, Symphytum Officinale (Comfrey) Leaf Extract, Calendula Officinalis (Calendula) Flower Extract, Salvia Officinalis (Sage) Leaf Extract, Rosmarinus Officinalis (Rosemary) Leaf Extract, Equisetum Arvense (Horsetail) Leaf Extract, Sodium Hyaluronate, Sodium PCA, Panthenol, Magnesium Sulfate, PEG-12 Dimethicone, Citric Acid, Potassium Sorbate, Phenoxyethanol, Caprylyl Glycol, Sodium Hydroxymethylglycinate, Fragrance. | BS35: kg | BU35: 53.22 | BV35: active
A36: =S36 -> UFD-MIDT-237 | B36: uncle-funkys-daughter-midnite-train | C36: Uncle Funky's Daughter Midnite Train | D36: <p><span>Discover the solution for nourished and conditioned hair with this Midnite Train Leave-In Conditioner. This lightweight spray is formulated to deeply nourish and condition your hair, leaving it irresistibly soft, silky-smooth, and effortlessly manageable throughout the day. </span></p> | E36: Uncle Funky's Daughter | F36: Uncategorized | G36: Moisturizers & Leave - Ins | H36: CG Approved, Colour Safe, Coloured Hair, Curl Defining, Curly Hair, Kid Safe, Leave In Conditioner, Lightweight Leave In, Low Porosity Essentials, Midnite Train, Moisture Rich, Natural, Natural Hair, Protein Free, Styler, Sulfate - Free | I36: TRUE | J36: Size | K36: 8 fl oz | S36: UFD-MIDT-237 | T36: 540 | U36: shopify | V36: deny | W36: manual | X36: 85 | Z36: TRUE | AA36: TRUE | AF36: 856681006097 | AG36: https://cdn.shopify.com/s/files/1/0504/5187/3989/files/Uncle_Funky_s_Daughter_Midnite_Train.png?v=1725976747 | AH36: 1 | AI36: Uncle Funky's Daughter Midnite Train | AJ36: FALSE | AL36: Midnite Train Leave-In Conditioner is your go-to solution for deep nourishment and effortless manageability. This lightweight, ultra-hydrating spray softens and conditions every strand, leaving your hair silky-smooth, touchably soft, and easy to style — all day long. It also increase shine and it's a non greasy formula. | AY36: Enjoy this range of naturally formulated products crafted to satisfy every curl and enhance and celebrate your natural curl pattern. <br> This range includes the infamous Curly Magic Curl Stimulator. Uncle Funky's Daughter also commonly known as UFD is created with the finest natural ingredients to promote moisture, hydration, curl formation and curl protection.<br> | AZ36: Uncle Funky's Daughter | BA36: Step 1: Spray liberally onto hair. <br> Step 2: Do not rinse. <br> Step 3: Use as often as needed. <br> Spray on hair before Extra Butter or Supercurl for long-lasting moisture. <br> | BB36: Water, Glycerin, Aloe Barbadensis (Aloe Vera) Leaf Juice, Polysorbate 20, Olea Europaea (Olive) Fruit Oil, Helianthus Annuus (Sunflower) Seed Oil, Urtica Dioica (Nettle) Extract, Chamomilla Recutita (Matricaria) Flower Extract, Symphytum Officinale (Comfrey) Leaf Extract, Calendula Officinalis (Marigold) Flower Extract, Salvia Officinalis (Sage) Extract, Rosmarinus Officinalis (Rosemary) Leaf Extract, Equisetum Arvense (Horsetail) Extract, Mentha Piperita (Peppermint) Leaf Extract, Lavandula Angustifolia (Lavender) Flower Extract, Arnica Montana Flower Extract, Arctium Lappa (Burdock) Root Extract, Chondrus Crispus (Carrageenan) Extract, Rosa Canina (Rosehip) Extract, Kelp Extract, Honey, Sodium PCA, Sea Salt, Citric Acid, Panthenol, Potassium Sorbate, Sodium Hydroxymethylglycinate, Fragrance. | BN36: kinky-curly-knot-today; treluxe-hi-definition™-curl-enhancer-styling-gel | BP36: only manual | BS36: kg | BU36: 53.22 | BV36: active
A37: =S37 -> UFD-SUCUL-237 | B37: uncle-funkys-daughter-supercurl | C37: Uncle Funky's Daughter Supercurl | D37: <p><span>Pamper your curls with Supercurl, a plush creme designed to drench your hair in moisture and untangle every strand with ease. Let your curls spring to life with exquisite definition and an irresistible shine. Pairs well with Curly Magic and Thirsty Curls for maximum moisture. </span></p> | E37: Uncle Funky's Daughter | F37: Uncategorized | G37: Moisturizers & Leave - Ins | H37: CG Approved, Colour Safe, Coloured Hair, Curl Cream, Curly Hair, High Porosity Essentials, Kid Safe, Moisture Rich, Moisturising Cream, Natural, Natural Hair, New Arrivals, Styler, Sulfate - Free, Supercurl | I37: TRUE | J37: Size | K37: 8 fl oz | S37: UFD-SUCUL-237 | T37: 540 | U37: shopify | V37: deny | W37: manual | X37: 95 | Z37: TRUE | AA37: TRUE | AF37: 856681006134 | AG37: https://cdn.shopify.com/s/files/1/0504/5187/3989/files/Uncle_Funky_s_Daughter_Supercurl_Miracle_Moisture_Creme_1.png?v=1725975506 | AH37: 1 | AI37: Uncle Funky's Daughter Supercurl | AJ37: FALSE | AL37: This moisture-rich hydrating crème designed to drench your strands in moisture, making detangling effortless and leaves your curl feeling soft, defined and full of life. Even more it provides hydration, hold and can be paired with curly magic and thirsty curls your dream team for maximum curl perfection. | AY37: Enjoy this range of naturally formulated products crafted to satisfy every curl and enhance and celebrate your natural curl pattern. <br> This range includes the infamous Curly Magic Curl Stimulator. Uncle Funky's Daughter also commonly known as UFD is created with the finest natural ingredients to promote moisture, hydration, curl formation and curl protection.<br> | AZ37: Uncle Funky's Daughter | BA37: Step 1: Divide hair into sections.<br> Step 2: Emulsify a quarter-sized dollop in your palms. <br> Step 3: Apply from the roots to the ends of damp or dry hair.<br> Step 4: Style as desired.<br> | BB37: Water, Glycine Soja (Soybean) Oil, Glycerin, Cocos Nucifera (Coconut) Oil, Honey, Polymide-1, Caprylic/Capric Triglyceride, Butyrospermum Parkii (Shea Butter), Fragrance, Cetearyl Alcohol, Ceteareth-20, Glyceryl Stearate, Aloe Barbadensis Leaf Extract, Olea Europaea (Olive) Fruit Oil, Prunus Amygdalus Dulcis (Sweet Almond) Oil, Macadamia Ternifolia (Macadamia) Seed Oil, Potassium Hydroxide, Xanthan Gum, Carbomer, Tetrasodium EDTA, Phenoxyethanol, Caprylyl Glycol, Potassium Sorbate, Caramel. | BS37: kg | BU37: 53.22 | BV37: active
A38: =S38 -> UFD-HERM-237 | B38: uncle-funkys-daughter-heal-renew-intensive-hair-masque | C38: Uncle Funky's Daughter Heal & Renew Intensive Hair Masque | D38: <p><span>Get the feeling for some healing with this transformative deep treatment masque, designed to restore moisture and balance to your curls. Enriched with silk protein, avocado oil, and aloe vera juice, this masque strengthens hair follicles and replenishes moisture. </span></p> | E38: Uncle Funky's Daughter | F38: Uncategorized | G38: Conditioners | H38: CG Approved, Colour Safe, Coloured Hair, Curly Hair, Hair Growth, Hair Growth & Length Retention, Hair Masque, Hair Masque Treatment, High Porosity Essentials, Kid Safe, Moisture-Protein Balanced, Natural, Natural Hair, Styler, Sulfate - Free | I38: TRUE | J38: Size | K38: 8 oz | S38: UFD-HERM-237 | T38: 540 | U38: shopify | V38: deny | W38: manual | X38: 95 | Z38: TRUE | AA38: TRUE | AF38: 856681006264 | AG38: https://cdn.shopify.com/s/files/1/0504/5187/3989/files/Uncle_Funky_s_Daughter_Heal_Renew_Intensive_Hair_Masque_1.png?v=1725975705 | AH38: 1 | AI38: Uncle Funky's Daughter Heal & Renew Intensive Hair Masque | AJ38: FALSE | AL38: Treat your curls with this transformative deep treatment masque crafted to restore, replenish moisture and revive strands. Infused with silk protein, avocado oil, and aloe vera juice which help with deeply nourished. | AY38: Enjoy this range of naturally formulated products crafted to satisfy every curl and enhance and celebrate your natural curl pattern. <br> This range includes the infamous Curly Magic Curl Stimulator. Uncle Funky's Daughter also commonly known as UFD is created with the finest natural ingredients to promote moisture, hydration, curl formation and curl protection.<br> | AZ38: Uncle Funky's Daughter | BA38: Step 1: Start with clean hair. <br> Step 2: Apply from root to ends. <br> Step 3: Detangle using a wide tooth comb. <br> Step 4: Cover with a plastic cap and let stand 5 minutes or apply heat for 30 minutes. <br> Step 5: Rinse.<br> | BB38: Water, Behentrimonium Methosulfate, Cetearyl Alcohol, Organic Aloe Vera Leaf Juice, Glycerin, Soybean Oil, Cetyl Alcohol, Cetrimonium Chloride, Grape Seed Oil, Argan Kernel Oil, Cetyl Esters, Organic Baobob Seed Oil, Avocado Oil, Rosemary Leaf Oil, Olive Oil, Silk Amino Acids, Fragrance, Glyceryl Stearate, Quaternium-80, Hydroxyethylcellulose, Organic Peppermint Oil, Citric Acid, Dehydroacetic Acid, Benzyl Alcohol, Lavender Spica Oil. | BD38: 1 | BS38: kg | BU38: 41 | BV38: active
A39: =S39 -> UFD-EBUTT-237 | B39: uncle-funkys-daughter-extra-butter | C39: Uncle Funky's Daughter Extra Butter | D39: <p><span>Fortified with shea butter, palm kernel, and coconut oil - this smooth butta is Uncle Funky's Daughters CEO's crown jewel. Offering a slight hold, this blend defines and softens dry or damaged hair. Pairs well with Curly Magic, Thirsty Curls, and Midnite Train.</span></p> | E39: Uncle Funky's Daughter | F39: Uncategorized | G39: Styler | H39: CG Approved, Colour Safe, Coloured Hair, Curl Cream, Curl Defining, Curling Cream, Curly Hair, High Porosity Essentials, Kid Safe, Natural, Natural Hair, New Arrivals, Protein Free, Styler, Sulfate - Free | I39: TRUE | J39: Size | K39: 8 fl oz | S39: UFD-EBUTT-237 | T39: 540 | U39: shopify | V39: deny | W39: manual | X39: 100 | Z39: TRUE | AA39: TRUE | AF39: 856681006127 | AG39: https://cdn.shopify.com/s/files/1/0504/5187/3989/files/Uncle_Funky_s_Daughter_Extra_Butter_3.png?v=1725976077 | AH39: 1 | AI39: Uncle Funky's Daughter Extra Butter | AJ39: FALSE | AY39: Enjoy this range of naturally formulated products crafted to satisfy every curl and enhance and celebrate your natural curl pattern. <br> This range includes the infamous Curly Magic Curl Stimulator. Uncle Funky's Daughter also commonly known as UFD is created with the finest natural ingredients to promote moisture, hydration, curl formation and curl protection.<br> | AZ39: Uncle Funky's Daughter | BA39: Step 1: Divide hair into sections.<br> Step 2: Emulsify a quarter-sized dollop in your palms.<br> Step 3: Apply from the roots to the ends of damp or dry hair.<br> Step 4: Style as desired.<br> | BB39: Water, Cocos Nucifera (Coconut) Oil, Glycerin, Elaeis Guineesis (Palm) Kernel Oil, Butyrospermum Parkii (Shea Butter), Glyceryl Stearate, Stearic Acid, Cetearyl Alcohol, Organic Aloe Barbadensis Leaf Extract, Caprylic/Capric Triglyceride, Prunus Amygdalus Dulcis (Sweet Almond) Oil, Macadamia Ternifolia Seed Oil, Fragrance, Potassium Hydroxide, Xanthan Gum, Carbomer, Phenoxyethanol, Caprylyl Glycol, Potassium Sorbate, Tetrasodium EDTA. | BS39: kg | BU39: 53.22 | BV39: active
A40: =S40 -> UFD-CMAG-532 | B40: uncle-funkys-daughter-curly-magic | C40: Uncle Funky's Daughter Curly Magic | D40: <p><span>A cult favorite for Type 3 &amp; 4 curls with over 3,000 5* reviews!</span></p> <p><span>This aloe-based curl stimulator instantly detangles, defines, and elongates curls with a soft,<br>touchable hold and zero crunch.<br>Perfect for high-porosity curls, coils, and thick textures that demand moisture, shine, and control in one step.</span></p> <p><br></p> <p><span><strong>Key Benefits</strong><br>- Instant Slip for Easy Detangling</span></p> <p><span>- No Crunch or Flakes</span></p> <p><span></span>- Humidity-Resistant Shine<br></p> <p>- Perfect for Wash &amp; Go or Twist out</p> <p>- Natural Aloe Vera Base</p> | E40: Uncle Funky's Daughter | F40: Uncategorized | G40: Styler | H40: bestseller, Bestsellers, CG Approved, Colour Safe, Coloured Hair, Curl Defining, Curl Maker, Curling Jelly, Curly Hair, Gel, High Porosity Essentials, Kid Safe, Natural, Natural Hair, Protein Free, Styler, Sulfate - Free, Trending Now | I40: TRUE | J40: Size | K40: 18 fl oz | S40: UFD-CMAG-532 | T40: 540 | U40: shopify | V40: deny | W40: manual | X40: 145 | Z40: TRUE | AA40: TRUE | AF40: 856681006189 | AG40: https://cdn.shopify.com/s/files/1/0504/5187/3989/files/Uncle_Funky_s_Daughter_Curly_Magic_1.png?v=1725969406 | AH40: 1 | AI40: Uncle Funky's Daughter Curly Magic | AJ40: FALSE | AK40: Uncle Funky's Daughter Curly Magic | Curly Hair Gel | AL40: This aloe-based curl stimulator is your go-to for instant detangling, curl definition, and elongation—all with a soft, touchable hold. Loved by the curl community for its performance and versatility, it leaves curls defined, hydrated, and frizz-free without the crunch. A flexible hold for perfect type 3 & 4 curls. | AY40: Enjoy this range of naturally formulated products crafted to satisfy every curl and enhance and celebrate your natural curl pattern. <br> This range includes the infamous Curly Magic Curl Stimulator. Uncle Funky's Daughter also commonly known as UFD is created with the finest natural ingredients to promote moisture, hydration, curl formation and curl protection.<br> | AZ40: Uncle Funky's Daughter | BA40: Step 1: Apply Curly Magic on soaking wet hair. <br> Step 2: Fingercomb product through hair to stimulate curls.<br> Step 3: Allow to air dry or diffuse.<br> | BB40: Water, Glycerin, Aloe Barbadensis (Aloe Vera) Leaf Juice*, Simmendsia Chinensis (Jojoba) Seed Oil, Hydrolyzed Wheat Protein, Althaea Officinalis (Marshmallow) Root Extract, Urtica Dioica (Nettle) Extract, Equisetum Arvense (Horsetail) Extract, Tocopherol (Vitamin E), Phenoxyethanol, Ethylhexylglycerin, Fragrance *Organically Sourced | BN40: the-doux-mousse-def-texture-foam; innersense-i-create-hold; innersense-i-create-shine; camille-rose-curl-maker; uncle-funkys-daughter-soul-bounce-texture-defining-mousse | BP40: only manual | BS40: kg | BU40: 53.22 | BV40: active
A41: =S41 -> UFD-CMAG-946 | B41: uncle-funkys-daughter-curly-magic | K41: 32 fl oz | S41: UFD-CMAG-946 | T41: 1760 | U41: shopify | V41: deny | W41: manual | X41: 250 | Z41: TRUE | AA41: TRUE | AF41: 856681006129 | BS41: kg | BU41: 86.25
A42: =S42 -> INN-CLVL-177 | B42: innersense-i-create-lift-volumizing-foam-1 | C42: Innersense I Create Lift Volumizing Foam | D42: <p><span>As seen on In Her Mirror, Episode 1 </span><span>— </span><span>the styler used behind her effortless lift and movement.</span></p> <p>A volumizing foam</p> <p>Create beautiful hair from roots to ends with this light weight styler. Use to add texture, boost volume, define curls, shape and sculpt wet or dry hair or enjoy as a root refresher between washes.</p> <p>Works well with all hair types.</p> <p><strong>Key Ingredients: Aloe Vera</strong> - This versatile ingredient gives hair strength and silky texture. Brings fullness and manageability to even the finest hair.<strong><span> </span>Honey-</strong><span> </span>This humectant provides moisturizing benefits for hair and skin. Honey also acts as antioxidant, making it ideal for sensitive scalps and skin. It also offers light hold. Sugarcane- provides hold and thickness and improves manageability<strong>. Pumpkin Seed Oil -</strong><span> </span>provides hydration, protection and gloss and conditions the scalp, hair and skin.<strong></strong></p> | E42: Innersense Beauty | F42: Uncategorized | G42: Styler | H42: CG Approved, Curly Hair, Foam, Hair Styling, Innersense, Innersense I Create Lift Volumizing foam, Natural, Natural Hair, Styling, Styling Foam, Vegan | I42: TRUE | J42: Size | K42: 6 oz | S42: INN-CLVL-177 | T42: 380 | U42: shopify | V42: deny | W42: manual | X42: 120 | Z42: TRUE | AA42: TRUE | AF42: 850006575978 | AG42: https://cdn.shopify.com/s/files/1/0504/5187/3989/products/InnersenseICreateLiftVolumizingFoam_16941190-e3bb-402a-a635-6b4d163a44b7.png?v=1674220397 | AH42: 1 | AI42: Innersense I Create Lift Volumizing Foam | AJ42: FALSE | AL42: Discover Innersense I Create Lift Volumizing Foam, a Lightweight styler to add Texture, Boost Volume, define curls & as a refresher. Perfect for all hair types | AY42: Innersense Organic Beauty is a love story between two seasoned beauty professionals </span><span>who share a passion for health, hair, beauty and the planet. <br> Founded 2005 to meet the need for clean, pure, organic and non-toxic professional quality hair care products. In doing so, sourcing the highest quality and Certified Organic ingredients, in the purest, most concentrated form has been at the forefront of each product. Innersense have create a complete, award-winning line of safe, sustainable and cruelty free haircare products. | AZ42: Innersense | BA42: Take a deep breath and distribute throughout damp hair. <br> Use fingers to gently separate and shape, adding more products as needed.<br> Blow dry, scrunch or style as desired. <br> For defined curls, diffuse or let it air dry. | BB42: Water/aqua/eau, pullulan, galactoarabinan, aloe barbadensis (aloe vera) leaf juice*, glycerin, caprylyl/capryl glucoside, gluconolactone, sodium benzoate, calcium gluconate, hydrolyzed rice protein, decyl glucoside, lauryl glucoside, sorbitol, potassium sorbate, cananga odorata flower oil, lavandula angustifolia (lavender) oil, citrus aurantium dulcis (orange) peel oil, salvia sclarea (clary) oil, vanillin, pogostemon cablin (patchouli) oil, glycine soja (soybean) oil, hydroxypropyltrimonium honey, sorbic acid, citric acid, diheptyl succinate, capryloyl glycerin/sebacic acid copolymer, vaccinium macrocarpon (cranberry) seed oil, vitis vinifera (grape) seed oil, cucurbita pepo (pumpkin) seed oil*, macadamia ternifolia seed oil, macelignan, tocopherol, linalool†, limonene†<br> *Certified Organic<br> +A natural component of essential oils. | BS42: kg | BU42: 51.38 | BV42: active
A43: =S43 -> INN-CLVL-70 | B43: innersense-i-create-lift-volumizing-foam-1 | K43: 2.3 fl oz | S43: INN-CLVL-70 | T43: 380 | U43: shopify | V43: deny | W43: manual | X43: 55 | Z43: TRUE | AA43: TRUE | AF43: 852415001949 | BS43: kg | BU43: 51.38
A44: =S44 -> CUP-TCT-237 | B44: curls-potions-chebula-green-tea-2-in-1-conditioning-treatment | C44: Curls & Potions Chebula & Green Tea 2 in 1 Conditioning Treatment | D44: <p><span>Get ready to level up your hair care with this Chebula and Green Tea 2 in 1 conditioning treatment! With a unique blend of green tea, hemisqualane and other natural ingredients works to deeply condition your hair while providing a long-lasting shine.<br> This conditioner helps reduce hair loss, improve elasticity, and provide a lasting hydration boost for healthier looking hair.<br> Try the Chebula and Green Tea 2 in 1 conditioning treatment today for the best results</span></p> | E44: Curls & Potions | F44: Health & Beauty > Personal Care > Hair Care | G44: Treatment | H44: Ayuverda, Ayuverdic, CG Approved, Chebula, Curls & Potions, Deep Conditioner, Green Tea, Hair fall, Hair Goals, Hair Growth, Hair Growth & Length Retention, Hair Loss, Hair Loss Solution, Hair Loss System, Hair Shedding, High Porosity, Leave In Conditioner, Low Porosity, Transitioning Hair, Weak & Brittle Hair | I44: TRUE | J44: Size | K44: 8 oz | S44: CUP-TCT-237 | T44: 440 | U44: shopify | V44: deny | W44: manual | X44: 95 | Z44: TRUE | AA44: TRUE | AF44: 652811927900 | AG44: https://cdn.shopify.com/s/files/1/0504/5187/3989/files/Curls_PotionsChebula_GreenTea2in1ConditioningTreatment.png?v=1720616597 | AH44: 1 | AI44: Curls & Potions Chebula & Green Tea 2 in 1 Conditioning Treatment | AJ44: FALSE | AL44: Curls & Potions Chebula & Green Tea Conditioning Treatment deeply conditions hair, reduce hair loss, improves elasticity and boost hydration. Good for hair transition | AM44: 486 | AY44: <p data-mce-fragment="1">Curls and Potions was founded with a pinch of a rebellious fighting spirit and a pinch of wanting to change one curl at a time. With one fighting Breast Cancer and one wanting to make the most of the curls and coils, the idea was born to focus on ways to blend healthy hair with overall wellness.&nbsp;</p> <p data-mce-fragment="1"><strong data-mce-fragment="1"><em data-mce-fragment="1">Every idea begins with a problem and ours was simple: healthy hair, healthy living, and an amazing wash-n-go.</em><span data-mce-fragment="1">&nbsp;</span></strong>The idea of having one without the other just didn’t make sense.&nbsp; We focused on changing the way we think about overall health and hair, they go hand in hand. &nbsp;So how did we fix that?<span data-mce-fragment="1">&nbsp;</span><em data-mce-fragment="1"><strong data-mce-fragment="1">We took ingredients that help with overall wellness sprinkled with a little bit of old traditional hair recipes and created the new blends that Curls &amp; Potions® needed to help change the way we look at hair and health.&nbsp;</strong></em><span data-mce-fragment="1">&nbsp;</span>Healthy Hair + Healthy Lifestyle = Good Hair.</p> | AZ44: Curls & Potions | BA44: As a deep conditioner, apply to clean, damp hair and cover with a plastic cap and let it sit for 30 mins with or without heat.<br>Proceed to rinse with cool water and style as usual. <br> As a leave in, separate your hair into sections and apply a nickel to dime size amount per section, brush or comb each section to distribute evenly.<br> Do not rinse, style as usual <br> | BB44: Distilled Water, Green Tea Extract, Rosemary Extract, Chebula Extract, Chia Seed Extract. Hydrangea Root Extract, Fenugreek Extract, Hemisqualane (C13-15 Alkane), Aloe Juice, Sugar Cane, Mango Butter, Avocado Oil, Babassu Oil, Behentrimonium Mmethosulfate, Guar Hydroxypropyltrimonium Chloride, Boabab Protein, Quinoa Protein, Zea Mays (corn) Starch, Polyquaternium-7, Polyquaternium-16, Pro Vitamin B5, Glycerin, Coconut Oil, Citric Acid, Peppermint Essential Oil, Rosemary Essential Oil <br> | BS44: kg | BU44: 34.83 | BV44: active
A45: =S45 -> CUP-CHM-237 | B45: curls-potions-chebe-hydration-mask | C45: Curls & Potions Chebe Hydration Mask | D45: <p>Chebe Hydration Mask is a mix of oils and butters blended with infused water to give any texture the hydration it needs. Easy to comb through and help detangle all textures to ensure no strand is left behind!</p> <p>The mask seals in hydration and leaves strands feeling soft, smooth, and replenished. It also helps to improve the overall health of your hair, reducing breakage and aids hair growth.</p> | E45: Curls & Potions | F45: Uncategorized | G45: Conditioner | H45: CG Approved, Chebe, Chebe Clay Gloss, Clay, Clay Mask, Curls & Potions, Deep Conditioner, Hair Goals, Hair Growth, Hair Growth & Length Retention, Hair Treatment, High Porosity, Low Porosity, Moisture Rich, Moisturizing Deep Conditioner, Pre poo treatment, Prepoo Treatment, Transitioning Hair | I45: TRUE | J45: Size | K45: 8 oz | S45: CUP-CHM-237 | T45: 440 | U45: shopify | V45: deny | W45: manual | X45: 78 | Z45: TRUE | AA45: TRUE | AF45: 652811927900 | AG45: https://cdn.shopify.com/s/files/1/0504/5187/3989/files/Curls_PotionChebeHydrationMask.png?v=1720615607 | AH45: 1 | AI45: Curls & Potions Chebe Hydration Mask | AJ45: FALSE | AL45: Discover Curls & Potions Chebe Hydration Mask: Moisturizing Deep Conditioner that detangles hair, reduce breakage & aids growth. perfect for all curly textures | AY45: <p data-mce-fragment="1">Curls and Potions was founded with a pinch of a rebellious fighting spirit and a pinch of wanting to change one curl at a time. With one fighting Breast Cancer and one wanting to make the most of the curls and coils, the idea was born to focus on ways to blend healthy hair with overall wellness.&nbsp;</p> <p data-mce-fragment="1"><strong data-mce-fragment="1"><em data-mce-fragment="1">Every idea begins with a problem and ours was simple: healthy hair, healthy living, and an amazing wash-n-go.</em><span data-mce-fragment="1">&nbsp;</span></strong>The idea of having one without the other just didn’t make sense.&nbsp; We focused on changing the way we think about overall health and hair, they go hand in hand. &nbsp;So how did we fix that?<span data-mce-fragment="1">&nbsp;</span><em data-mce-fragment="1"><strong data-mce-fragment="1">We took ingredients that help with overall wellness sprinkled with a little bit of old traditional hair recipes and created the new blends that Curls &amp; Potions® needed to help change the way we look at hair and health.&nbsp;</strong></em><span data-mce-fragment="1">&nbsp;</span>Healthy Hair + Healthy Lifestyle = Good Hair.</p> | AZ45: Curls & Potions | BA45: Apply to sections of freshly washed hair, section by section. <br> Focus treatment on the length of the hair, avoid the scalp <br> Cover with a plastic cap and let it sit for 15 -30 minutes with or without heat. Rinse with cool water. Follow with a leave in conditioner and your favourite stylers. <br> | BB45: Distilled Water infused with Marshmallow Root, Nettle, Fenugreek, Horsetail, Chebe Powder, Coconut Milk, Aloe Vera Juice, Agave Nectar, Mango Butter, Cupuacu Butter, Behentrimonium Methosulfate, Cetyl Alcohol, Beet Sugar, Vitamin E, Citric Acid, Xanthan Gum, Optiphen ND, Peppermint Oil, Spearmint Oil, Fragrance <br> | BS45: kg | BU45: 34.83 | BV45: active
A46: =S46 -> CUP-GTRR-237 | B46: curls-potions-chebula-green-tea-hair-repair-rinse | C46: Curls & Potions Chebula & Green Tea Hair Repair Rinse | D46: This Chebula &amp; Green Tea Hair Rinse is the solution to hair loss and shedding.<br> Green Tea is packed with anti-inflammatory properties that helps to reduce hair loss, stimulates hair growth, &amp; keeps your scalp clean. Green Tea contains catechins which help to block DHT (hormone responsible for hair loss).<br>Fenugreek is high in protein and nicotinic acid content which is known to help combat dandruff and hair loss. It also aids in moisturizing the hair and restores sheen to strands.<br>Chebula aka Haritaki is an Ayurvedic herb that helps promote hair growth and alleviate scalp issues. It is known to help prevent hair loss and reduce hair graying <br> | E46: Curls & Potions | F46: Health & Beauty > Personal Care > Hair Care | G46: Treatment | H46: Amla Oil, Ayurverdic, Ayuverda, Best seller, CG Approved, Chebula, Chemically Treated Hair, Curls & Potions, Curls and Potions, Curly Hair, Dry & Itchy Scalp Care, Fenugreek, Green Tea, Growth oil, Hair fall, Hair Growth, Hair Growth & Length Retention, Hair Growth System, Hair Loss Solution, Hair rinse, Low Porosity Essentials, Natural Hair, Rosemary Oil, Sulfate - Free, Transitioning Hair | I46: TRUE | J46: Size | K46: 8 fl oz | S46: CUP-GTRR-237 | T46: 440 | U46: shopify | V46: deny | W46: manual | X46: 80 | Z46: TRUE | AA46: TRUE | AF46: 708210353564 | AG46: https://cdn.shopify.com/s/files/1/0504/5187/3989/files/Curls_PotionsChebula_GreenTeaHairRepairTeaRinse.png?v=1720111785 | AH46: 1 | AI46: Curls & Potions Chebula & Green Tea Hair Repair Rinse | AJ46: FALSE | AL46: Curls & Potions Chebula Green Tea Rinse - perfect treatment for hair loss & shedding. Ayurvedic herbs promote hair growth and alleviate scalp issues. | AM46: 486 | AY46: <p data-mce-fragment="1">Curls and Potions was founded with a pinch of a rebellious fighting spirit and a pinch of wanting to change one curl at a time. With one fighting Breast Cancer and one wanting to make the most of the curls and coils, the idea was born to focus on ways to blend healthy hair with overall wellness.&nbsp;</p> <p data-mce-fragment="1"><strong data-mce-fragment="1"><em data-mce-fragment="1">Every idea begins with a problem and ours was simple: healthy hair, healthy living, and an amazing wash-n-go.</em><span data-mce-fragment="1">&nbsp;</span></strong>The idea of having one without the other just didn’t make sense.&nbsp; We focused on changing the way we think about overall health and hair, they go hand in hand. &nbsp;So how did we fix that?<span data-mce-fragment="1">&nbsp;</span><em data-mce-fragment="1"><strong data-mce-fragment="1">We took ingredients that help with overall wellness sprinkled with a little bit of old traditional hair recipes and created the new blends that Curls &amp; Potions® needed to help change the way we look at hair and health.&nbsp;</strong></em><span data-mce-fragment="1">&nbsp;</span>Healthy Hair + Healthy Lifestyle = Good Hair.</p> | AZ46: Curls & Potions | BA46: Apply to dry hair, spray into sections and focus on roots as well as length of hair. <br> Distribute evenly. <br> Option 1: Leave in for 10 min or overnight. Shampoo hair thoroughly. <br> Option 2: After shampooing, spray tea rinse throughout hair, let it sit for 10 mins, rinse with cool water. <br> Follow up with deep conditioning and styling | BB46: Distilled water, Green Tea, Chebula, Fennugreek, Pro Vitamin b5 (panthenol), Apple Cider Vinegar, Glycerin, Carob Seed Oil, Soy Protein, Quinoa Protein, Polyquaternium 16, Polyquaternium 7, Guar Hydroxypropyltrimonium Chloride, Chia Seed Extract, Phenoxyethanol, Benzoic Acid, Dehyrdroacetic Acid, Biotin, Vitamin E, Rosemary Essential Oil, Peppermint Essential Oil, Fragrance | BS46: kg | BU46: 34.83 | BV46: active
A47: =S47 -> CAM-HSMS-237 | B47: camille-rose-honey-spiked-mousse-4-in-1-styler | C47: Camille Rose Spiked Honey Mousse 4 in 1 Styler | D47: <p><span>A lightweight setting mousse infused with HONEY and NETTLE, crafted to smooth strands, boost shine, and set styles.</span></p> | E47: Camille Rose | F47: Uncategorized | G47: Styler | H47: Bestsellers, Camille Rose, CG Approved, Colour Safe, Coloured Hair, Curl Defining, Curl defining mousse, Curly Hair, Honey, Kid Safe, Moisture-Protein Balanced, Mousse, Natural, Natural Hair, Protein Free, Styler, Styling Mousse, Sulfate - Free | I47: TRUE | J47: Size | K47: 8 Fl oz | S47: CAM-HSMS-237 | T47: 440 | U47: shopify | V47: deny | W47: manual | X47: 75 | Z47: TRUE | AA47: TRUE | AG47: https://cdn.shopify.com/s/files/1/0504/5187/3989/files/CamilleRoseSpikedHoneyMousse4in1Styler_1.png?v=1697096574 | AH47: 1 | AI47: Camille Rose Honey Spiked Mousse 4 in 1 Styler | AJ47: FALSE | AL47: A lightweight setting mousse infused with HONEY and NETTLE, crafted to smooth strands, boost shine, and set your style with soft, touchable hold which gives structure without stiffness. | AY47: Camille Rose Naturals is a trusted source for premium hair and beauty products formulated with gourmet ingredients to provide true nourishment to your strands.<br> <br> Each product is developed with integrity and hand crafted with love. Perfect for all hair types and textures. <br> | AZ47: Camille Rose | BA47: Apply a generous amount onto freshly washed and conditioned strands. <br> Style hair. Can be used on wash-and go’s, braid outs, twist outs, rodsets and many more protective styles! <br> Allow to fully dry before fluffing. | BB47: Water (Aqua, Eau), Oryza Sativa (Rice Water) Extract, Honey (Mel) Wildflower &amp; Clover, Urtica Dioica Extract (Nettle), Cocamidopropyl Betaine (Coconut Derived), Polyquaternium-55, Polysorbate-20, PVP, Methyl Gluceth-20 (Emollient), Oleth-20 (Vegetable alcohol), Aloe Barbadensis (Aloe Vera) Leaf Juice, Panthenol, Phenoxyethanol (Optiphen ND), Benzoic Acid, Ethylhexylglycerin, Glycereth-2 Cocoate, Quaternium-75, Tocopheryl Acetate (Vitamin E), Silk Amino Acids, Phthalate Free Fragrance, Citric Acid And Love! | BN47: camille-rose-curl-love-moisture-milk; camille-rose-curl-maker | BP47: only manual | BS47: kg | BU47: 47.35 | BV47: active
A48: =S48 -> CAM-HSMS-100 | B48: camille-rose-honey-spiked-mousse-4-in-1-styler | K48: 3.4 Fl oz | S48: CAM-HSMS-100 | T48: 240 | U48: shopify | V48: deny | W48: manual | X48: 35 | Z48: TRUE | AA48: TRUE | BS48: kg | BU48: 17.62
A49: =S49 -> INN-PUTT-59 | B49: innersense-pure-travel-trio | C49: Innersense Pure Travel Trio | D49: <p>The Pure Trio Collection is 100% color safe and perfect for fine to medium hair types.</p> <p><strong>Includes:</strong> 1x Pure Harmony Hairbath, 1x Pure Inspiration Daily Conditioner and 1x Sweet Spirit Leave In Conditioner (all 2 oz sizes).<br></p> <p><br></p> | E49: Innersense Beauty | F49: Uncategorized | G49: Moisturizers & Leave - Ins | H49: Best Seller, Bundle, Bundle Set, CG Approved, Colour Safe, Colour Treated Hair, Conditioner, Fine Hair, Fine haircare, Innersense, Innersense Bundle, Innersense Pure Travel Trio, Leave In Conditioner, Moisture Protein Balanced, Organic Hair Care, Shampoo, Vegan Hair Care | I49: TRUE | J49: Size | K49: 2 oz | S49: INN-PUTT-59 | T49: 1200 | U49: shopify | V49: deny | W49: manual | X49: 115 | Z49: TRUE | AA49: TRUE | AF49: 852415001956 | AG49: https://cdn.shopify.com/s/files/1/0504/5187/3989/files/InnersensePureTravelTrio.png?v=1696404969 | AH49: 1 | AI49: Innersense Pure Travel Trio | AJ49: FALSE | AY49: Innersense Organic Beauty is a love story between two seasoned beauty professionals who share a passion for health, hair, beauty and the planet. <br> Founded 2005 to meet the need for clean, pure, organic and non-toxic professional quality hair care products. In doing so, sourcing the highest quality and Certified Organic ingredients, in the purest, most concentrated form has been at the forefront of each product. Innersense have create a complete, award-winning line of safe, sustainable and cruelty free haircare products. | AZ49: Innersense | BA49: Please see individual product listings for directions | BB49: Please see individual product listings for full ingredient list | BS49: kg | BU49: 49.55 | BV49: active
A50: =S50 -> INN-COTT-59 | B50: innersense-colour-travel-trio | C50: Innersense Color Travel Trio | D50: <p>The Color Trio Collection is 100% color safe. Keeps color vibrant, healthy and hydrated. Best for chemically processed hair, works well with all hair types.<br> <strong>Includes:</strong> 1x Color Awakening Hairbath, 1x Color Radiance Daily Conditioner and 1x Sweet Spirit Leave In Conditioner (all 2 oz sizes).<br> </p> | E50: Innersense Beauty | F50: Uncategorized | G50: Moisturizers & Leave - Ins | H50: Best Seller, Bundle, Bundle Set, CG Approved, Colour Safe, Colour Treated Hair, Conditioner, Innersense, Innersense Bundle, Innersense Colour Travel Trio, Leave In Conditioner, Moisture Protein Balanced, Organic Hair Care, Shampoo, Vegan Hair Care | I50: TRUE | J50: Size | K50: 2 oz | S50: INN-COTT-59 | T50: 440 | U50: shopify | V50: deny | W50: manual | X50: 115 | Z50: TRUE | AA50: TRUE | AF50: 852415001963 | AG50: https://cdn.shopify.com/s/files/1/0504/5187/3989/files/InnersenseColourTravelTrio.png?v=1696404124 | AH50: 1 | AI50: Innersense Color Travel Trio | AJ50: FALSE | AY50: Innersense Organic Beauty is a love story between two seasoned beauty professionals who share a passion for health, hair, beauty and the planet. <br> Founded 2005 to meet the need for clean, pure, organic and non-toxic professional quality hair care products. In doing so, sourcing the highest quality and Certified Organic ingredients, in the purest, most concentrated form has been at the forefront of each product. Innersense have create a complete, award-winning line of safe, sustainable and cruelty free haircare products. | AZ50: Innersense | BA50: Please see individual product listings for directions | BB50: Please see individual product listings for full ingredient list. | BS50: kg | BU50: 49.55 | BV50: active
A51: =S51 -> MIE-MSSOL-59 | B51: mielle-rosemary-mint-strengthening-scalp-hair-oil-light | C51: Mielle Rosemary Mint Strengthening Scalp & Hair Oil - Light | D51: <p>Achieve longer, stronger, healthier hair with this organic hair oil from Mielle.</p><br> <p>The lighter version of this oil contains all the goodness of the original oil including:</p> <br> <p>• More than 30 essential oils and nutrients<br>• Infused with Biotin<br>• Use for daily hair care or specialized scalp treatments</p><br> <p>This lighter version was formulated with fine hair textures and low porosity hair in mind. Enjoy all the growth and strengthening benefits without the added weight.</p> <br> <p>Mielle Rosemary Mint organic hair oil is a nutrient-rich, intensive formula meant to help you address all of your hair concerns. From supporting length retention and nourishing hair follicles to smoothing split ends and preventing dry scalp, this organic hair oil uses natural ingredients and essential oils to provide the care your hair deserves.</p> <p><br></p> | E51: Mielle Organics | F51: Uncategorized | G51: Oil | H51: bestseller, Bestsellers, Biotin, BS2022, CG Approved, Curly Hair, Dry & Itchy Scalp Care, Hair Growth, Hair Growth & Length Retention, Hair Growth Oil, Hair Repair, Hair Strengthening, Hot Oil Treatment, Mielle, Natural Hair, New Arrivals, oil, Quick Hair Growth, Rapid Hair Growth, Scalp Massage, Scalp Oil, Sealant, Split End, Strengthening Treatment | I51: TRUE | J51: Size | K51: 2 fl oz | S51: MIE-MSSOL-59 | T51: 320 | U51: shopify | V51: deny | W51: manual | X51: 60 | Z51: TRUE | AA51: TRUE | AF51: 854102006732 | AG51: https://cdn.shopify.com/s/files/1/0504/5187/3989/files/IMG-8471.png?v=1695278395 | AH51: 1 | AI51: Mielle Rosemary Mint Strengthening Scalp & Hair Oil - Light | AJ51: FALSE | AL51: Mielle Rosemary Mint Strengthening Scalp & Hair Oil - Light. A light strengthening hair oil to aid length retention & prevent dry, itchy scalp - fine & Low porosity hair | AY51: Mielle Organics a natural haircare brand that delivers on its promises of healthier, stronger and more hydrated hair through use of organic ingredients, products have been uniquely formulated to deliver hydration, moisture and definition.<br> | AZ51: Mielle | BA51: Use it on protective styles, including braids and weaves, and enjoy its fresh, invigorating scent during your next hot oil treatment. This formula is made to be versatile!<br><br><strong>Scalp Treatment<br></strong>Section hair into 4 parts exposing scalp. Apply a small amount of oil to scalp, massage oil in with fingers and comb through to ends of hair. Leave in and style as desired.<br><br> <strong>Daily Use<br></strong>Apply a small amount to scalp and comb through to ends.<br><br> <strong>Split End Care<br></strong>Apply oil to ends of hair, place a processing cap on head and leave on for 10 minutes. Rinse and proceed with shampooing. | BB51: Glycine Soja (Soybean) Oil, Ricinus Communis (Castor) Seed Oil, Rosmarinus Officinalis (Rosemary) Leaf Oil, Simmondsia Chinensis (Jojoba) Seed Oil, Mentha Piperita (Peppermint) Oil, Eucalyptus Globolus (Eucalyptus) Leaf Oil, Menthol, Melalueca Alternifolia (Tea Tree) Leaf Oil, Cocos Nucifera (Coconut) Oil, Equisetum Arvense (Horsetail) Extract, Aloe Barbadensis Extract, Lavandula Angustifolia (Lavender) Oil, Triticum Vulgare (Wheat) Germ Oil, Carthamus Tinctorius (Safflower) Seed Oil, Oenothera Biennis (Evening Primrose) Oil, Vitis Vinifera (Grape) Seed Oil, Benzyl Nicotinate, Prunus Amygdalus Dulcis (Sweet Almond) Oil, Oryza Sativa (Rice) Bran Oil, Tocopheryl Acetate, Biotin, Arctium Lappa (Burdock) Root Extract, Glycerin, Apium Graveolens (Celery) Seed Extract, Retinyl Palmitate, Cholecalciferol (Vitamin D), Ascorbic Acid, Ocimum, Basilicum (Basil) Oil, Pogostemon Cablin (Patchouli) Oil, Salvia Officinalis (Sage) Oil, Silica, Urtica Dioica (Nettle) Extract | BN51: mielle-mongongo-oil-protein-free-hydrating-conditioner; mielle-babassu-curly-cocktail-curl-cream; mielle-mongongo-oil-thermal-heat-protectant-spray | BP51: only manual | BS51: kg | BU51: 29.33 | BV51: active
A52: =S52 -> CUP-GTSO-59 | B52: curls-potions-chebula-green-tea-herbal-mint-hair-scalp-oil | C52: Curls & Potions Chebula & Green Tea Herbal Mint Hair & Scalp Oil | D52: <meta charset="UTF-8"> <p class="p1">This Chebula &amp; Green tea herbal mint hair &amp; scalp oil is the solution to hair loss, shedding, encouraging growth, &amp; seals split ends.</p><br> <p class="p2">Green tea is packed with properties that helps to reduce hair loss, stimulates hair growth, &amp; keeps your scalp clean. Green tea contains catachins which help to block dht (hormone responsible for hair loss).</p><br> <p class="p2">Rosemary protects against hair loss, stimulates growth, thickens hair.</p><br> <p class="p2">Fennugreek is high in protein and nicotinic acid content which is known to help combat dandruff and hair loss. It also aids in moisturizing the hair and restores sheen to strands.</p> | E52: Curls & Potions | F52: Uncategorized | G52: Treatment | H52: Amla Oil, Ayurverdic, Ayuverda, Best seller, CG Approved, Chebula, Chemically Treated Hair, Curls & Potions, Curls and Potions, Curly Hair, Dry & Itchy Scalp Care, Fenugreek, Green Tea, Growth oil, Hair fall, Hair Growth, Hair Growth & Length Retention, Hair Growth System, Hair Loss Solution, Natural Hair, Rosemary Oil, Sulfate - Free, Transitioning Hair | I52: TRUE | J52: Size | K52: 2 fl oz | S52: CUP-GTSO-59 | T52: 440 | U52: shopify | V52: deny | W52: manual | X52: 70 | Z52: TRUE | AA52: TRUE | AF52: 708210353564 | AG52: https://cdn.shopify.com/s/files/1/0504/5187/3989/files/41D8EFB0-A116-48EA-8759-FD454D216B76.png?v=1720109419 | AH52: 1 | AI52: Curls & Potions Chebula & Green Tea Herbal Mint Hair & Scalp Oil | AJ52: FALSE | AL52: Discover the Chebula & Green tea herbal mint hair & scalp oil is the solution; This oil has DHT blockers, protects against hair loss & thickens hair & restores sheen | AY52: <p data-mce-fragment="1">Curls and Potions was founded with a pinch of a rebellious fighting spirit and a pinch of wanting to change one curl at a time. With one fighting Breast Cancer and one wanting to make the most of the curls and coils, the idea was born to focus on ways to blend healthy hair with overall wellness.&nbsp;</p> <p data-mce-fragment="1"><strong data-mce-fragment="1"><em data-mce-fragment="1">Every idea begins with a problem and ours was simple: healthy hair, healthy living, and an amazing wash-n-go.</em><span data-mce-fragment="1">&nbsp;</span></strong>The idea of having one without the other just didn’t make sense.&nbsp; We focused on changing the way we think about overall health and hair, they go hand in hand. &nbsp;So how did we fix that?<span data-mce-fragment="1">&nbsp;</span><em data-mce-fragment="1"><strong data-mce-fragment="1">We took ingredients that help with overall wellness sprinkled with a little bit of old traditional hair recipes and created the new blends that Curls &amp; Potions® needed to help change the way we look at hair and health.&nbsp;</strong></em><span data-mce-fragment="1">&nbsp;</span>Healthy Hair + Healthy Lifestyle = Good Hair.</p> | AZ52: Curls & Potions | BA52: Part hair in sections and apply to scalp. Massage in. <br> Can be used daily as needed.<br> Apply a few drops to the ends of hair to seal in moisture. <br> | BB52: Rice Bran Oil, Argan Oil, Avocado Oil, Green Tea Extract, Red Raspberry Seed Oil, Jamaican Black Castor Oil, Black Cumin Seed Oil, Safflower Oil, Grapeseed Oil, Sweet Almond Oil, Chebula Extract, Jojoba Oil, Rosemary Oil, Peppermint Oil, Eucalyptus Oil, Tea Tree Oil, Fractionated Coconut Oil, Horsetail Extract, Patchouli Oil, Lavender Oil, Fenugreek, Henna, Burdock Root Extract, Celery Seed Extract, Basil Extract, Nettle Extract, Aloe, Cayenne Extract, Glycerin. | BS52: kg | BU52: 34.83 | BV52: active
A53: =S53 -> CUP-SLRS-237 | B53: curls-potions-chebe-scalp-length-retention-shampoo | C53: Curls & Potions Chebe Scalp & Length Retention Shampoo | D53: Chebe Scalp Length Retention Shampoo is a gentle cleansing shampoo that is packed with nutrients that help to cleanse hair &amp; scalp while also aiding in length retention.<br> Alleviates dry scalp, cleanses without stripping. This utilizes the benefits of Chebe Powder that originated in Chad, Africa. | E53: Curls & Potions | F53: Uncategorized | G53: Shampoo & Cleanser | H53: Amla Oil, Ayurverda, Ayurverdic, Ayuverda, Breakage, CG Approved, Chebe, Curls & Potions, Curly Hair, Damaged Hair, Fenugreek, Hair Growth, Hair Growth & Length Retention, Hair Loss, Hair Loss System, Kinky Hair, Strengthening Shampoo, Sulfate Free, Transitioning Hair | I53: TRUE | J53: Size | K53: 8 fl oz | S53: CUP-SLRS-237 | T53: 440 | U53: shopify | V53: deny | W53: manual | X53: 85 | Z53: TRUE | AA53: TRUE | AF53: 786368807528 | AG53: https://cdn.shopify.com/s/files/1/0504/5187/3989/files/Curls_PotionsChebeScalp_LengthRetentionShampoo.png?v=1693483230 | AH53: 1 | AI53: Curls & Potions Chebe Scalp & Length Retention Shampoo | AJ53: FALSE | AL53: Curls & Potions Chebe Scalp & Length Retention Shampoo is a gentle cleanser that cleanses hair & scalp without stripping while aiding length retention. | AY53: <p data-mce-fragment="1">Curls and Potions was founded with a pinch of a rebellious fighting spirit and a pinch of wanting to change one curl at a time. With one fighting Breast Cancer and one wanting to make the most of the curls and coils, the idea was born to focus on ways to blend healthy hair with overall wellness.&nbsp;</p> <p data-mce-fragment="1"><strong data-mce-fragment="1"><em data-mce-fragment="1">Every idea begins with a problem and ours was simple: healthy hair, healthy living, and an amazing wash-n-go.</em><span data-mce-fragment="1">&nbsp;</span></strong>The idea of having one without the other just didn’t make sense.&nbsp; We focused on changing the way we think about overall health and hair, they go hand in hand. &nbsp;So how did we fix that?<span data-mce-fragment="1">&nbsp;</span><em data-mce-fragment="1"><strong data-mce-fragment="1">We took ingredients that help with overall wellness sprinkled with a little bit of old traditional hair recipes and created the new blends that Curls &amp; Potions® needed to help change the way we look at hair and health.&nbsp;</strong></em><span data-mce-fragment="1">&nbsp;</span>Healthy Hair + Healthy Lifestyle = Good Hair.</p> | AZ53: Curls & Potions | BA53: Shake well. Massage a generous amount to scalp and wet hair. <br> Distribute through hair.<br> Rinse and follow up with Curls & Potions Deep Moisture Potion Conditioner. | BB53: Fermented Rice Water infused with Ambunu, Chebe Powder, Flaxseed, Marshmallow Root, Nettle Leaf, Shikakai, Aritha, Amla, Fennugreek, Cocamidopropyl, Betaine, Decyl Glucoside, Cassia Hydroxypropyltrimonium, Aloe Vera Juice, Hemisqualane, Brahmi Powder, Organic Honey, Jamaican Black Castor Oil, Polyquaterium-7, DL Panthenol (Pro-Vitamin B5), Phenoxyethanol, Benzoic Acid, Dehydroacetic Acid, Citric Acid, Essential Oil Blend. | BS53: kg | BU53: 31.16 | BV53: active
A54: =S54 -> CAM-SHSD-56 | B54: camille-rose-rosemary-oil-strengthening-hair-scalp-drops | C54: Camille Rose Rosemary Oil Strengthening Hair & Scalp Drops | D54: <p><span>An intensely nourishing, multi use oil enriched with pure rosemary to promote healthy hair growth, stronger strands, and visibly revitalized, shiny curls.</span></p> <p><span>Made with a blend of pure rosemary oil, a hint of peppermint, amla, apigenin, shikakai, and biotin, our vegan hair treats harness the power of beauty’s favourite ingredients to boost maximum hair strength in all textures. </span></p><br> <p><span>The result is a nourished scalp and unstoppable strands that need no introduction.</span></p> | E54: Camille Rose | F54: Health & Beauty > Personal Care > Hair Care | G54: Oils & Refreshers | H54: Ayurverdic, Best seller, bestseller, BS2022, Camille Rose, Camille Rose Rosemary Oil, CG Approved, Colour Safe, Coloured Hair, Curly Hair, Hair Growth, Hair Growth & Length Retention, Hair Growth Oil, High Porosity Essentials, Natural, Natural Hair, Oil, Oil treatment, Protein Free, Rapid Hair Growth, Rosemary, Rosemary Oil | I54: TRUE | J54: Size | K54: 1.9 fl oz | S54: CAM-SHSD-56 | T54: 320 | U54: shopify | V54: deny | W54: manual | X54: 65 | Z54: TRUE | AA54: TRUE | AF54: 860006856595 | AG54: https://cdn.shopify.com/s/files/1/0504/5187/3989/files/CamilleRoseStrengtheningHair_ScalpDrops.png?v=1692870262 | AH54: 1 | AI54: Camille Rose Rosemary Oil Strengthening Hair & Scalp Drops | AJ54: FALSE | AL54: An intensely nourishing spray crafted with a fortified blend of rosemary oil. This formula delivers a maximum strength and shine across all hair texture weather used as a treatment for scalp or sealing oil. | AY54: Camille Rose Naturals is a trusted source for premium hair and beauty products formulated with gourmet ingredients to provide true nourishment to your strands.<br> <br> Each product is developed with integrity and hand crafted with love. Perfect for all hair types and textures. <br> | AZ54: Camille Rose | BA54: Apply to wet or dry hair. <br>Use 2-3 drops and massage into scalp, edges, or delicate ends.<br> Apply daily or as needed for nourishment. <br> Follow up with your favourite Camille Rose Rosemary Collection conditioning and styling products. | BB54: Ricinus Communis (Castor) Seed Oil, Olea Europaea (Olive) Fruit Oil, Rosmarinus Officinalis (Rosemary) Leaf Oil, Melaleuca Alternifolia (Tea Tree) Leaf Oil, Menthol, Rosmarinus Officinalis (Rosemary) Flower/Leaf/Stem Extract, Ethylhexyl Palmitate, Oenothera Biennis (Evening Primrose) Root Extract, Abronia Villosa (Sand Verbena) Leaf Extract, Agave Americana (Agave) Stem Extract, Yucca Brevifolia (Joshua Tree) Root Extract, Opuntia Coccinellifera (Cholla Cactus) Flower Extract, Fouquieria Splendens (Ocotillo) Stem Extract, Larrea Tridentata (Creosote Bush) Extract, Lavandula Angustifolia (Lavender) Lavender oil, Pogostemon Cablin (Patchouli) Oil, Prunus Amygdalus Dulcis (Sweet Almond) Oil, Rosa Canina (Rosehip) Seed Oil, Vitis Vinifera (Grape) Seed Oil, Acacia Concinna (Shikakai) Fruit Extract, Emblica Officinalis (Amla) Fruit Extract, Mentha Piperita (Peppermint) Oil | BS54: kg | BU54: 31.75 | BV54: active
A55: =S55 -> CAM-OSLC-237 | B55: camille-rose-rosemary-oil-strengthening-leave-in-conditioner | C55: Camille Rose Rosemary Oil Strengthening Leave-In Conditioner | D55: <p><span>Say hello to new length retention and goodbye to weakened hair with the new Rosemary Collection from Camille Rose. </span></p><br> <p><span>Made with a blend of pure rosemary oil, a hint of peppermint, amla, apigenin, shikakai, and biotin, our vegan hair treats harness the power of beauty’s favourite ingredients to boost maximum hair strength in all textures.</span></p><br> <p><span>T</span>he result is a nourished scalp and unstoppable strands that need no introduction!</p> | E55: Camille Rose | F55: Health & Beauty > Personal Care > Hair Care | G55: Conditioner | H55: Ayurverdic, Ayurverdic leave in, BS2022, Camille Rose, Camille Rose Rosemary Oil, CG Approved, Colour Safe, Coloured Hair, Conditioner, Hair Growth, Hair Growth & Length Retention, Hair Growth Oil, High Porosity Essentials, Kid Safe, Natural, Natural Hair, Protein Free, Rapid Hair Growth, Rosemary, Rosemary Hair Mask, Strengthening Conditioner, strengthening moisturizer, Sulfate - Free | I55: TRUE | J55: Size | K55: 8 fl oz | S55: CAM-OSLC-237 | T55: 440 | U55: shopify | V55: deny | W55: manual | X55: 70 | Z55: TRUE | AA55: TRUE | AF55: 860006856571 | AG55: https://cdn.shopify.com/s/files/1/0504/5187/3989/files/CamilleRoseStrengtheningLeave-InConditioner.png?v=1692869356 | AH55: 1 | AI55: Camille Rose Rosemary Oil Strengthening Leave-In Conditioner | AJ55: FALSE | AL55: Powered by potent blend of rosemary pure Oil, a touch of Peppermint, this beauty product is formulated to treat and nourish hair from root to the tips. It makes the hair grows stronger and shine brighter. | AY55: Camille Rose Naturals is a trusted source for premium hair and beauty products formulated with gourmet ingredients to provide true nourishment to your strands.<br> <br> Each product is developed with integrity and hand crafted with love. Perfect for all hair types and textures. <br> | AZ55: Camille Rose | BA55: Apply evenly from root to tip on freshly cleansed and conditioned hair. <br> Style as usual. <br> May also be used to detangle and refresh styles on dry hair. | BB55: Glycerin, Propanediol, Olea Europaea (Olive) Fruit Oil, PEG-40 Hydrogenated Castor Oil, Rosmarinus Officinalis (Rosemary) Leaf Oil, Honey (Mel), Rosmarinus Officinalis (Rosemary) Flower/Leaf/Stem Extract, Water (Aqua), Lactic Acid, Glycolic Acid, Vaccinium Myrtillus Fruit Extract, Saccharum Officinarum (Sugarcane) Extract, Citric Acid, Citrus Aurantium Dulcis (Orange) Fruit Extract, Citrus Limon (Lemon) Fruit Extract, Acer Saccharum (Sugar Maple) Extract, Tartaric Acid, Malic Acid, Mentha Piperita (Peppermint) Oil, Phenoxyethanol, EthylhexylGLycerin, Chromium Oxide, Curcuma Longa (Turmeric) Root Extract, Spirulina Platensis Extract. | BN55: camille-rose-rosemary-oil-5-minute-strengthening-hair-mask; camille-rose-rosemary-oil-strengthening-hair-scalp-cleanser | BP55: only manual | BS55: kg | BU55: 36.7 | BV55: active
A56: =S56 -> CAM-O5SM-351 | B56: camille-rose-rosemary-oil-5-minute-strengthening-hair-mask | C56: Camille Rose Rosemary Oil 5 Minute Strengthening Hair Mask | D56: <p><span>Say hello to new length retention and goodbye to weakened hair with the new Rosemary Collection from Camille Rose. </span></p> <p><span>Made with a blend of pure rosemary oil, a hint of peppermint, amla, apigenin, shikakai, and biotin, our vegan hair treats harness the power of beauty’s favourite ingredients to boost maximum hair strength in all textures. </span></p><br> <p><span>T</span>he result is a nourished scalp and unstoppable strands that need no introduction!</p> | E56: Camille Rose | F56: Health & Beauty > Personal Care > Hair Care | G56: Conditioner | H56: Ayurverdic, BS2022, Camille Rose, Camille Rose Rosemary Oil, CG Approved, Colour Safe, Coloured Hair, Conditioner, Gentle Cleanser, Hair Growth, Hair Growth & Length Retention, Hair Growth Oil, Hair Mask, Kid Safe, Natural, Natural Hair, Protein Free, Rapid Hair Growth, Rosemary, Rosemary Hair Mask, Strengthening Conditioner, Strengthening Hair Mask, Sulfate - Free | I56: TRUE | J56: Size | K56: 8.5 fl oz | S56: CAM-O5SM-351 | T56: 540 | U56: shopify | V56: deny | W56: manual | X56: 75 | Z56: TRUE | AA56: TRUE | AF56: 860006856694 | AG56: https://cdn.shopify.com/s/files/1/0504/5187/3989/files/CamilleRose5MinuteStrengtheningHairMask.png?v=1692868140 | AH56: 1 | AI56: Camille Rose Rosemary Oil 5 Minute Strengthening Hair Mask | AJ56: FALSE | AL56: Deep condition in minutes with this protein-rich mask. Fortified to Strengthens brittle curls and reduces breakage using rosemary and peppermint oils. | AY56: Camille Rose Naturals is a trusted source for premium hair and beauty products formulated with gourmet ingredients to provide true nourishment to your strands.<br> <br> Each product is developed with integrity and hand crafted with love. Perfect for all hair types and textures. <br> | AZ56: Camille Rose | BA56: Apply a generous amount throughout freshly washed strands.<br> Use fingers or a wide tooth comb to distribute evenly from root to tip.<br> Leave on for up to 5 minutes before rinsing with cool water. <br> For best results, follow with Camille Rose Rosemary Strengthening leave-in. | BB56: Water (Aqua), Cetearyl Alcohol, Olea Europaea (Olive) Fruit Oil, Glycerin, Behentrimonium Methosulfate, Stearamidopropyl Dimethylamine, Ricinus Communis (Castor) Seed Oil, Cetrimonium Chloride, Rosmarinus Officinalis (Rosemary) Leaf Oil, Urtica Dioica (Nettle) Leaf Extract, Melissa Officinalis (Melissa) Leaf Extract, Mentha Piperita (Peppermint) Leaf Extract, Equisetum Arvense (Horsetail) Leaf Extract, Yucca Leaf Extract, Rosmarinus Officinalis (Rosemary) Flower/Leaf/Stem Extract, Mentha Piperita (Peppermint) Oil, Guar Hydroxypropyltrimonium Chloride, Hydrolyzed Wheat Protein, Phenoxyethanol, EthylhexylGLycerin, Citric Acid. | BN56: camille-rose-rosemary-oil-strengthening-hair-scalp-cleanser; camille-rose-rosemary-oil-strengthening-leave-in-conditioner | BP56: ahead | BS56: kg | BU56: 36.7 | BV56: active
A57: =S57 -> CAM-OSSC-351 | B57: camille-rose-rosemary-oil-strengthening-hair-scalp-cleanser | C57: Camille Rose Rosemary Oil Strengthening Hair & Scalp Cleanser | D57: <p><span>Say hello to new length retention and goodbye to weakened hair with the new Rosemary Collection from Camille Rose. </span></p> <p><span>Made with a blend of pure rosemary oil, a hint of peppermint, amla, apigenin, shikakai, and biotin, our vegan hair treats harness the power of beauty’s favourite ingredients to boost maximum hair strength in all textures. </span></p> <p><span>The result is a nourished scalp and unstoppable strands that need no introduction.</span></p> <p><strong> Ingredients:</strong> <span data-mce-fragment="1">Water (Aqua), C14-16 Alpha Olefin Sulfonate, Cetearyl Alcohol, Cocamidopropyl Betaine, Glyceryl Stearate, Behentrimonium Methosulfate, PEG-100 Stearate, Prunus Amygdalus Dulcis (Sweet Almond) Oil, Rosmarinus Officinalis (Rosemary) Leaf Oil, Urtica Dioica (Nettle) Leaf Extract, Melissa Officinalis (Melissa) Leaf Extract, Mentha Piperita (Peppermint) Leaf Extract, Equisetum Arvense (Horsetail) Leaf Extract, Yucca Leaf Extract, Rosmarinus Officinalis (Rosemary) Flower/Leaf/Stem Extract, Mentha Piperita (Peppermint) Oil, Guar Hydroxypropyltrimonium Chloride, Citrus Limon (Lemon) Peel Powder, Glycerin, Behenyl Behenate, Phenoxyethanol, EthylhexylGLycerin, Citric Acid.</span></p> <p><strong>Directions:</strong> <span data-mce-fragment="1">Apply to drenched strands throughout the length of hair. For thicker textures, section before applying to ensure every strand is penetrated. Using fingers or palms, massage to emulsify with water until hair and scalp are fully cleansed. Follow with Camille Rose Rosemary Oil 5-Minute Strengthening Hair Mask.</span></p> | E57: Camille Rose | F57: Health & Beauty > Personal Care > Hair Care | G57: Shampoo & Cleanser | H57: Ayurverdic, BS2022, Camille Rose, Camille Rose Rosemary Oil, CG Approved, Cleansing, Colour Safe, Coloured Hair, Curly Hair, Gentle Cleanser, Gentle Cleansing, Gentle Shampoo, Hair Growth, Hair Growth & Length Retention, Hair Growth Oil, Kid Safe, Natural, Natural Hair, Protein Free, Rapid Hair Growth, Rosemary, Shampoo, Sulfate - Free | I57: TRUE | J57: Size | K57: 8.5 fl oz | S57: CAM-OSSC-351 | T57: 540 | U57: shopify | V57: deny | W57: manual | X57: 70 | Z57: TRUE | AA57: TRUE | AF57: 860006856588 | AG57: https://cdn.shopify.com/s/files/1/0504/5187/3989/files/CamilleRoseStrengtheningHair_ScalpCleanser.png?v=1692867510 | AH57: 1 | AI57: Camille Rose Rosemary Oil Strengthening Hair & Scalp Cleanser | AJ57: FALSE | AL57: Gently cleanse while promoting hair growth. This rosemary oil shampoo removes buildup and strengthens curls without stripping. | BN57: camille-rose-rosemary-oil-5-minute-strengthening-hair-mask; camille-rose-rosemary-oil-strengthening-leave-in-conditioner | BP57: only manual | BS57: kg | BU57: 31.75 | BV57: active
A58: =S58 -> TRX-SRCDM-209 | B58: treluxe-soothe-restore-curl-defining-mousse | C58: TréLuxe Soothe & Restore Curl Defining Mousse | D58: <p>Whip your curls into shape with TréLuxe <strong>Soothe &amp; Restore</strong> <strong>Curl Defining Mousse</strong>. This non-drying, alcohol-free, foaming mousse, is formulated to <strong>define curls and waves without weighing them down, providing great hold and volume</strong>. </p><br> <p>The smooth, non-sticky, no-drip, foam consistency, is easy to distribute through waves, curls, and coils, for maximum styling versatility.</p> <br> <p>Can be used on dry or wet hair. Great for wash and go styling, curl refreshes, sleek bun-looks, and low-high manipulation styles.</p> <br> <p><strong>Key Ingredients: </strong><span>Oat Milk, Vitamin E, Bamboo Extract</span></p> | E58: Treluxe | F58: Uncategorized | G58: Styler | H58: CG Approved, Chemically Treated Hair, Colour Treated Hair, Coloured Hair, Curl defining mousse, Curl definition, Damaged Hair, Deep Moisture, Foam, Hair Strengthening, Mousse, protein free, SALE, Styler, Styling Mousse, Summer Curl Edit, Treluxe | I58: TRUE | J58: Size | K58: 7.1 oz | S58: TRX-SRCDM-209 | T58: 420 | U58: shopify | V58: deny | W58: manual | X58: 110 | Z58: TRUE | AA58: TRUE | AF58: 851533006096 | AG58: https://cdn.shopify.com/s/files/1/0504/5187/3989/files/TreLuxeSoothe_RestoreCurlDefiningMousse_1.png?v=1686037291 | AH58: 1 | AI58: TréLuxe Soothe & Restore Curl Defining Mousse | AJ58: FALSE | AL58: TréLuxe Soothe & Restore Curl Defining Mousse! This alcohol-free, non-drying foaming mousse delivers touchable hold, volume, and definition without weighing your hair down. The smooth, non-sticky, no-drip formula is easy to distribute through waves, curls, and coils, making it a go-to for both low- and high porosity hair styles. | AY58: TréLuxe products were created to solve the curly hair woes of dryness, frizz, weak strands, and dull hair using premium quality natural ingredients and Active Botanical blends that moisturize, strengthen, and define curly and wavy hair.<br> No parabens, No silicones, No phthalates, No sulfates, No artificial colors, Gluten-free, Cruelty-free | AZ58: TréLuxe | BA58: Dispense 1 to 2 full pumps of Soothe &amp; Restore Curl Defining Mousse into hands*, and distribute product evenly from roots to ends. <br><br> Use on wet hair for stronger hold and longer lasting definition. Can also be used on dry or damp hair to refresh curls. <br><br>*If 1-2 full pumps does not dispense enough mousse to distribute product throughout hair, and greater hold is desired, increase the number of full pumps used. | BB58: Water (Aqua), Polysorbate 20, Cocamidopropyl Betaine, PVP, VP/VA Copolymer, Aloe Barbadensis (Aloe Vera) Leaf Juice, Avena Sativa (Oat) Kernel Extract, Bambusa (Bamboo) Vulgaris Extract, Maltodextrin/VP Copolymer, Tocopheryl (Vitamin E) Acetate, Sodium Chloride, Squalane (olive derived), Guar Hydroxypropyltrimonium Chloride, Citric Acid, Laurtrimonium Chloride, Sodium Bisulfite, Glycerin, Butylene Glycol, Solanum Lycopersicum (Tomato) Fruit Extract, Potassium Sorbate, Sodium Benzoate, PPG-20 Methyl Glucose Ether, Ethylhexylglycerin, Parfum (Naturally-derived Fragrance), Hexyl Cinnamal ,Hydroxycitronellal , Limonene, Phenoxyethanol | BS58: kg | BU58: 43.86 | BV58: active
A59: =S59 -> MIE-BUCCM-210 | B59: mielle-babassu-brazilian-curly-cocktail-curl-mousse | C59: Mielle Brazilian Curly Cocktail Curl Mousse | D59: <p><span>A hair mousse with organic ingredients you won’t want to put down!</span></p><br> <p>Every curly-haired girl’s dream is to have soft, defined, frizz-free curls. With Mielle’s Brazilian Curly Cocktail Collection, you can finally make it a reality! This hair mousse blends certified organic ingredients like babassu, buriti buriti, muru muru, and copaiba oils for lasting hydration that locks moisture into curls while providing ultimate definition.</p><br> <p><strong>Key Benefits:</strong></p> <p>• Achieve healthy curl definition<br>• Contains a blend of organic Brazilian oils<br>• Made for dry and curly hair types<br>• No parabens, preservatives, or harmful chemicals</p><br> <p><strong>7.5 oz | Made with natural ingredients | Not tested on animals</strong></p> <p> </p> | E59: Mielle Organics | F59: Health & Beauty > Personal Care > Hair Care > Hair Styling Products | G59: Moisturizers & Leave - Ins | H59: All curl types, Brazilian Curly Cocktail, Curl Defining, Curl definition, Curl Enhancing, curls, Curly Hair, Frizz Free, Mielle, Mielle Organics, Mousse, Styler, Styling, Styling Mousse, Summer Curl Edit, Summer hero styler | I59: TRUE | J59: Size | K59: 7.5 oz | S59: MIE-BUCCM-210 | T59: 440 | U59: shopify | V59: deny | W59: manual | X59: 67 | Z59: TRUE | AA59: TRUE | AF59: 854102006299 | AG59: https://cdn.shopify.com/s/files/1/0504/5187/3989/products/MielleBabassuCurlyCocktailCurlMousse.png?v=1680277326 | AH59: 1 | AI59: Mielle Brazilian Curly Cocktail Curl Mousse | AJ59: FALSE | AL59: Mielle Brazilian Curly Cocktail Curl Mousse: A curly styling mousse that defines curls, provide long lasting hydration & fights frizz. Ideal for dry & curly types | AY59: Mielle Organics a natural haircare brand that delivers on its promises of healthier, stronger and more hydrated hair through use of organic ingredients, products have been uniquely formulated to deliver hydration, moisture and definition.<br> | AZ59: Mielle | BA59: After hair has been cleaned and is damp, divide into sections. Apply a liberal amount of the Mielle Brazilian Curl Cream to hair combing or fingering through from root to end.<br> <br> Immediately follow in the same section of hair with the Mielle Brazilian Cocktail Mousse. Follow the same pattern in each section of hair until completely done. Style hair as desired. | BB59: Water (Aqua, EAU), Polyquaternium-11, Cocamidopropyl Betaine, Phenoxyethanol, Panthenol, Oleth-20, PEG-75 Lanolin, Cetrimonium Chloride, Quaternium-80, Fragrance (Parfum), Hydrolyzed Wheat Protein, Organic Orbignya Oleifera (Babassu) Oil, Organic Mauritia Flexuosa (Buriti) Fruit Oil, Organic Copaiferi Officinalis (Balsam Copaiba) Resin, Organic Astrocaryum Murumuru Seed Butter, Benzoic Acid, Ethylhexylglycerine, Glycereth-2 Cocoate, Limonene, Linalool, Hexyl Cinnamal, Geraniol<br><br> All natural ingredients. no parabens, no drying alcohols, no harmful chemicals or preservatives.<br><br> *CERTIFIED ORGANIC INGREDIENTS | BG59: shiny | BI59: curly; wavy | BJ59: light | BK59: mousse | BL59: female | BS59: kg | BU59: 25.56 | BV59: active
